Workbook

Sheet Сводка
A1: Сравнение КП: где и на сколько нам снизили цены
A2: Исходное КП (наше) vs файл с правками заказчика. Все суммы в рублях без НДС; считаются формулами по листу «Все позиции».
A4: Главное
A5: Наше КП (исходное) | B5: =SUM('Все позиции'!$G$5:$G$331) -> 22665254
A6: Итог в файле заказчика (как у них посчитано) | B6: =SUM('Все позиции'!$J$5:$J$331) -> 16526808
A7: Ещё снижения в комментариях, не внесённые в их итог | B7: =SUM('Все позиции'!$M$5:$M$331)-SUM('Все позиции'!$J$5:$J$331) -> -452611.16
A8: Итог с учётом ВСЕХ правок заказчика | B8: =SUM('Все позиции'!$M$5:$M$331) -> 16074197
A9: Общее снижение против нашего КП, ₽ | B9: =B8-B5 -> -6591057
A10: Общее снижение, % | B10: =IF(B5=0,"",B9/B5) -> -0.29080005
A11: По разделам
A12: Раздел | B12: Наше КП, ₽ | C12: В файле заказчика, ₽ | D12: С учётом всех правок, ₽ | E12: Разница, ₽ | F12: Разница, %
A13: 1. Вентиляция | B13: =SUMIFS('Все позиции'!$G$5:$G$331,'Все позиции'!$A$5:$A$331,$A13) -> 3137546.9 | C13: =SUMIFS('Все позиции'!$J$5:$J$331,'Все позиции'!$A$5:$A$331,$A13) -> 3137546.9 | D13: =SUMIFS('Все позиции'!$M$5:$M$331,'Все позиции'!$A$5:$A$331,$A13) -> 3052972 | E13: =D13-B13 -> -84574.98 | F13: =IF(B13=0,"",E13/B13) -> -0.026955766
A14: 2. Кондиционирование | B14: =SUMIFS('Все позиции'!$G$5:$G$331,'Все позиции'!$A$5:$A$331,$A14) -> 9902752 | C14: =SUMIFS('Все позиции'!$J$5:$J$331,'Все позиции'!$A$5:$A$331,$A14) -> 8491752 | D14: =SUMIFS('Все позиции'!$M$5:$M$331,'Все позиции'!$A$5:$A$331,$A14) -> 8179752 | E14: =D14-B14 -> -1723000 | F14: =IF(B14=0,"",E14/B14) -> -0.17399204
A15: 3. Дополнительные работы 3,7,8,9 этаж | B15: =SUMIFS('Все позиции'!$G$5:$G$331,'Все позиции'!$A$5:$A$331,$A15) -> 1951684 | C15: =SUMIFS('Все позиции'!$J$5:$J$331,'Все позиции'!$A$5:$A$331,$A15) -> 1411914 | D15: =SUMIFS('Все позиции'!$M$5:$M$331,'Все позиции'!$A$5:$A$331,$A15) -> 1411914 | E15: =D15-B15 -> -539770 | F15: =IF(B15=0,"",E15/B15) -> -0.27656629
A16: 4. Вентиляция 10 этаж | B16: =SUMIFS('Все позиции'!$G$5:$G$331,'Все позиции'!$A$5:$A$331,$A16) -> 1416664.8 | C16: =SUMIFS('Все позиции'!$J$5:$J$331,'Все позиции'!$A$5:$A$331,$A16) -> 845451.58 | D16: =SUMIFS('Все позиции'!$M$5:$M$331,'Все позиции'!$A$5:$A$331,$A16) -> 845451.58 | E16: =D16-B16 -> -571213.22 | F16: =IF(B16=0,"",E16/B16) -> -0.40320986
A17: 4. Дымоудаление (10 этаж) | B17: =SUMIFS('Все позиции'!$G$5:$G$331,'Все позиции'!$A$5:$A$331,$A17) -> 253760 | C17: =SUMIFS('Все позиции'!$J$5:$J$331,'Все позиции'!$A$5:$A$331,$A17) -> 0 | D17: =SUMIFS('Все позиции'!$M$5:$M$331,'Все позиции'!$A$5:$A$331,$A17) -> 0 | E17: =D17-B17 -> -253760 | F17: =IF(B17=0,"",E17/B17) -> -1
A18: 5. Холодоснабжение 10 этаж | B18: =SUMIFS('Все позиции'!$G$5:$G$331,'Все позиции'!$A$5:$A$331,$A18) -> 1777290 | C18: =SUMIFS('Все позиции'!$J$5:$J$331,'Все позиции'!$A$5:$A$331,$A18) -> 1075964 | D18: =SUMIFS('Все позиции'!$M$5:$M$331,'Все позиции'!$A$5:$A$331,$A18) -> 1075964 | E18: =D18-B18 -> -701326 | F18: =IF(B18=0,"",E18/B18) -> -0.39460414
A19: 6. Вентиляция 2 этаж | B19: =SUMIFS('Все позиции'!$G$5:$G$331,'Все позиции'!$A$5:$A$331,$A19) -> 1563350.4 | C19: =SUMIFS('Все позиции'!$J$5:$J$331,'Все позиции'!$A$5:$A$331,$A19) -> 863491.78 | D19: =SUMIFS('Все позиции'!$M$5:$M$331,'Все позиции'!$A$5:$A$331,$A19) -> 815195.6 | E19: =D19-B19 -> -748154.8 | F19: =IF(B19=0,"",E19/B19) -> -0.47855861
A20: 6. Дымоудаление (2 этаж) | B20: =SUMIFS('Все позиции'!$G$5:$G$331,'Все позиции'!$A$5:$A$331,$A20) -> 774720 | C20: =SUMIFS('Все позиции'!$J$5:$J$331,'Все позиции'!$A$5:$A$331,$A20) -> 0 | D20: =SUMIFS('Все позиции'!$M$5:$M$331,'Все позиции'!$A$5:$A$331,$A20) -> 0 | E20: =D20-B20 -> -774720 | F20: =IF(B20=0,"",E20/B20) -> -1
A21: 7. Холодоснабжение 2 этаж | B21: =SUMIFS('Все позиции'!$G$5:$G$331,'Все позиции'!$A$5:$A$331,$A21) -> 1887486 | C21: =SUMIFS('Все позиции'!$J$5:$J$331,'Все позиции'!$A$5:$A$331,$A21) -> 700688 | D21: =SUMIFS('Все позиции'!$M$5:$M$331,'Все позиции'!$A$5:$A$331,$A21) -> 692948 | E21: =D21-B21 -> -1194538 | F21: =IF(B21=0,"",E21/B21) -> -0.63287251
A22: ИТОГО | B22: =SUM(B13:B21) -> 22665254 | C22: =SUM(C13:C21) -> 16526808 | D22: =SUM(D13:D21) -> 16074197 | E22: =SUM(E13:E21) -> -6591057 | F22: =IF(B22=0,"",E22/B22) -> -0.29080005
A24: Из-за чего снижение
A25: Что произошло | B25: Позиций | C25: Разница, ₽ | D25: Доля в общем снижении
A26: Цена снижена | B26: =COUNTIF('Все позиции'!$P$5:$P$331,A26) -> 175 | C26: =SUMIFS('Все позиции'!$N$5:$N$331,'Все позиции'!$P$5:$P$331,A26) -> -3881419.8 | D26: =IF($C$34=0,"",C26/$C$34) -> 0.58889186
A27: Снижены цена и количество | B27: =COUNTIF('Все позиции'!$P$5:$P$331,A27) -> 1 | C27: =SUMIFS('Все позиции'!$N$5:$N$331,'Все позиции'!$P$5:$P$331,A27) -> -78200 | D27: =IF($C$34=0,"",C27/$C$34) -> 0.011864561
A28: Удалено заказчиком без комментария | B28: =COUNTIF('Все позиции'!$P$5:$P$331,A28) -> 6 | C28: =SUMIFS('Все позиции'!$N$5:$N$331,'Все позиции'!$P$5:$P$331,A28) -> -1151370 | D28: =IF($C$34=0,"",C28/$C$34) -> 0.1746867
A29: Исключено → отдельный допник | B29: =COUNTIF('Все позиции'!$P$5:$P$331,A29) -> 8 | C29: =SUMIFS('Все позиции'!$N$5:$N$331,'Все позиции'!$P$5:$P$331,A29) -> -1028480 | D29: =IF($C$34=0,"",C29/$C$34) -> 0.15604174
A30: Снижение согласовано, но не внесено в итог | B30: =COUNTIF('Все позиции'!$P$5:$P$331,A30) -> 6 | C30: =SUMIFS('Все позиции'!$N$5:$N$331,'Все позиции'!$P$5:$P$331,A30) -> -404314.98 | D30: =IF($C$34=0,"",C30/$C$34) -> 0.061342965
A31: Снижение предложено, но не внесено в итог | B31: =COUNTIF('Все позиции'!$P$5:$P$331,A31) -> 3 | C31: =SUMIFS('Все позиции'!$N$5:$N$331,'Все позиции'!$P$5:$P$331,A31) -> -48296.18 | D31: =IF($C$34=0,"",C31/$C$34) -> 0.0073275318
A32: Цена повышена | B32: =COUNTIF('Все позиции'!$P$5:$P$331,A32) -> 3 | C32: =SUMIFS('Все позиции'!$N$5:$N$331,'Все позиции'!$P$5:$P$331,A32) -> 1024 | D32: =IF($C$34=0,"",C32/$C$34) -> -0.00015536203
A33: Без изменений | B33: =COUNTIF('Все позиции'!$P$5:$P$331,A33) -> 117 | C33: =SUMIFS('Все позиции'!$N$5:$N$331,'Все позиции'!$P$5:$P$331,A33) -> 0 | D33: =IF($C$34=0,"",C33/$C$34) -> 0
A34: ИТОГО | B34: =SUM(B26:B33) -> 319 | C34: =SUM(C26:C33) -> -6591057 | D34: =IF(C34=0,"",C34/C34) -> 1
A35: Проверка: итог по причинам = итогу по разделам → | C35: =IF(ABS(C34-E22)<0.01,"сходится","НЕ СХОДИТСЯ") -> сходится

Sheet Где занизили
A1: Позиции с изменениями — от самых больших потерь к меньшим
A2: Значения подтягиваются формулами с листа «Все позиции».
A3: Раздел | B3: № | C3: Наименование | D3: Ед. | E3: Кол-во наше | F3: Цена наша, ₽ | G3: Кол-во заказчика | H3: Итоговая цена, ₽ | I3: Изменение цены, % | J3: Сумма наша, ₽ | K3: Итоговая сумма, ₽ | L3: Разница, ₽ | M3: Что произошло | N3: Комментарий заказчика | O3: Ответ / согласование
A4: =IF('Все позиции'!A46="","",'Все позиции'!A46) -> 2. Кондиционирование | B4: =IF('Все позиции'!B46="","",'Все позиции'!B46) -> 2.7 | C4: =IF('Все позиции'!C46="","",'Все позиции'!C46) -> Узел регулирования климатической балки 1/2 Modulator ½ | D4: =IF('Все позиции'!D46="","",'Все позиции'!D46) -> шт. | E4: =IF('Все позиции'!E46="","",'Все позиции'!E46) -> 340 | F4: =IF('Все позиции'!F46="","",'Все позиции'!F46) -> 6650 | G4: =IF('Все позиции'!H46="","",'Все позиции'!H46) -> 340 | H4: =IF('Все позиции'!L46="","",'Все позиции'!L46) -> 2500 | I4: =IF('Все позиции'!O46="","",'Все позиции'!O46) -> -0.62406015 | J4: =IF('Все позиции'!G46="","",'Все позиции'!G46) -> 2261000 | K4: =IF('Все позиции'!M46="","",'Все позиции'!M46) -> 850000 | L4: =IF('Все позиции'!N46="","",'Все позиции'!N46) -> -1411000 | M4: =IF('Все позиции'!P46="","",'Все позиции'!P46) -> Цена снижена | N4: =IF('Все позиции'!Q46="","",'Все позиции'!Q46) -> по договоренности | O4: =IF('Все позиции'!R46="","",'Все позиции'!R46)
A5: =IF('Все позиции'!A321="","",'Все позиции'!A321) -> 7. Холодоснабжение 2 этаж | B5: =IF('Все позиции'!B321="","",'Все позиции'!B321) -> 7.1 | C5: =IF('Все позиции'!C321="","",'Все позиции'!C321) -> Фанкойл кассетный, 600x600 SK-12 | D5: =IF('Все позиции'!D321="","",'Все позиции'!D321) -> шт. | E5: =IF('Все позиции'!E321="","",'Все позиции'!E321) -> 31 | F5: =IF('Все позиции'!F321="","",'Все позиции'!F321) -> 29160 | G5: =IF('Все позиции'!H321="","",'Все позиции'!H321) -> 31 | H5: =IF('Все позиции'!L321="","",'Все позиции'!L321) -> 14000 | I5: =IF('Все позиции'!O321="","",'Все позиции'!O321) -> -0.51989026 | J5: =IF('Все позиции'!G321="","",'Все позиции'!G321) -> 903960 | K5: =IF('Все позиции'!M321="","",'Все позиции'!M321) -> 434000 | L5: =IF('Все позиции'!N321="","",'Все позиции'!N321) -> -469960 | M5: =IF('Все позиции'!P321="","",'Все позиции'!P321) -> Цена снижена | N5: =IF('Все позиции'!Q321="","",'Все позиции'!Q321) | O5: =IF('Все позиции'!R321="","",'Все позиции'!R321)
A6: =IF('Все позиции'!A316="","",'Все позиции'!A316) -> 6. Дымоудаление (2 этаж) | B6: =IF('Все позиции'!B316="","",'Все позиции'!B316) -> 6.75 | C6: =IF('Все позиции'!C316="","",'Все позиции'!C316) -> Воздуховод 800*500 | D6: =IF('Все позиции'!D316="","",'Все позиции'!D316) -> м2 | E6: =IF('Все позиции'!E316="","",'Все позиции'!E316) -> 168 | F6: =IF('Все позиции'!F316="","",'Все позиции'!F316) -> 2560 | G6: =IF('Все позиции'!H316="","",'Все позиции'!H316) -> 168 | H6: =IF('Все позиции'!L316="","",'Все позиции'!L316) | I6: =IF('Все позиции'!O316="","",'Все позиции'!O316) -> -1 | J6: =IF('Все позиции'!G316="","",'Все позиции'!G316) -> 430080 | K6: =IF('Все позиции'!M316="","",'Все позиции'!M316) -> 0 | L6: =IF('Все позиции'!N316="","",'Все позиции'!N316) -> -430080 | M6: =IF('Все позиции'!P316="","",'Все позиции'!P316) -> Исключено → отдельный допник | N6: =IF('Все позиции'!Q316="","",'Все позиции'!Q316) -> удалить (если будут данные позиции сделаем отдельный допник) | O6: =IF('Все позиции'!R316="","",'Все позиции'!R316)
A7: =IF('Все позиции'!A311="","",'Все позиции'!A311) -> 6. Вентиляция 2 этаж | B7: =IF('Все позиции'!B311="","",'Все позиции'!B311) -> 6.71 | C7: =IF('Все позиции'!C311="","",'Все позиции'!C311) -> демонтаж воздуховодов | D7: =IF('Все позиции'!D311="","",'Все позиции'!D311) -> к-т | E7: =IF('Все позиции'!E311="","",'Все позиции'!E311) -> 1 | F7: =IF('Все позиции'!F311="","",'Все позиции'!F311) -> 388800 | G7: =IF('Все позиции'!H311="","",'Все позиции'!H311) -> 0 | H7: =IF('Все позиции'!L311="","",'Все позиции'!L311) | I7: =IF('Все позиции'!O311="","",'Все позиции'!O311) -> -1 | J7: =IF('Все позиции'!G311="","",'Все позиции'!G311) -> 388800 | K7: =IF('Все позиции'!M311="","",'Все позиции'!M311) -> 0 | L7: =IF('Все позиции'!N311="","",'Все позиции'!N311) -> -388800 | M7: =IF('Все позиции'!P311="","",'Все позиции'!P311) -> Удалено заказчиком без комментария | N7: =IF('Все позиции'!Q311="","",'Все позиции'!Q311) | O7: =IF('Все позиции'!R311="","",'Все позиции'!R311)
A8: =IF('Все позиции'!A89="","",'Все позиции'!A89) -> 3. Дополнительные работы 3,7,8,9 этаж | B8: =IF('Все позиции'!B89="","",'Все позиции'!B89) -> 3.7 | C8: =IF('Все позиции'!C89="","",'Все позиции'!C89) -> Изоляция изделий (отводы, тройники, переходы, клапана) | D8: =IF('Все позиции'!D89="","",'Все позиции'!D89) -> шт. | E8: =IF('Все позиции'!E89="","",'Все позиции'!E89) -> 1195 | F8: =IF('Все позиции'!F89="","",'Все позиции'!F89) -> 840 | G8: =IF('Все позиции'!H89="","",'Все позиции'!H89) -> 1195 | H8: =IF('Все позиции'!L89="","",'Все позиции'!L89) -> 570 | I8: =IF('Все позиции'!O89="","",'Все позиции'!O89) -> -0.32142857 | J8: =IF('Все позиции'!G89="","",'Все позиции'!G89) -> 1003800 | K8: =IF('Все позиции'!M89="","",'Все позиции'!M89) -> 681150 | L8: =IF('Все позиции'!N89="","",'Все позиции'!N89) -> -322650 | M8: =IF('Все позиции'!P89="","",'Все позиции'!P89) -> Цена снижена | N8: =IF('Все позиции'!Q89="","",'Все позиции'!Q89) | O8: =IF('Все позиции'!R89="","",'Все позиции'!R89)
A9: =IF('Все позиции'!A317="","",'Все позиции'!A317) -> 6. Дымоудаление (2 этаж) | B9: =IF('Все позиции'!B317="","",'Все позиции'!B317) -> 6.76 | C9: =IF('Все позиции'!C317="","",'Все позиции'!C317) -> Изоляция М-БОР | D9: =IF('Все позиции'!D317="","",'Все позиции'!D317) -> м2 | E9: =IF('Все позиции'!E317="","",'Все позиции'!E317) -> 186 | F9: =IF('Все позиции'!F317="","",'Все позиции'!F317) -> 1440 | G9: =IF('Все позиции'!H317="","",'Все позиции'!H317) -> 186 | H9: =IF('Все позиции'!L317="","",'Все позиции'!L317) | I9: =IF('Все позиции'!O317="","",'Все позиции'!O317) -> -1 | J9: =IF('Все позиции'!G317="","",'Все позиции'!G317) -> 267840 | K9: =IF('Все позиции'!M317="","",'Все позиции'!M317) -> 0 | L9: =IF('Все позиции'!N317="","",'Все позиции'!N317) -> -267840 | M9: =IF('Все позиции'!P317="","",'Все позиции'!P317) -> Исключено → отдельный допник | N9: =IF('Все позиции'!Q317="","",'Все позиции'!Q317) -> удалить (если будут данные позиции сделаем отдельный допник) | O9: =IF('Все позиции'!R317="","",'Все позиции'!R317)
A10: =IF('Все позиции'!A328="","",'Все позиции'!A328) -> 7. Холодоснабжение 2 этаж | B10: =IF('Все позиции'!B328="","",'Все позиции'!B328) -> 7.8 | C10: =IF('Все позиции'!C328="","",'Все позиции'!C328) -> дренаж | D10: =IF('Все позиции'!D328="","",'Все позиции'!D328) -> м.п. | E10: =IF('Все позиции'!E328="","",'Все позиции'!E328) -> 200 | F10: =IF('Все позиции'!F328="","",'Все позиции'!F328) -> 1092 | G10: =IF('Все позиции'!H328="","",'Все позиции'!H328) -> 0 | H10: =IF('Все позиции'!L328="","",'Все позиции'!L328) | I10: =IF('Все позиции'!O328="","",'Все позиции'!O328) -> -1 | J10: =IF('Все позиции'!G328="","",'Все позиции'!G328) -> 218400 | K10: =IF('Все позиции'!M328="","",'Все позиции'!M328) -> 0 | L10: =IF('Все позиции'!N328="","",'Все позиции'!N328) -> -218400 | M10: =IF('Все позиции'!P328="","",'Все позиции'!P328) -> Удалено заказчиком без комментария | N10: =IF('Все позиции'!Q328="","",'Все позиции'!Q328) | O10: =IF('Все позиции'!R328="","",'Все позиции'!R328)
A11: =IF('Все позиции'!A194="","",'Все позиции'!A194) -> 4. Вентиляция 10 этаж | B11: =IF('Все позиции'!B194="","",'Все позиции'!B194) -> 4.81 | C11: =IF('Все позиции'!C194="","",'Все позиции'!C194) -> Изоляция прямоугольного изделия | D11: =IF('Все позиции'!D194="","",'Все позиции'!D194) -> шт. | E11: =IF('Все позиции'!E194="","",'Все позиции'!E194) -> 80 | F11: =IF('Все позиции'!F194="","",'Все позиции'!F194) -> 3240 | G11: =IF('Все позиции'!H194="","",'Все позиции'!H194) -> 80 | H11: =IF('Все позиции'!L194="","",'Все позиции'!L194) -> 665 | I11: =IF('Все позиции'!O194="","",'Все позиции'!O194) -> -0.79475309 | J11: =IF('Все позиции'!G194="","",'Все позиции'!G194) -> 259200 | K11: =IF('Все позиции'!M194="","",'Все позиции'!M194) -> 53200 | L11: =IF('Все позиции'!N194="","",'Все позиции'!N194) -> -206000 | M11: =IF('Все позиции'!P194="","",'Все позиции'!P194) -> Цена снижена | N11: =IF('Все позиции'!Q194="","",'Все позиции'!Q194) -> за м2 а не за штуку | O11: =IF('Все позиции'!R194="","",'Все позиции'!R194)
A12: =IF('Все позиции'!A322="","",'Все позиции'!A322) -> 7. Холодоснабжение 2 этаж | B12: =IF('Все позиции'!B322="","",'Все позиции'!B322) -> 7.2 | C12: =IF('Все позиции'!C322="","",'Все позиции'!C322) -> Подключение фанкойлов в радиусе 2,5 м | D12: =IF('Все позиции'!D322="","",'Все позиции'!D322) -> шт. | E12: =IF('Все позиции'!E322="","",'Все позиции'!E322) -> 31 | F12: =IF('Все позиции'!F322="","",'Все позиции'!F322) -> 5670 | G12: =IF('Все позиции'!H322="","",'Все позиции'!H322) -> 0 | H12: =IF('Все позиции'!L322="","",'Все позиции'!L322) | I12: =IF('Все позиции'!O322="","",'Все позиции'!O322) -> -1 | J12: =IF('Все позиции'!G322="","",'Все позиции'!G322) -> 175770 | K12: =IF('Все позиции'!M322="","",'Все позиции'!M322) -> 0 | L12: =IF('Все позиции'!N322="","",'Все позиции'!N322) -> -175770 | M12: =IF('Все позиции'!P322="","",'Все позиции'!P322) -> Удалено заказчиком без комментария | N12: =IF('Все позиции'!Q322="","",'Все позиции'!Q322) | O12: =IF('Все позиции'!R322="","",'Все позиции'!R322)
A13: =IF('Все позиции'!A329="","",'Все позиции'!A329) -> 7. Холодоснабжение 2 этаж | B13: =IF('Все позиции'!B329="","",'Все позиции'!B329) -> 7.9 | C13: =IF('Все позиции'!C329="","",'Все позиции'!C329) -> демонтаж холодоснабжения | D13: =IF('Все позиции'!D329="","",'Все позиции'!D329) -> к-т | E13: =IF('Все позиции'!E329="","",'Все позиции'!E329) -> 1 | F13: =IF('Все позиции'!F329="","",'Все позиции'!F329) -> 162000 | G13: =IF('Все позиции'!H329="","",'Все позиции'!H329) -> 0 | H13: =IF('Все позиции'!L329="","",'Все позиции'!L329) | I13: =IF('Все позиции'!O329="","",'Все позиции'!O329) -> -1 | J13: =IF('Все позиции'!G329="","",'Все позиции'!G329) -> 162000 | K13: =IF('Все позиции'!M329="","",'Все позиции'!M329) -> 0 | L13: =IF('Все позиции'!N329="","",'Все позиции'!N329) -> -162000 | M13: =IF('Все позиции'!P329="","",'Все позиции'!P329) -> Удалено заказчиком без комментария | N13: =IF('Все позиции'!Q329="","",'Все позиции'!Q329) | O13: =IF('Все позиции'!R329="","",'Все позиции'!R329)
A14: =IF('Все позиции'!A199="","",'Все позиции'!A199) -> 4. Дымоудаление (10 этаж) | B14: =IF('Все позиции'!B199="","",'Все позиции'!B199) -> 4.85 | C14: =IF('Все позиции'!C199="","",'Все позиции'!C199) -> Воздуховод 800*500 | D14: =IF('Все позиции'!D199="","",'Все позиции'!D199) -> м2 | E14: =IF('Все позиции'!E199="","",'Все позиции'!E199) -> 52 | F14: =IF('Все позиции'!F199="","",'Все позиции'!F199) -> 2560 | G14: =IF('Все позиции'!H199="","",'Все позиции'!H199) -> 52 | H14: =IF('Все позиции'!L199="","",'Все позиции'!L199) | I14: =IF('Все позиции'!O199="","",'Все позиции'!O199) -> -1 | J14: =IF('Все позиции'!G199="","",'Все позиции'!G199) -> 133120 | K14: =IF('Все позиции'!M199="","",'Все позиции'!M199) -> 0 | L14: =IF('Все позиции'!N199="","",'Все позиции'!N199) -> -133120 | M14: =IF('Все позиции'!P199="","",'Все позиции'!P199) -> Исключено → отдельный допник | N14: =IF('Все позиции'!Q199="","",'Все позиции'!Q199) -> удалить (если будут данные позиции сделаем отдельный допник) | O14: =IF('Все позиции'!R199="","",'Все позиции'!R199)
A15: =IF('Все позиции'!A48="","",'Все позиции'!A48) -> 2. Кондиционирование | B15: =IF('Все позиции'!B48="","",'Все позиции'!B48) -> 2.9 | C15: =IF('Все позиции'!C48="","",'Все позиции'!C48) -> Трубопровод из полимерных труб РЕХ-а, Дн25х3.5 REHAU Rautitan Flex 11303701006 | D15: =IF('Все позиции'!D48="","",'Все позиции'!D48) -> м.п. | E15: =IF('Все позиции'!E48="","",'Все позиции'!E48) -> 1280 | F15: =IF('Все позиции'!F48="","",'Все позиции'!F48) -> 500 | G15: =IF('Все позиции'!H48="","",'Все позиции'!H48) -> 1280 | H15: =IF('Все позиции'!L48="","",'Все позиции'!L48) -> 400 | I15: =IF('Все позиции'!O48="","",'Все позиции'!O48) -> -0.2 | J15: =IF('Все позиции'!G48="","",'Все позиции'!G48) -> 640000 | K15: =IF('Все позиции'!M48="","",'Все позиции'!M48) -> 512000 | L15: =IF('Все позиции'!N48="","",'Все позиции'!N48) -> -128000 | M15: =IF('Все позиции'!P48="","",'Все позиции'!P48) -> Снижение согласовано, но не внесено в итог | N15: =IF('Все позиции'!Q48="","",'Все позиции'!Q48) -> по договру | O15: =IF('Все позиции'!R48="","",'Все позиции'!R48) -> Цена Согласована Марк
A16: =IF('Все позиции'!A204="","",'Все позиции'!A204) -> 5. Холодоснабжение 10 этаж | B16: =IF('Все позиции'!B204="","",'Все позиции'!B204) -> 5.1 | C16: =IF('Все позиции'!C204="","",'Все позиции'!C204) -> Фанкойл кассетный, 600x600 SK-32 | D16: =IF('Все позиции'!D204="","",'Все позиции'!D204) -> шт. | E16: =IF('Все позиции'!E204="","",'Все позиции'!E204) -> 10 | F16: =IF('Все позиции'!F204="","",'Все позиции'!F204) -> 25920 | G16: =IF('Все позиции'!H204="","",'Все позиции'!H204) -> 10 | H16: =IF('Все позиции'!L204="","",'Все позиции'!L204) -> 14000 | I16: =IF('Все позиции'!O204="","",'Все позиции'!O204) -> -0.45987654 | J16: =IF('Все позиции'!G204="","",'Все позиции'!G204) -> 259200 | K16: =IF('Все позиции'!M204="","",'Все позиции'!M204) -> 140000 | L16: =IF('Все позиции'!N204="","",'Все позиции'!N204) -> -119200 | M16: =IF('Все позиции'!P204="","",'Все позиции'!P204) -> Цена снижена | N16: =IF('Все позиции'!Q204="","",'Все позиции'!Q204) -> в чем разница в 2,5раза от балок? | O16: =IF('Все позиции'!R204="","",'Все позиции'!R204)
A17: =IF('Все позиции'!A238="","",'Все позиции'!A238) -> 5. Холодоснабжение 10 этаж | B17: =IF('Все позиции'!B238="","",'Все позиции'!B238) -> 5.35 | C17: =IF('Все позиции'!C238="","",'Все позиции'!C238) -> Дренаж | D17: =IF('Все позиции'!D238="","",'Все позиции'!D238) -> мп | E17: =IF('Все позиции'!E238="","",'Все позиции'!E238) -> 100 | F17: =IF('Все позиции'!F238="","",'Все позиции'!F238) -> 1092 | G17: =IF('Все позиции'!H238="","",'Все позиции'!H238) -> 0 | H17: =IF('Все позиции'!L238="","",'Все позиции'!L238) | I17: =IF('Все позиции'!O238="","",'Все позиции'!O238) -> -1 | J17: =IF('Все позиции'!G238="","",'Все позиции'!G238) -> 109200 | K17: =IF('Все позиции'!M238="","",'Все позиции'!M238) -> 0 | L17: =IF('Все позиции'!N238="","",'Все позиции'!N238) -> -109200 | M17: =IF('Все позиции'!P238="","",'Все позиции'!P238) -> Удалено заказчиком без комментария | N17: =IF('Все позиции'!Q238="","",'Все позиции'!Q238) | O17: =IF('Все позиции'!R238="","",'Все позиции'!R238)
A18: =IF('Все позиции'!A330="","",'Все позиции'!A330) -> 7. Холодоснабжение 2 этаж | B18: =IF('Все позиции'!B330="","",'Все позиции'!B330) -> 7.10 | C18: =IF('Все позиции'!C330="","",'Все позиции'!C330) -> демонтаж дренажной системы | D18: =IF('Все позиции'!D330="","",'Все позиции'!D330) -> к-т | E18: =IF('Все позиции'!E330="","",'Все позиции'!E330) -> 1 | F18: =IF('Все позиции'!F330="","",'Все позиции'!F330) -> 97200 | G18: =IF('Все позиции'!H330="","",'Все позиции'!H330) -> 0 | H18: =IF('Все позиции'!L330="","",'Все позиции'!L330) | I18: =IF('Все позиции'!O330="","",'Все позиции'!O330) -> -1 | J18: =IF('Все позиции'!G330="","",'Все позиции'!G330) -> 97200 | K18: =IF('Все позиции'!M330="","",'Все позиции'!M330) -> 0 | L18: =IF('Все позиции'!N330="","",'Все позиции'!N330) -> -97200 | M18: =IF('Все позиции'!P330="","",'Все позиции'!P330) -> Удалено заказчиком без комментария | N18: =IF('Все позиции'!Q330="","",'Все позиции'!Q330) | O18: =IF('Все позиции'!R330="","",'Все позиции'!R330)
A19: =IF('Все позиции'!A95="","",'Все позиции'!A95) -> 3. Дополнительные работы 3,7,8,9 этаж | B19: =IF('Все позиции'!B95="","",'Все позиции'!B95) -> 3.13 | C19: =IF('Все позиции'!C95="","",'Все позиции'!C95) -> Перемонтаж щелевых диффузоров | D19: =IF('Все позиции'!D95="","",'Все позиции'!D95) -> к-т | E19: =IF('Все позиции'!E95="","",'Все позиции'!E95) -> 8 | F19: =IF('Все позиции'!F95="","",'Все позиции'!F95) -> 16800 | G19: =IF('Все позиции'!H95="","",'Все позиции'!H95) -> 8 | H19: =IF('Все позиции'!L95="","",'Все позиции'!L95) -> 4800 | I19: =IF('Все позиции'!O95="","",'Все позиции'!O95) -> -0.71428571 | J19: =IF('Все позиции'!G95="","",'Все позиции'!G95) -> 134400 | K19: =IF('Все позиции'!M95="","",'Все позиции'!M95) -> 38400 | L19: =IF('Все позиции'!N95="","",'Все позиции'!N95) -> -96000 | M19: =IF('Все позиции'!P95="","",'Все позиции'!P95) -> Цена снижена | N19: =IF('Все позиции'!Q95="","",'Все позиции'!Q95) -> сильно завышено, что за диффузоры? С КСД? Размер? | O19: =IF('Все позиции'!R95="","",'Все позиции'!R95) -> Демонтаж - монтаж щелевого диффузора. Поставь цену сама
A20: =IF('Все позиции'!A200="","",'Все позиции'!A200) -> 4. Дымоудаление (10 этаж) | B20: =IF('Все позиции'!B200="","",'Все позиции'!B200) -> 4.86 | C20: =IF('Все позиции'!C200="","",'Все позиции'!C200) -> Изоляция М-БОР | D20: =IF('Все позиции'!D200="","",'Все позиции'!D200) -> м2 | E20: =IF('Все позиции'!E200="","",'Все позиции'!E200) -> 66 | F20: =IF('Все позиции'!F200="","",'Все позиции'!F200) -> 1440 | G20: =IF('Все позиции'!H200="","",'Все позиции'!H200) -> 66 | H20: =IF('Все позиции'!L200="","",'Все позиции'!L200) | I20: =IF('Все позиции'!O200="","",'Все позиции'!O200) -> -1 | J20: =IF('Все позиции'!G200="","",'Все позиции'!G200) -> 95040 | K20: =IF('Все позиции'!M200="","",'Все позиции'!M200) -> 0 | L20: =IF('Все позиции'!N200="","",'Все позиции'!N200) -> -95040 | M20: =IF('Все позиции'!P200="","",'Все позиции'!P200) -> Исключено → отдельный допник | N20: =IF('Все позиции'!Q200="","",'Все позиции'!Q200) -> удалить (если будут данные позиции сделаем отдельный допник) | O20: =IF('Все позиции'!R200="","",'Все позиции'!R200)
A21: =IF('Все позиции'!A37="","",'Все позиции'!A37) -> 1. Вентиляция | B21: =IF('Все позиции'!B37="","",'Все позиции'!B37) -> 1.33 | C21: =IF('Все позиции'!C37="","",'Все позиции'!C37) -> Универсальная теплоизоляция в виде рулонов, толщиной 6 мм K- Flex-ST | D21: =IF('Все позиции'!D37="","",'Все позиции'!D37) -> м2 | E21: =IF('Все позиции'!E37="","",'Все позиции'!E37) -> 882 | F21: =IF('Все позиции'!F37="","",'Все позиции'!F37) -> 665.89 | G21: =IF('Все позиции'!H37="","",'Все позиции'!H37) -> 882 | H21: =IF('Все позиции'!L37="","",'Все позиции'!L37) -> 570 | I21: =IF('Все позиции'!O37="","",'Все позиции'!O37) -> -0.14400276 | J21: =IF('Все позиции'!G37="","",'Все позиции'!G37) -> 587314.98 | K21: =IF('Все позиции'!M37="","",'Все позиции'!M37) -> 502740 | L21: =IF('Все позиции'!N37="","",'Все позиции'!N37) -> -84574.98 | M21: =IF('Все позиции'!P37="","",'Все позиции'!P37) -> Снижение согласовано, но не внесено в итог | N21: =IF('Все позиции'!Q37="","",'Все позиции'!Q37) -> р по договору | O21: =IF('Все позиции'!R37="","",'Все позиции'!R37) -> Цена Согласована Марк
A22: =IF('Все позиции'!A49="","",'Все позиции'!A49) -> 2. Кондиционирование | B22: =IF('Все позиции'!B49="","",'Все позиции'!B49) -> 2.10 | C22: =IF('Все позиции'!C49="","",'Все позиции'!C49) -> Трубопровод из полимерных труб РЕХ-а, Дн32х3.5 REHAU Rautitan Flex | D22: =IF('Все позиции'!D49="","",'Все позиции'!D49) -> м.п. | E22: =IF('Все позиции'!E49="","",'Все позиции'!E49) -> 800 | F22: =IF('Все позиции'!F49="","",'Все позиции'!F49) -> 500 | G22: =IF('Все позиции'!H49="","",'Все позиции'!H49) -> 800 | H22: =IF('Все позиции'!L49="","",'Все позиции'!L49) -> 400 | I22: =IF('Все позиции'!O49="","",'Все позиции'!O49) -> -0.2 | J22: =IF('Все позиции'!G49="","",'Все позиции'!G49) -> 400000 | K22: =IF('Все позиции'!M49="","",'Все позиции'!M49) -> 320000 | L22: =IF('Все позиции'!N49="","",'Все позиции'!N49) -> -80000 | M22: =IF('Все позиции'!P49="","",'Все позиции'!P49) -> Снижение согласовано, но не внесено в итог | N22: =IF('Все позиции'!Q49="","",'Все позиции'!Q49) -> по договру | O22: =IF('Все позиции'!R49="","",'Все позиции'!R49) -> Цена Согласована Марк
A23: =IF('Все позиции'!A91="","",'Все позиции'!A91) -> 3. Дополнительные работы 3,7,8,9 этаж | B23: =IF('Все позиции'!B91="","",'Все позиции'!B91) -> 3.9 | C23: =IF('Все позиции'!C91="","",'Все позиции'!C91) -> Монтаж пожарного клапана | D23: =IF('Все позиции'!D91="","",'Все позиции'!D91) -> к-т | E23: =IF('Все позиции'!E91="","",'Все позиции'!E91) -> 4 | F23: =IF('Все позиции'!F91="","",'Все позиции'!F91) -> 21000 | G23: =IF('Все позиции'!H91="","",'Все позиции'!H91) -> 2 | H23: =IF('Все позиции'!L91="","",'Все позиции'!L91) -> 2900 | I23: =IF('Все позиции'!O91="","",'Все позиции'!O91) -> -0.86190476 | J23: =IF('Все позиции'!G91="","",'Все позиции'!G91) -> 84000 | K23: =IF('Все позиции'!M91="","",'Все позиции'!M91) -> 5800 | L23: =IF('Все позиции'!N91="","",'Все позиции'!N91) -> -78200 | M23: =IF('Все позиции'!P91="","",'Все позиции'!P91) -> Снижены цена и количество | N23: =IF('Все позиции'!Q91="","",'Все позиции'!Q91) -> сильно завышена расценка | O23: =IF('Все позиции'!R91="","",'Все позиции'!R91)
A24: =IF('Все позиции'!A197="","",'Все позиции'!A197) -> 4. Вентиляция 10 этаж | B24: =IF('Все позиции'!B197="","",'Все позиции'!B197) -> 4.84 | C24: =IF('Все позиции'!C197="","",'Все позиции'!C197) -> ПНР10этаж | D24: =IF('Все позиции'!D197="","",'Все позиции'!D197) -> к-т | E24: =IF('Все позиции'!E197="","",'Все позиции'!E197) -> 1 | F24: =IF('Все позиции'!F197="","",'Все позиции'!F197) -> 162000 | G24: =IF('Все позиции'!H197="","",'Все позиции'!H197) -> 1 | H24: =IF('Все позиции'!L197="","",'Все позиции'!L197) -> 95000 | I24: =IF('Все позиции'!O197="","",'Все позиции'!O197) -> -0.41358025 | J24: =IF('Все позиции'!G197="","",'Все позиции'!G197) -> 162000 | K24: =IF('Все позиции'!M197="","",'Все позиции'!M197) -> 95000 | L24: =IF('Все позиции'!N197="","",'Все позиции'!N197) -> -67000 | M24: =IF('Все позиции'!P197="","",'Все позиции'!P197) -> Цена снижена | N24: =IF('Все позиции'!Q197="","",'Все позиции'!Q197) -> по тип.эт | O24: =IF('Все позиции'!R197="","",'Все позиции'!R197)
A25: =IF('Все позиции'!A314="","",'Все позиции'!A314) -> 6. Вентиляция 2 этаж | B25: =IF('Все позиции'!B314="","",'Все позиции'!B314) -> 6.74 | C25: =IF('Все позиции'!C314="","",'Все позиции'!C314) -> ПНР 2й этаж | D25: =IF('Все позиции'!D314="","",'Все позиции'!D314) -> к-т | E25: =IF('Все позиции'!E314="","",'Все позиции'!E314) -> 1 | F25: =IF('Все позиции'!F314="","",'Все позиции'!F314) -> 162000 | G25: =IF('Все позиции'!H314="","",'Все позиции'!H314) -> 1 | H25: =IF('Все позиции'!L314="","",'Все позиции'!L314) -> 95000 | I25: =IF('Все позиции'!O314="","",'Все позиции'!O314) -> -0.41358025 | J25: =IF('Все позиции'!G314="","",'Все позиции'!G314) -> 162000 | K25: =IF('Все позиции'!M314="","",'Все позиции'!M314) -> 95000 | L25: =IF('Все позиции'!N314="","",'Все позиции'!N314) -> -67000 | M25: =IF('Все позиции'!P314="","",'Все позиции'!P314) -> Цена снижена | N25: =IF('Все позиции'!Q314="","",'Все позиции'!Q314) -> по тип.эт | O25: =IF('Все позиции'!R314="","",'Все позиции'!R314)
A26: =IF('Все позиции'!A76="","",'Все позиции'!A76) -> 2. Кондиционирование | B26: =IF('Все позиции'!B76="","",'Все позиции'!B76) -> 2.37 | C26: =IF('Все позиции'!C76="","",'Все позиции'!C76) -> Тепловая изоляция из вспененного каучука, толщиной 9 мм Armaflex АСЕ 28*13 | D26: =IF('Все позиции'!D76="","",'Все позиции'!D76) -> м.п. | E26: =IF('Все позиции'!E76="","",'Все позиции'!E76) -> 1280 | F26: =IF('Все позиции'!F76="","",'Все позиции'!F76) -> 200 | G26: =IF('Все позиции'!H76="","",'Все позиции'!H76) -> 1280 | H26: =IF('Все позиции'!L76="","",'Все позиции'!L76) -> 150 | I26: =IF('Все позиции'!O76="","",'Все позиции'!O76) -> -0.25 | J26: =IF('Все позиции'!G76="","",'Все позиции'!G76) -> 256000 | K26: =IF('Все позиции'!M76="","",'Все позиции'!M76) -> 192000 | L26: =IF('Все позиции'!N76="","",'Все позиции'!N76) -> -64000 | M26: =IF('Все позиции'!P76="","",'Все позиции'!P76) -> Снижение согласовано, но не внесено в итог | N26: =IF('Все позиции'!Q76="","",'Все позиции'!Q76) -> по договору | O26: =IF('Все позиции'!R76="","",'Все позиции'!R76) -> Цена Согласована Марк
A27: =IF('Все позиции'!A236="","",'Все позиции'!A236) -> 5. Холодоснабжение 10 этаж | B27: =IF('Все позиции'!B236="","",'Все позиции'!B236) -> 5.33 | C27: =IF('Все позиции'!C236="","",'Все позиции'!C236) -> Трубки теплоизоляционные для трубы Ø32х5,4 толщиной 6мм | D27: =IF('Все позиции'!D236="","",'Все позиции'!D236) -> шт. | E27: =IF('Все позиции'!E236="","",'Все позиции'!E236) -> 75 | F27: =IF('Все позиции'!F236="","",'Все позиции'!F236) -> 1020 | G27: =IF('Все позиции'!H236="","",'Все позиции'!H236) -> 75 | H27: =IF('Все позиции'!L236="","",'Все позиции'!L236) -> 200 | I27: =IF('Все позиции'!O236="","",'Все позиции'!O236) -> -0.80392157 | J27: =IF('Все позиции'!G236="","",'Все позиции'!G236) -> 76500 | K27: =IF('Все позиции'!M236="","",'Все позиции'!M236) -> 15000 | L27: =IF('Все позиции'!N236="","",'Все позиции'!N236) -> -61500 | M27: =IF('Все позиции'!P236="","",'Все позиции'!P236) -> Цена снижена | N27: =IF('Все позиции'!Q236="","",'Все позиции'!Q236) -> по договору | O27: =IF('Все позиции'!R236="","",'Все позиции'!R236) -> Цена Согласована Марк
A28: =IF('Все позиции'!A195="","",'Все позиции'!A195) -> 4. Вентиляция 10 этаж | B28: =IF('Все позиции'!B195="","",'Все позиции'!B195) -> 4.82 | C28: =IF('Все позиции'!C195="","",'Все позиции'!C195) -> Изоляция прямоугольных воздуховодов | D28: =IF('Все позиции'!D195="","",'Все позиции'!D195) -> м2 | E28: =IF('Все позиции'!E195="","",'Все позиции'!E195) -> 120 | F28: =IF('Все позиции'!F195="","",'Все позиции'!F195) -> 1092 | G28: =IF('Все позиции'!H195="","",'Все позиции'!H195) -> 120 | H28: =IF('Все позиции'!L195="","",'Все позиции'!L195) -> 665 | I28: =IF('Все позиции'!O195="","",'Все позиции'!O195) -> -0.39102564 | J28: =IF('Все позиции'!G195="","",'Все позиции'!G195) -> 131040 | K28: =IF('Все позиции'!M195="","",'Все позиции'!M195) -> 79800 | L28: =IF('Все позиции'!N195="","",'Все позиции'!N195) -> -51240 | M28: =IF('Все позиции'!P195="","",'Все позиции'!P195) -> Цена снижена | N28: =IF('Все позиции'!Q195="","",'Все позиции'!Q195) | O28: =IF('Все позиции'!R195="","",'Все позиции'!R195)
A29: =IF('Все позиции'!A319="","",'Все позиции'!A319) -> 6. Дымоудаление (2 этаж) | B29: =IF('Все позиции'!B319="","",'Все позиции'!B319) -> 6.78 | C29: =IF('Все позиции'!C319="","",'Все позиции'!C319) -> Отвод 45гр 800*500 | D29: =IF('Все позиции'!D319="","",'Все позиции'!D319) -> шт. | E29: =IF('Все позиции'!E319="","",'Все позиции'!E319) -> 6 | F29: =IF('Все позиции'!F319="","",'Все позиции'!F319) -> 8000 | G29: =IF('Все позиции'!H319="","",'Все позиции'!H319) -> 6 | H29: =IF('Все позиции'!L319="","",'Все позиции'!L319) | I29: =IF('Все позиции'!O319="","",'Все позиции'!O319) -> -1 | J29: =IF('Все позиции'!G319="","",'Все позиции'!G319) -> 48000 | K29: =IF('Все позиции'!M319="","",'Все позиции'!M319) -> 0 | L29: =IF('Все позиции'!N319="","",'Все позиции'!N319) -> -48000 | M29: =IF('Все позиции'!P319="","",'Все позиции'!P319) -> Исключено → отдельный допник | N29: =IF('Все позиции'!Q319="","",'Все позиции'!Q319) -> удалить (если будут данные позиции сделаем отдельный допник) | O29: =IF('Все позиции'!R319="","",'Все позиции'!R319)
A30: =IF('Все позиции'!A243="","",'Все позиции'!A243) -> 6. Вентиляция 2 этаж | B30: =IF('Все позиции'!B243="","",'Все позиции'!B243) -> 6.3 | C30: =IF('Все позиции'!C243="","",'Все позиции'!C243) -> Решетка защитная круглая, Ø200 БСК 200 | D30: =IF('Все позиции'!D243="","",'Все позиции'!D243) -> шт. | E30: =IF('Все позиции'!E243="","",'Все позиции'!E243) -> 44 | F30: =IF('Все позиции'!F243="","",'Все позиции'!F243) -> 1296 | G30: =IF('Все позиции'!H243="","",'Все позиции'!H243) -> 44 | H30: =IF('Все позиции'!L243="","",'Все позиции'!L243) -> 298.89 | I30: =IF('Все позиции'!O243="","",'Все позиции'!O243) -> -0.769375 | J30: =IF('Все позиции'!G243="","",'Все позиции'!G243) -> 57024 | K30: =IF('Все позиции'!M243="","",'Все позиции'!M243) -> 13151.16 | L30: =IF('Все позиции'!N243="","",'Все позиции'!N243) -> -43872.84 | M30: =IF('Все позиции'!P243="","",'Все позиции'!P243) -> Снижение предложено, но не внесено в итог | N30: =IF('Все позиции'!Q243="","",'Все позиции'!Q243) -> по договору | O30: =IF('Все позиции'!R243="","",'Все позиции'!R243)
A31: =IF('Все позиции'!A312="","",'Все позиции'!A312) -> 6. Вентиляция 2 этаж | B31: =IF('Все позиции'!B312="","",'Все позиции'!B312) -> 6.72 | C31: =IF('Все позиции'!C312="","",'Все позиции'!C312) -> Изоляция прямоугольных воздуховодов | D31: =IF('Все позиции'!D312="","",'Все позиции'!D312) -> м2 | E31: =IF('Все позиции'!E312="","",'Все позиции'!E312) -> 150 | F31: =IF('Все позиции'!F312="","",'Все позиции'!F312) -> 1092 | G31: =IF('Все позиции'!H312="","",'Все позиции'!H312) -> 150 | H31: =IF('Все позиции'!L312="","",'Все позиции'!L312) -> 800 | I31: =IF('Все позиции'!O312="","",'Все позиции'!O312) -> -0.26739927 | J31: =IF('Все позиции'!G312="","",'Все позиции'!G312) -> 163800 | K31: =IF('Все позиции'!M312="","",'Все позиции'!M312) -> 120000 | L31: =IF('Все позиции'!N312="","",'Все позиции'!N312) -> -43800 | M31: =IF('Все позиции'!P312="","",'Все позиции'!P312) -> Цена снижена | N31: =IF('Все позиции'!Q312="","",'Все позиции'!Q312) | O31: =IF('Все позиции'!R312="","",'Все позиции'!R312)
A32: =IF('Все позиции'!A239="","",'Все позиции'!A239) -> 5. Холодоснабжение 10 этаж | B32: =IF('Все позиции'!B239="","",'Все позиции'!B239) -> 5.36 | C32: =IF('Все позиции'!C239="","",'Все позиции'!C239) -> ПНР 10й этаж | D32: =IF('Все позиции'!D239="","",'Все позиции'!D239) -> к-т | E32: =IF('Все позиции'!E239="","",'Все позиции'!E239) -> 1 | F32: =IF('Все позиции'!F239="","",'Все позиции'!F239) -> 162000 | G32: =IF('Все позиции'!H239="","",'Все позиции'!H239) -> 1 | H32: =IF('Все позиции'!L239="","",'Все позиции'!L239) -> 120000 | I32: =IF('Все позиции'!O239="","",'Все позиции'!O239) -> -0.25925926 | J32: =IF('Все позиции'!G239="","",'Все позиции'!G239) -> 162000 | K32: =IF('Все позиции'!M239="","",'Все позиции'!M239) -> 120000 | L32: =IF('Все позиции'!N239="","",'Все позиции'!N239) -> -42000 | M32: =IF('Все позиции'!P239="","",'Все позиции'!P239) -> Цена снижена | N32: =IF('Все позиции'!Q239="","",'Все позиции'!Q239) -> по тип.эт | O32: =IF('Все позиции'!R239="","",'Все позиции'!R239)
A33: =IF('Все позиции'!A331="","",'Все позиции'!A331) -> 7. Холодоснабжение 2 этаж | B33: =IF('Все позиции'!B331="","",'Все позиции'!B331) -> 7.11 | C33: =IF('Все позиции'!C331="","",'Все позиции'!C331) -> ПНР 2й этаж | D33: =IF('Все позиции'!D331="","",'Все позиции'!D331) -> к-т | E33: =IF('Все позиции'!E331="","",'Все позиции'!E331) -> 1 | F33: =IF('Все позиции'!F331="","",'Все позиции'!F331) -> 162000 | G33: =IF('Все позиции'!H331="","",'Все позиции'!H331) -> 1 | H33: =IF('Все позиции'!L331="","",'Все позиции'!L331) -> 120000 | I33: =IF('Все позиции'!O331="","",'Все позиции'!O331) -> -0.25925926 | J33: =IF('Все позиции'!G331="","",'Все позиции'!G331) -> 162000 | K33: =IF('Все позиции'!M331="","",'Все позиции'!M331) -> 120000 | L33: =IF('Все позиции'!N331="","",'Все позиции'!N331) -> -42000 | M33: =IF('Все позиции'!P331="","",'Все позиции'!P331) -> Цена снижена | N33: =IF('Все позиции'!Q331="","",'Все позиции'!Q331) -> по тип.эт | O33: =IF('Все позиции'!R331="","",'Все позиции'!R331)
A34: =IF('Все позиции'!A120="","",'Все позиции'!A120) -> 4. Вентиляция 10 этаж | B34: =IF('Все позиции'!B120="","",'Все позиции'!B120) -> 4.7 | C34: =IF('Все позиции'!C120="","",'Все позиции'!C120) -> Адаптер для щелевой решетки с регулятором расхода и увеличенным патрубком, 1000мм Адаптер для ЛРЩ 22-1-1000 y=67мм + заслонка | D34: =IF('Все позиции'!D120="","",'Все позиции'!D120) -> шт. | E34: =IF('Все позиции'!E120="","",'Все позиции'!E120) -> 12 | F34: =IF('Все позиции'!F120="","",'Все позиции'!F120) -> 4860 | G34: =IF('Все позиции'!H120="","",'Все позиции'!H120) -> 12 | H34: =IF('Все позиции'!L120="","",'Все позиции'!L120) -> 1500 | I34: =IF('Все позиции'!O120="","",'Все позиции'!O120) -> -0.69135802 | J34: =IF('Все позиции'!G120="","",'Все позиции'!G120) -> 58320 | K34: =IF('Все позиции'!M120="","",'Все позиции'!M120) -> 18000 | L34: =IF('Все позиции'!N120="","",'Все позиции'!N120) -> -40320 | M34: =IF('Все позиции'!P120="","",'Все позиции'!P120) -> Цена снижена | N34: =IF('Все позиции'!Q120="","",'Все позиции'!Q120) -> расценка сильно завышена | O34: =IF('Все позиции'!R120="","",'Все позиции'!R120)
A35: =IF('Все позиции'!A77="","",'Все позиции'!A77) -> 2. Кондиционирование | B35: =IF('Все позиции'!B77="","",'Все позиции'!B77) -> 2.38 | C35: =IF('Все позиции'!C77="","",'Все позиции'!C77) -> Тепловая изоляция из вспененного каучука, толщиной 9 мм Armaflex АСЕ 35*13 | D35: =IF('Все позиции'!D77="","",'Все позиции'!D77) -> м.п. | E35: =IF('Все позиции'!E77="","",'Все позиции'!E77) -> 800 | F35: =IF('Все позиции'!F77="","",'Все позиции'!F77) -> 200 | G35: =IF('Все позиции'!H77="","",'Все позиции'!H77) -> 800 | H35: =IF('Все позиции'!L77="","",'Все позиции'!L77) -> 150 | I35: =IF('Все позиции'!O77="","",'Все позиции'!O77) -> -0.25 | J35: =IF('Все позиции'!G77="","",'Все позиции'!G77) -> 160000 | K35: =IF('Все позиции'!M77="","",'Все позиции'!M77) -> 120000 | L35: =IF('Все позиции'!N77="","",'Все позиции'!N77) -> -40000 | M35: =IF('Все позиции'!P77="","",'Все позиции'!P77) -> Снижение согласовано, но не внесено в итог | N35: =IF('Все позиции'!Q77="","",'Все позиции'!Q77) -> по договору | O35: =IF('Все позиции'!R77="","",'Все позиции'!R77) -> Цена Согласована Марк
A36: =IF('Все позиции'!A211="","",'Все позиции'!A211) -> 5. Холодоснабжение 10 этаж | B36: =IF('Все позиции'!B211="","",'Все позиции'!B211) -> 5.8 | C36: =IF('Все позиции'!C211="","",'Все позиции'!C211) -> Ниппель 3/4" | D36: =IF('Все позиции'!D211="","",'Все позиции'!D211) -> шт. | E36: =IF('Все позиции'!E211="","",'Все позиции'!E211) -> 62 | F36: =IF('Все позиции'!F211="","",'Все позиции'!F211) -> 1296 | G36: =IF('Все позиции'!H211="","",'Все позиции'!H211) -> 62 | H36: =IF('Все позиции'!L211="","",'Все позиции'!L211) -> 700 | I36: =IF('Все позиции'!O211="","",'Все позиции'!O211) -> -0.45987654 | J36: =IF('Все позиции'!G211="","",'Все позиции'!G211) -> 80352 | K36: =IF('Все позиции'!M211="","",'Все позиции'!M211) -> 43400 | L36: =IF('Все позиции'!N211="","",'Все позиции'!N211) -> -36952 | M36: =IF('Все позиции'!P211="","",'Все позиции'!P211) -> Цена снижена | N36: =IF('Все позиции'!Q211="","",'Все позиции'!Q211) | O36: =IF('Все позиции'!R211="","",'Все позиции'!R211) -> Цена Согласована Марк
A37: =IF('Все позиции'!A212="","",'Все позиции'!A212) -> 5. Холодоснабжение 10 этаж | B37: =IF('Все позиции'!B212="","",'Все позиции'!B212) -> 5.9 | C37: =IF('Все позиции'!C212="","",'Все позиции'!C212) -> Муфта переходная 3/4"x 1/2" | D37: =IF('Все позиции'!D212="","",'Все позиции'!D212) -> шт. | E37: =IF('Все позиции'!E212="","",'Все позиции'!E212) -> 62 | F37: =IF('Все позиции'!F212="","",'Все позиции'!F212) -> 1296 | G37: =IF('Все позиции'!H212="","",'Все позиции'!H212) -> 62 | H37: =IF('Все позиции'!L212="","",'Все позиции'!L212) -> 700 | I37: =IF('Все позиции'!O212="","",'Все позиции'!O212) -> -0.45987654 | J37: =IF('Все позиции'!G212="","",'Все позиции'!G212) -> 80352 | K37: =IF('Все позиции'!M212="","",'Все позиции'!M212) -> 43400 | L37: =IF('Все позиции'!N212="","",'Все позиции'!N212) -> -36952 | M37: =IF('Все позиции'!P212="","",'Все позиции'!P212) -> Цена снижена | N37: =IF('Все позиции'!Q212="","",'Все позиции'!Q212) | O37: =IF('Все позиции'!R212="","",'Все позиции'!R212) -> Цена Согласована Марк
A38: =IF('Все позиции'!A213="","",'Все позиции'!A213) -> 5. Холодоснабжение 10 этаж | B38: =IF('Все позиции'!B213="","",'Все позиции'!B213) -> 5.10 | C38: =IF('Все позиции'!C213="","",'Все позиции'!C213) -> Гибкая подводка 3/4" гайка/штуцер, длиной 500мм | D38: =IF('Все позиции'!D213="","",'Все позиции'!D213) -> шт. | E38: =IF('Все позиции'!E213="","",'Все позиции'!E213) -> 62 | F38: =IF('Все позиции'!F213="","",'Все позиции'!F213) -> 1296 | G38: =IF('Все позиции'!H213="","",'Все позиции'!H213) -> 62 | H38: =IF('Все позиции'!L213="","",'Все позиции'!L213) -> 700 | I38: =IF('Все позиции'!O213="","",'Все позиции'!O213) -> -0.45987654 | J38: =IF('Все позиции'!G213="","",'Все позиции'!G213) -> 80352 | K38: =IF('Все позиции'!M213="","",'Все позиции'!M213) -> 43400 | L38: =IF('Все позиции'!N213="","",'Все позиции'!N213) -> -36952 | M38: =IF('Все позиции'!P213="","",'Все позиции'!P213) -> Цена снижена | N38: =IF('Все позиции'!Q213="","",'Все позиции'!Q213) | O38: =IF('Все позиции'!R213="","",'Все позиции'!R213) -> Цена Согласована Марк
A39: =IF('Все позиции'!A214="","",'Все позиции'!A214) -> 5. Холодоснабжение 10 этаж | B39: =IF('Все позиции'!B214="","",'Все позиции'!B214) -> 5.11 | C39: =IF('Все позиции'!C214="","",'Все позиции'!C214) -> Ниппель переходной 3/4" | D39: =IF('Все позиции'!D214="","",'Все позиции'!D214) -> шт. | E39: =IF('Все позиции'!E214="","",'Все позиции'!E214) -> 62 | F39: =IF('Все позиции'!F214="","",'Все позиции'!F214) -> 1296 | G39: =IF('Все позиции'!H214="","",'Все позиции'!H214) -> 62 | H39: =IF('Все позиции'!L214="","",'Все позиции'!L214) -> 700 | I39: =IF('Все позиции'!O214="","",'Все позиции'!O214) -> -0.45987654 | J39: =IF('Все позиции'!G214="","",'Все позиции'!G214) -> 80352 | K39: =IF('Все позиции'!M214="","",'Все позиции'!M214) -> 43400 | L39: =IF('Все позиции'!N214="","",'Все позиции'!N214) -> -36952 | M39: =IF('Все позиции'!P214="","",'Все позиции'!P214) -> Цена снижена | N39: =IF('Все позиции'!Q214="","",'Все позиции'!Q214) | O39: =IF('Все позиции'!R214="","",'Все позиции'!R214) -> Цена Согласована Марк
A40: =IF('Все позиции'!A215="","",'Все позиции'!A215) -> 5. Холодоснабжение 10 этаж | B40: =IF('Все позиции'!B215="","",'Все позиции'!B215) -> 5.12 | C40: =IF('Все позиции'!C215="","",'Все позиции'!C215) -> Переходник 32-R 3/4 | D40: =IF('Все позиции'!D215="","",'Все позиции'!D215) -> шт. | E40: =IF('Все позиции'!E215="","",'Все позиции'!E215) -> 62 | F40: =IF('Все позиции'!F215="","",'Все позиции'!F215) -> 1296 | G40: =IF('Все позиции'!H215="","",'Все позиции'!H215) -> 62 | H40: =IF('Все позиции'!L215="","",'Все позиции'!L215) -> 700 | I40: =IF('Все позиции'!O215="","",'Все позиции'!O215) -> -0.45987654 | J40: =IF('Все позиции'!G215="","",'Все позиции'!G215) -> 80352 | K40: =IF('Все позиции'!M215="","",'Все позиции'!M215) -> 43400 | L40: =IF('Все позиции'!N215="","",'Все позиции'!N215) -> -36952 | M40: =IF('Все позиции'!P215="","",'Все позиции'!P215) -> Цена снижена | N40: =IF('Все позиции'!Q215="","",'Все позиции'!Q215) | O40: =IF('Все позиции'!R215="","",'Все позиции'!R215) -> Цена Согласована Марк
A41: =IF('Все позиции'!A216="","",'Все позиции'!A216) -> 5. Холодоснабжение 10 этаж | B41: =IF('Все позиции'!B216="","",'Все позиции'!B216) -> 5.13 | C41: =IF('Все позиции'!C216="","",'Все позиции'!C216) -> Монтажная гильза 32 LX | D41: =IF('Все позиции'!D216="","",'Все позиции'!D216) -> шт. | E41: =IF('Все позиции'!E216="","",'Все позиции'!E216) -> 62 | F41: =IF('Все позиции'!F216="","",'Все позиции'!F216) -> 1296 | G41: =IF('Все позиции'!H216="","",'Все позиции'!H216) -> 62 | H41: =IF('Все позиции'!L216="","",'Все позиции'!L216) -> 700 | I41: =IF('Все позиции'!O216="","",'Все позиции'!O216) -> -0.45987654 | J41: =IF('Все позиции'!G216="","",'Все позиции'!G216) -> 80352 | K41: =IF('Все позиции'!M216="","",'Все позиции'!M216) -> 43400 | L41: =IF('Все позиции'!N216="","",'Все позиции'!N216) -> -36952 | M41: =IF('Все позиции'!P216="","",'Все позиции'!P216) -> Цена снижена | N41: =IF('Все позиции'!Q216="","",'Все позиции'!Q216) | O41: =IF('Все позиции'!R216="","",'Все позиции'!R216) -> Цена Согласована Марк
A42: =IF('Все позиции'!A258="","",'Все позиции'!A258) -> 6. Вентиляция 2 этаж | B42: =IF('Все позиции'!B258="","",'Все позиции'!B258) -> 6.18 | C42: =IF('Все позиции'!C258="","",'Все позиции'!C258) -> Воздуховод из оцинкованной стали толщиной 0,5мм, класса «В», Ø200 | D42: =IF('Все позиции'!D258="","",'Все позиции'!D258) -> мп | E42: =IF('Все позиции'!E258="","",'Все позиции'!E258) -> 55 | F42: =IF('Все позиции'!F258="","",'Все позиции'!F258) -> 1393.2 | G42: =IF('Все позиции'!H258="","",'Все позиции'!H258) -> 55 | H42: =IF('Все позиции'!L258="","",'Все позиции'!L258) -> 862.23 | I42: =IF('Все позиции'!O258="","",'Все позиции'!O258) -> -0.38111542 | J42: =IF('Все позиции'!G258="","",'Все позиции'!G258) -> 76626 | K42: =IF('Все позиции'!M258="","",'Все позиции'!M258) -> 47422.65 | L42: =IF('Все позиции'!N258="","",'Все позиции'!N258) -> -29203.35 | M42: =IF('Все позиции'!P258="","",'Все позиции'!P258) -> Цена снижена | N42: =IF('Все позиции'!Q258="","",'Все позиции'!Q258) -> по договору | O42: =IF('Все позиции'!R258="","",'Все позиции'!R258)
A43: =IF('Все позиции'!A318="","",'Все позиции'!A318) -> 6. Дымоудаление (2 этаж) | B43: =IF('Все позиции'!B318="","",'Все позиции'!B318) -> 6.77 | C43: =IF('Все позиции'!C318="","",'Все позиции'!C318) -> Отвод 90гр 800*500 | D43: =IF('Все позиции'!D318="","",'Все позиции'!D318) -> шт. | E43: =IF('Все позиции'!E318="","",'Все позиции'!E318) -> 3 | F43: =IF('Все позиции'!F318="","",'Все позиции'!F318) -> 9600 | G43: =IF('Все позиции'!H318="","",'Все позиции'!H318) -> 3 | H43: =IF('Все позиции'!L318="","",'Все позиции'!L318) | I43: =IF('Все позиции'!O318="","",'Все позиции'!O318) -> -1 | J43: =IF('Все позиции'!G318="","",'Все позиции'!G318) -> 28800 | K43: =IF('Все позиции'!M318="","",'Все позиции'!M318) -> 0 | L43: =IF('Все позиции'!N318="","",'Все позиции'!N318) -> -28800 | M43: =IF('Все позиции'!P318="","",'Все позиции'!P318) -> Исключено → отдельный допник | N43: =IF('Все позиции'!Q318="","",'Все позиции'!Q318) -> удалить (если будут данные позиции сделаем отдельный допник) | O43: =IF('Все позиции'!R318="","",'Все позиции'!R318)
A44: =IF('Все позиции'!A196="","",'Все позиции'!A196) -> 4. Вентиляция 10 этаж | B44: =IF('Все позиции'!B196="","",'Все позиции'!B196) -> 4.83 | C44: =IF('Все позиции'!C196="","",'Все позиции'!C196) -> Изоляция круглых воздуховодов | D44: =IF('Все позиции'!D196="","",'Все позиции'!D196) -> мп | E44: =IF('Все позиции'!E196="","",'Все позиции'!E196) -> 81 | F44: =IF('Все позиции'!F196="","",'Все позиции'!F196) -> 1020 | G44: =IF('Все позиции'!H196="","",'Все позиции'!H196) -> 81 | H44: =IF('Все позиции'!L196="","",'Все позиции'!L196) -> 665 | I44: =IF('Все позиции'!O196="","",'Все позиции'!O196) -> -0.34803922 | J44: =IF('Все позиции'!G196="","",'Все позиции'!G196) -> 82620 | K44: =IF('Все позиции'!M196="","",'Все позиции'!M196) -> 53865 | L44: =IF('Все позиции'!N196="","",'Все позиции'!N196) -> -28755 | M44: =IF('Все позиции'!P196="","",'Все позиции'!P196) -> Цена снижена | N44: =IF('Все позиции'!Q196="","",'Все позиции'!Q196) -> за м2 | O44: =IF('Все позиции'!R196="","",'Все позиции'!R196)
A45: =IF('Все позиции'!A193="","",'Все позиции'!A193) -> 4. Вентиляция 10 этаж | B45: =IF('Все позиции'!B193="","",'Все позиции'!B193) -> 4.80 | C45: =IF('Все позиции'!C193="","",'Все позиции'!C193) -> Изоляция круглого изделия от Ф100-ф250 | D45: =IF('Все позиции'!D193="","",'Все позиции'!D193) -> шт. | E45: =IF('Все позиции'!E193="","",'Все позиции'!E193) -> 30 | F45: =IF('Все позиции'!F193="","",'Все позиции'!F193) -> 1296 | G45: =IF('Все позиции'!H193="","",'Все позиции'!H193) -> 30 | H45: =IF('Все позиции'!L193="","",'Все позиции'!L193) -> 450 | I45: =IF('Все позиции'!O193="","",'Все позиции'!O193) -> -0.65277778 | J45: =IF('Все позиции'!G193="","",'Все позиции'!G193) -> 38880 | K45: =IF('Все позиции'!M193="","",'Все позиции'!M193) -> 13500 | L45: =IF('Все позиции'!N193="","",'Все позиции'!N193) -> -25380 | M45: =IF('Все позиции'!P193="","",'Все позиции'!P193) -> Цена снижена | N45: =IF('Все позиции'!Q193="","",'Все позиции'!Q193) -> по договору | O45: =IF('Все позиции'!R193="","",'Все позиции'!R193)
A46: =IF('Все позиции'!A219="","",'Все позиции'!A219) -> 5. Холодоснабжение 10 этаж | B46: =IF('Все позиции'!B219="","",'Все позиции'!B219) -> 5.16 | C46: =IF('Все позиции'!C219="","",'Все позиции'!C219) -> Труба из сшитого полиэтилена PEX-a, Ø32х4,4 | D46: =IF('Все позиции'!D219="","",'Все позиции'!D219) -> мп | E46: =IF('Все позиции'!E219="","",'Все позиции'!E219) -> 90 | F46: =IF('Все позиции'!F219="","",'Все позиции'!F219) -> 1020 | G46: =IF('Все позиции'!H219="","",'Все позиции'!H219) -> 90 | H46: =IF('Все позиции'!L219="","",'Все позиции'!L219) -> 750 | I46: =IF('Все позиции'!O219="","",'Все позиции'!O219) -> -0.26470588 | J46: =IF('Все позиции'!G219="","",'Все позиции'!G219) -> 91800 | K46: =IF('Все позиции'!M219="","",'Все позиции'!M219) -> 67500 | L46: =IF('Все позиции'!N219="","",'Все позиции'!N219) -> -24300 | M46: =IF('Все позиции'!P219="","",'Все позиции'!P219) -> Цена снижена | N46: =IF('Все позиции'!Q219="","",'Все позиции'!Q219) -> по договору | O46: =IF('Все позиции'!R219="","",'Все позиции'!R219) -> Цена Согласована Марк
A47: =IF('Все позиции'!A234="","",'Все позиции'!A234) -> 5. Холодоснабжение 10 этаж | B47: =IF('Все позиции'!B234="","",'Все позиции'!B234) -> 5.31 | C47: =IF('Все позиции'!C234="","",'Все позиции'!C234) -> Труба полипропиленовая, Ø32х5,4 | D47: =IF('Все позиции'!D234="","",'Все позиции'!D234) -> шт. | E47: =IF('Все позиции'!E234="","",'Все позиции'!E234) -> 75 | F47: =IF('Все позиции'!F234="","",'Все позиции'!F234) -> 1020 | G47: =IF('Все позиции'!H234="","",'Все позиции'!H234) -> 75 | H47: =IF('Все позиции'!L234="","",'Все позиции'!L234) -> 740 | I47: =IF('Все позиции'!O234="","",'Все позиции'!O234) -> -0.2745098 | J47: =IF('Все позиции'!G234="","",'Все позиции'!G234) -> 76500 | K47: =IF('Все позиции'!M234="","",'Все позиции'!M234) -> 55500 | L47: =IF('Все позиции'!N234="","",'Все позиции'!N234) -> -21000 | M47: =IF('Все позиции'!P234="","",'Все позиции'!P234) -> Цена снижена | N47: =IF('Все позиции'!Q234="","",'Все позиции'!Q234) | O47: =IF('Все позиции'!R234="","",'Все позиции'!R234) -> Цена Согласована Марк
A48: =IF('Все позиции'!A256="","",'Все позиции'!A256) -> 6. Вентиляция 2 этаж | B48: =IF('Все позиции'!B256="","",'Все позиции'!B256) -> 6.16 | C48: =IF('Все позиции'!C256="","",'Все позиции'!C256) -> Воздуховод из оцинкованной стали толщиной 0,5мм, класса «В», Ø125 | D48: =IF('Все позиции'!D256="","",'Все позиции'!D256) -> мп | E48: =IF('Все позиции'!E256="","",'Все позиции'!E256) -> 30 | F48: =IF('Все позиции'!F256="","",'Все позиции'!F256) -> 1360.8 | G48: =IF('Все позиции'!H256="","",'Все позиции'!H256) -> 30 | H48: =IF('Все позиции'!L256="","",'Все позиции'!L256) -> 689.79 | I48: =IF('Все позиции'!O256="","",'Все позиции'!O256) -> -0.49309965 | J48: =IF('Все позиции'!G256="","",'Все позиции'!G256) -> 40824 | K48: =IF('Все позиции'!M256="","",'Все позиции'!M256) -> 20693.7 | L48: =IF('Все позиции'!N256="","",'Все позиции'!N256) -> -20130.3 | M48: =IF('Все позиции'!P256="","",'Все позиции'!P256) -> Цена снижена | N48: =IF('Все позиции'!Q256="","",'Все позиции'!Q256) -> по договору | O48: =IF('Все позиции'!R256="","",'Все позиции'!R256)
A49: =IF('Все позиции'!A138="","",'Все позиции'!A138) -> 4. Вентиляция 10 этаж | B49: =IF('Все позиции'!B138="","",'Все позиции'!B138) -> 4.25 | C49: =IF('Все позиции'!C138="","",'Все позиции'!C138) -> Воздуховод из оцинкованной стали толщиной 0,5мм, класса «В», Ø160 | D49: =IF('Все позиции'!D138="","",'Все позиции'!D138) -> мп | E49: =IF('Все позиции'!E138="","",'Все позиции'!E138) -> 40 | F49: =IF('Все позиции'!F138="","",'Все позиции'!F138) -> 1360.8 | G49: =IF('Все позиции'!H138="","",'Все позиции'!H138) -> 40 | H49: =IF('Все позиции'!L138="","",'Все позиции'!L138) -> 862.23 | I49: =IF('Все позиции'!O138="","",'Все позиции'!O138) -> -0.36638007 | J49: =IF('Все позиции'!G138="","",'Все позиции'!G138) -> 54432 | K49: =IF('Все позиции'!M138="","",'Все позиции'!M138) -> 34489.2 | L49: =IF('Все позиции'!N138="","",'Все позиции'!N138) -> -19942.8 | M49: =IF('Все позиции'!P138="","",'Все позиции'!P138) -> Цена снижена | N49: =IF('Все позиции'!Q138="","",'Все позиции'!Q138) -> по договору | O49: =IF('Все позиции'!R138="","",'Все позиции'!R138)
A50: =IF('Все позиции'!A313="","",'Все позиции'!A313) -> 6. Вентиляция 2 этаж | B50: =IF('Все позиции'!B313="","",'Все позиции'!B313) -> 6.73 | C50: =IF('Все позиции'!C313="","",'Все позиции'!C313) -> Изоляция круглых воздуховодов | D50: =IF('Все позиции'!D313="","",'Все позиции'!D313) -> мп | E50: =IF('Все позиции'!E313="","",'Все позиции'!E313) -> 80 | F50: =IF('Все позиции'!F313="","",'Все позиции'!F313) -> 1020 | G50: =IF('Все позиции'!H313="","",'Все позиции'!H313) -> 80 | H50: =IF('Все позиции'!L313="","",'Все позиции'!L313) -> 800 | I50: =IF('Все позиции'!O313="","",'Все позиции'!O313) -> -0.21568627 | J50: =IF('Все позиции'!G313="","",'Все позиции'!G313) -> 81600 | K50: =IF('Все позиции'!M313="","",'Все позиции'!M313) -> 64000 | L50: =IF('Все позиции'!N313="","",'Все позиции'!N313) -> -17600 | M50: =IF('Все позиции'!P313="","",'Все позиции'!P313) -> Цена снижена | N50: =IF('Все позиции'!Q313="","",'Все позиции'!Q313) -> за м2 | O50: =IF('Все позиции'!R313="","",'Все позиции'!R313)
A51: =IF('Все позиции'!A97="","",'Все позиции'!A97) -> 3. Дополнительные работы 3,7,8,9 этаж | B51: =IF('Все позиции'!B97="","",'Все позиции'!B97) -> 3.15 | C51: =IF('Все позиции'!C97="","",'Все позиции'!C97) -> Демонтаж диффузора, монтаж гибкой подводки | D51: =IF('Все позиции'!D97="","",'Все позиции'!D97) -> к-т | E51: =IF('Все позиции'!E97="","",'Все позиции'!E97) -> 6 | F51: =IF('Все позиции'!F97="","",'Все позиции'!F97) -> 4200 | G51: =IF('Все позиции'!H97="","",'Все позиции'!H97) -> 6 | H51: =IF('Все позиции'!L97="","",'Все позиции'!L97) -> 1500 | I51: =IF('Все позиции'!O97="","",'Все позиции'!O97) -> -0.64285714 | J51: =IF('Все позиции'!G97="","",'Все позиции'!G97) -> 25200 | K51: =IF('Все позиции'!M97="","",'Все позиции'!M97) -> 9000 | L51: =IF('Все позиции'!N97="","",'Все позиции'!N97) -> -16200 | M51: =IF('Все позиции'!P97="","",'Все позиции'!P97) -> Цена снижена | N51: =IF('Все позиции'!Q97="","",'Все позиции'!Q97) -> Расписать какой диффузор, какая гибкая подводка? | O51: =IF('Все позиции'!R97="","",'Все позиции'!R97) -> демонтаж существующего диффузора, монтаж гибкой подводки временно, после зашивке ГКЛ будет монтаж данного диффузора в ГКЛ; Наименование изменено на: «Демонтаж диффузора, монтаж гибкой подводки, монтаж диффузора в гкл»
A52: =IF('Все позиции'!A202="","",'Все позиции'!A202) -> 4. Дымоудаление (10 этаж) | B52: =IF('Все позиции'!B202="","",'Все позиции'!B202) -> 4.88 | C52: =IF('Все позиции'!C202="","",'Все позиции'!C202) -> Отвод 45гр 800*500 | D52: =IF('Все позиции'!D202="","",'Все позиции'!D202) -> шт. | E52: =IF('Все позиции'!E202="","",'Все позиции'!E202) -> 2 | F52: =IF('Все позиции'!F202="","",'Все позиции'!F202) -> 8000 | G52: =IF('Все позиции'!H202="","",'Все позиции'!H202) -> 2 | H52: =IF('Все позиции'!L202="","",'Все позиции'!L202) | I52: =IF('Все позиции'!O202="","",'Все позиции'!O202) -> -1 | J52: =IF('Все позиции'!G202="","",'Все позиции'!G202) -> 16000 | K52: =IF('Все позиции'!M202="","",'Все позиции'!M202) -> 0 | L52: =IF('Все позиции'!N202="","",'Все позиции'!N202) -> -16000 | M52: =IF('Все позиции'!P202="","",'Все позиции'!P202) -> Исключено → отдельный допник | N52: =IF('Все позиции'!Q202="","",'Все позиции'!Q202) -> удалить (если будут данные позиции сделаем отдельный допник) | O52: =IF('Все позиции'!R202="","",'Все позиции'!R202)
A53: =IF('Все позиции'!A230="","",'Все позиции'!A230) -> 5. Холодоснабжение 10 этаж | B53: =IF('Все позиции'!B230="","",'Все позиции'!B230) -> 5.27 | C53: =IF('Все позиции'!C230="","",'Все позиции'!C230) -> Угольник 900 полипропиленовый, 32 | D53: =IF('Все позиции'!D230="","",'Все позиции'!D230) -> шт. | E53: =IF('Все позиции'!E230="","",'Все позиции'!E230) -> 30 | F53: =IF('Все позиции'!F230="","",'Все позиции'!F230) -> 1020 | G53: =IF('Все позиции'!H230="","",'Все позиции'!H230) -> 30 | H53: =IF('Все позиции'!L230="","",'Все позиции'!L230) -> 520 | I53: =IF('Все позиции'!O230="","",'Все позиции'!O230) -> -0.49019608 | J53: =IF('Все позиции'!G230="","",'Все позиции'!G230) -> 30600 | K53: =IF('Все позиции'!M230="","",'Все позиции'!M230) -> 15600 | L53: =IF('Все позиции'!N230="","",'Все позиции'!N230) -> -15000 | M53: =IF('Все позиции'!P230="","",'Все позиции'!P230) -> Цена снижена | N53: =IF('Все позиции'!Q230="","",'Все позиции'!Q230) | O53: =IF('Все позиции'!R230="","",'Все позиции'!R230) -> Цена Согласована Марк
A54: =IF('Все позиции'!A255="","",'Все позиции'!A255) -> 6. Вентиляция 2 этаж | B54: =IF('Все позиции'!B255="","",'Все позиции'!B255) -> 6.15 | C54: =IF('Все позиции'!C255="","",'Все позиции'!C255) -> Воздуховод из оцинкованной стали толщиной 0,5мм, класса «В», Ø100 | D54: =IF('Все позиции'!D255="","",'Все позиции'!D255) -> мп | E54: =IF('Все позиции'!E255="","",'Все позиции'!E255) -> 36 | F54: =IF('Все позиции'!F255="","",'Все позиции'!F255) -> 1360.8 | G54: =IF('Все позиции'!H255="","",'Все позиции'!H255) -> 36 | H54: =IF('Все позиции'!L255="","",'Все позиции'!L255) -> 950 | I54: =IF('Все позиции'!O255="","",'Все позиции'!O255) -> -0.30188125 | J54: =IF('Все позиции'!G255="","",'Все позиции'!G255) -> 48988.8 | K54: =IF('Все позиции'!M255="","",'Все позиции'!M255) -> 34200 | L54: =IF('Все позиции'!N255="","",'Все позиции'!N255) -> -14788.8 | M54: =IF('Все позиции'!P255="","",'Все позиции'!P255) -> Цена снижена | N54: =IF('Все позиции'!Q255="","",'Все позиции'!Q255) -> по договору | O54: =IF('Все позиции'!R255="","",'Все позиции'!R255)
A55: =IF('Все позиции'!A101="","",'Все позиции'!A101) -> 3. Дополнительные работы 3,7,8,9 этаж | B55: =IF('Все позиции'!B101="","",'Все позиции'!B101) -> 3.19 | C55: =IF('Все позиции'!C101="","",'Все позиции'!C101) -> Демонтаж короба щелевой решетки | D55: =IF('Все позиции'!D101="","",'Все позиции'!D101) -> шт | E55: =IF('Все позиции'!E101="","",'Все позиции'!E101) -> 8 | F55: =IF('Все позиции'!F101="","",'Все позиции'!F101) -> 4200 | G55: =IF('Все позиции'!H101="","",'Все позиции'!H101) -> 8 | H55: =IF('Все позиции'!L101="","",'Все позиции'!L101) -> 2400 | I55: =IF('Все позиции'!O101="","",'Все позиции'!O101) -> -0.42857143 | J55: =IF('Все позиции'!G101="","",'Все позиции'!G101) -> 33600 | K55: =IF('Все позиции'!M101="","",'Все позиции'!M101) -> 19200 | L55: =IF('Все позиции'!N101="","",'Все позиции'!N101) -> -14400 | M55: =IF('Все позиции'!P101="","",'Все позиции'!P101) -> Цена снижена | N55: =IF('Все позиции'!Q101="","",'Все позиции'!Q101) -> непонятно что за работа, расписать | O55: =IF('Все позиции'!R101="","",'Все позиции'!R101) -> щелевой диффузор достать из металлической плитки армстронга.
A56: =IF('Все позиции'!A220="","",'Все позиции'!A220) -> 5. Холодоснабжение 10 этаж | B56: =IF('Все позиции'!B220="","",'Все позиции'!B220) -> 5.17 | C56: =IF('Все позиции'!C220="","",'Все позиции'!C220) -> Труба из сшитого полиэтилена PEX-a, Ø40х5,5 | D56: =IF('Все позиции'!D220="","",'Все позиции'!D220) -> мп | E56: =IF('Все позиции'!E220="","",'Все позиции'!E220) -> 35 | F56: =IF('Все позиции'!F220="","",'Все позиции'!F220) -> 1296 | G56: =IF('Все позиции'!H220="","",'Все позиции'!H220) -> 35 | H56: =IF('Все позиции'!L220="","",'Все позиции'!L220) -> 900 | I56: =IF('Все позиции'!O220="","",'Все позиции'!O220) -> -0.30555556 | J56: =IF('Все позиции'!G220="","",'Все позиции'!G220) -> 45360 | K56: =IF('Все позиции'!M220="","",'Все позиции'!M220) -> 31500 | L56: =IF('Все позиции'!N220="","",'Все позиции'!N220) -> -13860 | M56: =IF('Все позиции'!P220="","",'Все позиции'!P220) -> Цена снижена | N56: =IF('Все позиции'!Q220="","",'Все позиции'!Q220) -> по договору | O56: =IF('Все позиции'!R220="","",'Все позиции'!R220) -> Цена Согласована Марк
A57: =IF('Все позиции'!A221="","",'Все позиции'!A221) -> 5. Холодоснабжение 10 этаж | B57: =IF('Все позиции'!B221="","",'Все позиции'!B221) -> 5.18 | C57: =IF('Все позиции'!C221="","",'Все позиции'!C221) -> Труба из сшитого полиэтилена PEX-a, Ø50х6,9 | D57: =IF('Все позиции'!D221="","",'Все позиции'!D221) -> мп | E57: =IF('Все позиции'!E221="","",'Все позиции'!E221) -> 40 | F57: =IF('Все позиции'!F221="","",'Все позиции'!F221) -> 1296 | G57: =IF('Все позиции'!H221="","",'Все позиции'!H221) -> 40 | H57: =IF('Все позиции'!L221="","",'Все позиции'!L221) -> 950 | I57: =IF('Все позиции'!O221="","",'Все позиции'!O221) -> -0.26697531 | J57: =IF('Все позиции'!G221="","",'Все позиции'!G221) -> 51840 | K57: =IF('Все позиции'!M221="","",'Все позиции'!M221) -> 38000 | L57: =IF('Все позиции'!N221="","",'Все позиции'!N221) -> -13840 | M57: =IF('Все позиции'!P221="","",'Все позиции'!P221) -> Цена снижена | N57: =IF('Все позиции'!Q221="","",'Все позиции'!Q221) -> по договору | O57: =IF('Все позиции'!R221="","",'Все позиции'!R221) -> Цена Согласована Марк
A58: =IF('Все позиции'!A305="","",'Все позиции'!A305) -> 6. Вентиляция 2 этаж | B58: =IF('Все позиции'!B305="","",'Все позиции'!B305) -> 6.65 | C58: =IF('Все позиции'!C305="","",'Все позиции'!C305) -> Ниппель из оцинкованной стали толщиной 0,5мм, класса «В», Ø100 | D58: =IF('Все позиции'!D305="","",'Все позиции'!D305) -> шт. | E58: =IF('Все позиции'!E305="","",'Все позиции'!E305) -> 20 | F58: =IF('Все позиции'!F305="","",'Все позиции'!F305) -> 1020 | G58: =IF('Все позиции'!H305="","",'Все позиции'!H305) -> 20 | H58: =IF('Все позиции'!L305="","",'Все позиции'!L305) -> 370 | I58: =IF('Все позиции'!O305="","",'Все позиции'!O305) -> -0.6372549 | J58: =IF('Все позиции'!G305="","",'Все позиции'!G305) -> 20400 | K58: =IF('Все позиции'!M305="","",'Все позиции'!M305) -> 7400 | L58: =IF('Все позиции'!N305="","",'Все позиции'!N305) -> -13000 | M58: =IF('Все позиции'!P305="","",'Все позиции'!P305) -> Цена снижена | N58: =IF('Все позиции'!Q305="","",'Все позиции'!Q305) | O58: =IF('Все позиции'!R305="","",'Все позиции'!R305)
A59: =IF('Все позиции'!A306="","",'Все позиции'!A306) -> 6. Вентиляция 2 этаж | B59: =IF('Все позиции'!B306="","",'Все позиции'!B306) -> 6.66 | C59: =IF('Все позиции'!C306="","",'Все позиции'!C306) -> Ниппель из оцинкованной стали толщиной 0,5мм, класса «В», Ø125 | D59: =IF('Все позиции'!D306="","",'Все позиции'!D306) -> шт. | E59: =IF('Все позиции'!E306="","",'Все позиции'!E306) -> 20 | F59: =IF('Все позиции'!F306="","",'Все позиции'!F306) -> 1020 | G59: =IF('Все позиции'!H306="","",'Все позиции'!H306) -> 20 | H59: =IF('Все позиции'!L306="","",'Все позиции'!L306) -> 370 | I59: =IF('Все позиции'!O306="","",'Все позиции'!O306) -> -0.6372549 | J59: =IF('Все позиции'!G306="","",'Все позиции'!G306) -> 20400 | K59: =IF('Все позиции'!M306="","",'Все позиции'!M306) -> 7400 | L59: =IF('Все позиции'!N306="","",'Все позиции'!N306) -> -13000 | M59: =IF('Все позиции'!P306="","",'Все позиции'!P306) -> Цена снижена | N59: =IF('Все позиции'!Q306="","",'Все позиции'!Q306) | O59: =IF('Все позиции'!R306="","",'Все позиции'!R306)
A60: =IF('Все позиции'!A96="","",'Все позиции'!A96) -> 3. Дополнительные работы 3,7,8,9 этаж | B60: =IF('Все позиции'!B96="","",'Все позиции'!B96) -> 3.14 | C60: =IF('Все позиции'!C96="","",'Все позиции'!C96) -> Перемонтаж вентканалов | D60: =IF('Все позиции'!D96="","",'Все позиции'!D96) -> мп | E60: =IF('Все позиции'!E96="","",'Все позиции'!E96) -> 61.6 | F60: =IF('Все позиции'!F96="","",'Все позиции'!F96) -> 1120 | G60: =IF('Все позиции'!H96="","",'Все позиции'!H96) -> 61.6 | H60: =IF('Все позиции'!L96="","",'Все позиции'!L96) -> 920 | I60: =IF('Все позиции'!O96="","",'Все позиции'!O96) -> -0.17857143 | J60: =IF('Все позиции'!G96="","",'Все позиции'!G96) -> 68992 | K60: =IF('Все позиции'!M96="","",'Все позиции'!M96) -> 56672 | L60: =IF('Все позиции'!N96="","",'Все позиции'!N96) -> -12320 | M60: =IF('Все позиции'!P96="","",'Все позиции'!P96) -> Цена снижена | N60: =IF('Все позиции'!Q96="","",'Все позиции'!Q96) -> Какие размеры? | O60: =IF('Все позиции'!R96="","",'Все позиции'!R96) -> Цена Согласована Марк
A61: =IF('Все позиции'!A191="","",'Все позиции'!A191) -> 4. Вентиляция 10 этаж | B61: =IF('Все позиции'!B191="","",'Все позиции'!B191) -> 4.78 | C61: =IF('Все позиции'!C191="","",'Все позиции'!C191) -> Ниппель из оцинкованной стали толщиной 0,5мм, класса «В», Ø160 | D61: =IF('Все позиции'!D191="","",'Все позиции'!D191) -> шт. | E61: =IF('Все позиции'!E191="","",'Все позиции'!E191) -> 17 | F61: =IF('Все позиции'!F191="","",'Все позиции'!F191) -> 1020 | G61: =IF('Все позиции'!H191="","",'Все позиции'!H191) -> 17 | H61: =IF('Все позиции'!L191="","",'Все позиции'!L191) -> 370 | I61: =IF('Все позиции'!O191="","",'Все позиции'!O191) -> -0.6372549 | J61: =IF('Все позиции'!G191="","",'Все позиции'!G191) -> 17340 | K61: =IF('Все позиции'!M191="","",'Все позиции'!M191) -> 6290 | L61: =IF('Все позиции'!N191="","",'Все позиции'!N191) -> -11050 | M61: =IF('Все позиции'!P191="","",'Все позиции'!P191) -> Цена снижена | N61: =IF('Все позиции'!Q191="","",'Все позиции'!Q191) | O61: =IF('Все позиции'!R191="","",'Все позиции'!R191)
A62: =IF('Все позиции'!A225="","",'Все позиции'!A225) -> 5. Холодоснабжение 10 этаж | B62: =IF('Все позиции'!B225="","",'Все позиции'!B225) -> 5.22 | C62: =IF('Все позиции'!C225="","",'Все позиции'!C225) -> Муфта полипропиленовая, 32 | D62: =IF('Все позиции'!D225="","",'Все позиции'!D225) -> шт. | E62: =IF('Все позиции'!E225="","",'Все позиции'!E225) -> 20 | F62: =IF('Все позиции'!F225="","",'Все позиции'!F225) -> 1020 | G62: =IF('Все позиции'!H225="","",'Все позиции'!H225) -> 20 | H62: =IF('Все позиции'!L225="","",'Все позиции'!L225) -> 520 | I62: =IF('Все позиции'!O225="","",'Все позиции'!O225) -> -0.49019608 | J62: =IF('Все позиции'!G225="","",'Все позиции'!G225) -> 20400 | K62: =IF('Все позиции'!M225="","",'Все позиции'!M225) -> 10400 | L62: =IF('Все позиции'!N225="","",'Все позиции'!N225) -> -10000 | M62: =IF('Все позиции'!P225="","",'Все позиции'!P225) -> Цена снижена | N62: =IF('Все позиции'!Q225="","",'Все позиции'!Q225) | O62: =IF('Все позиции'!R225="","",'Все позиции'!R225) -> Цена Согласована Марк
A63: =IF('Все позиции'!A201="","",'Все позиции'!A201) -> 4. Дымоудаление (10 этаж) | B63: =IF('Все позиции'!B201="","",'Все позиции'!B201) -> 4.87 | C63: =IF('Все позиции'!C201="","",'Все позиции'!C201) -> Отвод 90гр 800*500 | D63: =IF('Все позиции'!D201="","",'Все позиции'!D201) -> шт. | E63: =IF('Все позиции'!E201="","",'Все позиции'!E201) -> 1 | F63: =IF('Все позиции'!F201="","",'Все позиции'!F201) -> 9600 | G63: =IF('Все позиции'!H201="","",'Все позиции'!H201) -> 1 | H63: =IF('Все позиции'!L201="","",'Все позиции'!L201) | I63: =IF('Все позиции'!O201="","",'Все позиции'!O201) -> -1 | J63: =IF('Все позиции'!G201="","",'Все позиции'!G201) -> 9600 | K63: =IF('Все позиции'!M201="","",'Все позиции'!M201) -> 0 | L63: =IF('Все позиции'!N201="","",'Все позиции'!N201) -> -9600 | M63: =IF('Все позиции'!P201="","",'Все позиции'!P201) -> Исключено → отдельный допник | N63: =IF('Все позиции'!Q201="","",'Все позиции'!Q201) -> удалить (если будут данные позиции сделаем отдельный допник) | O63: =IF('Все позиции'!R201="","",'Все позиции'!R201)
A64: =IF('Все позиции'!A170="","",'Все позиции'!A170) -> 4. Вентиляция 10 этаж | B64: =IF('Все позиции'!B170="","",'Все позиции'!B170) -> 4.57 | C64: =IF('Все позиции'!C170="","",'Все позиции'!C170) -> Врезка плоская из оцинкованной стали толщиной 0,5мм, класса «В», Ø160 | D64: =IF('Все позиции'!D170="","",'Все позиции'!D170) -> шт. | E64: =IF('Все позиции'!E170="","",'Все позиции'!E170) -> 14 | F64: =IF('Все позиции'!F170="","",'Все позиции'!F170) -> 1020 | G64: =IF('Все позиции'!H170="","",'Все позиции'!H170) -> 14 | H64: =IF('Все позиции'!L170="","",'Все позиции'!L170) -> 370 | I64: =IF('Все позиции'!O170="","",'Все позиции'!O170) -> -0.6372549 | J64: =IF('Все позиции'!G170="","",'Все позиции'!G170) -> 14280 | K64: =IF('Все позиции'!M170="","",'Все позиции'!M170) -> 5180 | L64: =IF('Все позиции'!N170="","",'Все позиции'!N170) -> -9100 | M64: =IF('Все позиции'!P170="","",'Все позиции'!P170) -> Цена снижена | N64: =IF('Все позиции'!Q170="","",'Все позиции'!Q170) | O64: =IF('Все позиции'!R170="","",'Все позиции'!R170)
A65: =IF('Все позиции'!A147="","",'Все позиции'!A147) -> 4. Вентиляция 10 этаж | B65: =IF('Все позиции'!B147="","",'Все позиции'!B147) -> 4.34 | C65: =IF('Все позиции'!C147="","",'Все позиции'!C147) -> Воздуховод из оцинкованной стали толщиной 0,7мм, класса «В», 700x250 | D65: =IF('Все позиции'!D147="","",'Все позиции'!D147) -> мп | E65: =IF('Все позиции'!E147="","",'Все позиции'!E147) -> 18 | F65: =IF('Все позиции'!F147="","",'Все позиции'!F147) -> 3726 | G65: =IF('Все позиции'!H147="","",'Все позиции'!H147) -> 18 | H65: =IF('Все позиции'!L147="","",'Все позиции'!L147) -> 3230 | I65: =IF('Все позиции'!O147="","",'Все позиции'!O147) -> -0.13311863 | J65: =IF('Все позиции'!G147="","",'Все позиции'!G147) -> 67068 | K65: =IF('Все позиции'!M147="","",'Все позиции'!M147) -> 58140 | L65: =IF('Все позиции'!N147="","",'Все позиции'!N147) -> -8928 | M65: =IF('Все позиции'!P147="","",'Все позиции'!P147) -> Цена снижена | N65: =IF('Все позиции'!Q147="","",'Все позиции'!Q147) | O65: =IF('Все позиции'!R147="","",'Все позиции'!R147)
A66: =IF('Все позиции'!A325="","",'Все позиции'!A325) -> 7. Холодоснабжение 2 этаж | B66: =IF('Все позиции'!B325="","",'Все позиции'!B325) -> 7.5 | C66: =IF('Все позиции'!C325="","",'Все позиции'!C325) -> Комбинированный балансировочный клапан, Ду20 | D66: =IF('Все позиции'!D325="","",'Все позиции'!D325) -> шт. | E66: =IF('Все позиции'!E325="","",'Все позиции'!E325) -> 31 | F66: =IF('Все позиции'!F325="","",'Все позиции'!F325) -> 2268 | G66: =IF('Все позиции'!H325="","",'Все позиции'!H325) -> 31 | H66: =IF('Все позиции'!L325="","",'Все позиции'!L325) -> 1994 | I66: =IF('Все позиции'!O325="","",'Все позиции'!O325) -> -0.12081129 | J66: =IF('Все позиции'!G325="","",'Все позиции'!G325) -> 70308 | K66: =IF('Все позиции'!M325="","",'Все позиции'!M325) -> 61814 | L66: =IF('Все позиции'!N325="","",'Все позиции'!N325) -> -8494 | M66: =IF('Все позиции'!P325="","",'Все позиции'!P325) -> Цена снижена | N66: =IF('Все позиции'!Q325="","",'Все позиции'!Q325) -> в п.5.5 стоит 1944 | O66: =IF('Все позиции'!R325="","",'Все позиции'!R325)
A67: =IF('Все позиции'!A326="","",'Все позиции'!A326) -> 7. Холодоснабжение 2 этаж | B67: =IF('Все позиции'!B326="","",'Все позиции'!B326) -> 7.6 | C67: =IF('Все позиции'!C326="","",'Все позиции'!C326) -> Комплект трехходовой клапан, запорные краны, медные патрубки | D67: =IF('Все позиции'!D326="","",'Все позиции'!D326) -> шт. | E67: =IF('Все позиции'!E326="","",'Все позиции'!E326) -> 31 | F67: =IF('Все позиции'!F326="","",'Все позиции'!F326) -> 2268 | G67: =IF('Все позиции'!H326="","",'Все позиции'!H326) -> 31 | H67: =IF('Все позиции'!L326="","",'Все позиции'!L326) -> 1994 | I67: =IF('Все позиции'!O326="","",'Все позиции'!O326) -> -0.12081129 | J67: =IF('Все позиции'!G326="","",'Все позиции'!G326) -> 70308 | K67: =IF('Все позиции'!M326="","",'Все позиции'!M326) -> 61814 | L67: =IF('Все позиции'!N326="","",'Все позиции'!N326) -> -8494 | M67: =IF('Все позиции'!P326="","",'Все позиции'!P326) -> Цена снижена | N67: =IF('Все позиции'!Q326="","",'Все позиции'!Q326) -> в п.5.5 стоит 1944 | O67: =IF('Все позиции'!R326="","",'Все позиции'!R326)
A68: =IF('Все позиции'!A222="","",'Все позиции'!A222) -> 5. Холодоснабжение 10 этаж | B68: =IF('Все позиции'!B222="","",'Все позиции'!B222) -> 5.19 | C68: =IF('Все позиции'!C222="","",'Все позиции'!C222) -> Трубки теплоизоляционные для трубы Ø32х4,4 толщиной 9мм | D68: =IF('Все позиции'!D222="","",'Все позиции'!D222) -> мп | E68: =IF('Все позиции'!E222="","",'Все позиции'!E222) -> 90 | F68: =IF('Все позиции'!F222="","",'Все позиции'!F222) -> 291.6 | G68: =IF('Все позиции'!H222="","",'Все позиции'!H222) -> 90 | H68: =IF('Все позиции'!L222="","",'Все позиции'!L222) -> 200 | I68: =IF('Все позиции'!O222="","",'Все позиции'!O222) -> -0.31412894 | J68: =IF('Все позиции'!G222="","",'Все позиции'!G222) -> 26244 | K68: =IF('Все позиции'!M222="","",'Все позиции'!M222) -> 18000 | L68: =IF('Все позиции'!N222="","",'Все позиции'!N222) -> -8244 | M68: =IF('Все позиции'!P222="","",'Все позиции'!P222) -> Цена снижена | N68: =IF('Все позиции'!Q222="","",'Все позиции'!Q222) -> по договору | O68: =IF('Все позиции'!R222="","",'Все позиции'!R222) -> Цена Согласована Марк
A69: =IF('Все позиции'!A136="","",'Все позиции'!A136) -> 4. Вентиляция 10 этаж | B69: =IF('Все позиции'!B136="","",'Все позиции'!B136) -> 4.23 | C69: =IF('Все позиции'!C136="","",'Все позиции'!C136) -> Воздуховод из оцинкованной стали толщиной 0,5мм, класса «В», Ø100 | D69: =IF('Все позиции'!D136="","",'Все позиции'!D136) -> мп | E69: =IF('Все позиции'!E136="","",'Все позиции'!E136) -> 19 | F69: =IF('Все позиции'!F136="","",'Все позиции'!F136) -> 1360.8 | G69: =IF('Все позиции'!H136="","",'Все позиции'!H136) -> 19 | H69: =IF('Все позиции'!L136="","",'Все позиции'!L136) -> 950 | I69: =IF('Все позиции'!O136="","",'Все позиции'!O136) -> -0.30188125 | J69: =IF('Все позиции'!G136="","",'Все позиции'!G136) -> 25855.2 | K69: =IF('Все позиции'!M136="","",'Все позиции'!M136) -> 18050 | L69: =IF('Все позиции'!N136="","",'Все позиции'!N136) -> -7805.2 | M69: =IF('Все позиции'!P136="","",'Все позиции'!P136) -> Цена снижена | N69: =IF('Все позиции'!Q136="","",'Все позиции'!Q136) -> по договору | O69: =IF('Все позиции'!R136="","",'Все позиции'!R136)
A70: =IF('Все позиции'!A171="","",'Все позиции'!A171) -> 4. Вентиляция 10 этаж | B70: =IF('Все позиции'!B171="","",'Все позиции'!B171) -> 4.58 | C70: =IF('Все позиции'!C171="","",'Все позиции'!C171) -> Врезка плоская из оцинкованной стали толщиной 0,5мм, класса «В», Ø200 | D70: =IF('Все позиции'!D171="","",'Все позиции'!D171) -> шт. | E70: =IF('Все позиции'!E171="","",'Все позиции'!E171) -> 12 | F70: =IF('Все позиции'!F171="","",'Все позиции'!F171) -> 1020 | G70: =IF('Все позиции'!H171="","",'Все позиции'!H171) -> 12 | H70: =IF('Все позиции'!L171="","",'Все позиции'!L171) -> 370 | I70: =IF('Все позиции'!O171="","",'Все позиции'!O171) -> -0.6372549 | J70: =IF('Все позиции'!G171="","",'Все позиции'!G171) -> 12240 | K70: =IF('Все позиции'!M171="","",'Все позиции'!M171) -> 4440 | L70: =IF('Все позиции'!N171="","",'Все позиции'!N171) -> -7800 | M70: =IF('Все позиции'!P171="","",'Все позиции'!P171) -> Цена снижена | N70: =IF('Все позиции'!Q171="","",'Все позиции'!Q171) | O70: =IF('Все позиции'!R171="","",'Все позиции'!R171)
A71: =IF('Все позиции'!A192="","",'Все позиции'!A192) -> 4. Вентиляция 10 этаж | B71: =IF('Все позиции'!B192="","",'Все позиции'!B192) -> 4.79 | C71: =IF('Все позиции'!C192="","",'Все позиции'!C192) -> Ниппель из оцинкованной стали толщиной 0,5мм, класса «В», Ø200 | D71: =IF('Все позиции'!D192="","",'Все позиции'!D192) -> шт. | E71: =IF('Все позиции'!E192="","",'Все позиции'!E192) -> 12 | F71: =IF('Все позиции'!F192="","",'Все позиции'!F192) -> 1020 | G71: =IF('Все позиции'!H192="","",'Все позиции'!H192) -> 12 | H71: =IF('Все позиции'!L192="","",'Все позиции'!L192) -> 370 | I71: =IF('Все позиции'!O192="","",'Все позиции'!O192) -> -0.6372549 | J71: =IF('Все позиции'!G192="","",'Все позиции'!G192) -> 12240 | K71: =IF('Все позиции'!M192="","",'Все позиции'!M192) -> 4440 | L71: =IF('Все позиции'!N192="","",'Все позиции'!N192) -> -7800 | M71: =IF('Все позиции'!P192="","",'Все позиции'!P192) -> Цена снижена | N71: =IF('Все позиции'!Q192="","",'Все позиции'!Q192) | O71: =IF('Все позиции'!R192="","",'Все позиции'!R192)
A72: =IF('Все позиции'!A327="","",'Все позиции'!A327) -> 7. Холодоснабжение 2 этаж | B72: =IF('Все позиции'!B327="","",'Все позиции'!B327) -> 7.7 | C72: =IF('Все позиции'!C327="","",'Все позиции'!C327) -> теплоизоляция труб | D72: =IF('Все позиции'!D327="","",'Все позиции'!D327) -> м.п. | E72: =IF('Все позиции'!E327="","",'Все позиции'!E327) -> 30 | F72: =IF('Все позиции'!F327="","",'Все позиции'!F327) -> 486 | G72: =IF('Все позиции'!H327="","",'Все позиции'!H327) -> 30 | H72: =IF('Все позиции'!L327="","",'Все позиции'!L327) -> 228 | I72: =IF('Все позиции'!O327="","",'Все позиции'!O327) -> -0.5308642 | J72: =IF('Все позиции'!G327="","",'Все позиции'!G327) -> 14580 | K72: =IF('Все позиции'!M327="","",'Все позиции'!M327) -> 6840 | L72: =IF('Все позиции'!N327="","",'Все позиции'!N327) -> -7740 | M72: =IF('Все позиции'!P327="","",'Все позиции'!P327) -> Снижение согласовано, но не внесено в итог | N72: =IF('Все позиции'!Q327="","",'Все позиции'!Q327) -> по договору | O72: =IF('Все позиции'!R327="","",'Все позиции'!R327) -> Цена Согласована Марк
A73: =IF('Все позиции'!A228="","",'Все позиции'!A228) -> 5. Холодоснабжение 10 этаж | B73: =IF('Все позиции'!B228="","",'Все позиции'!B228) -> 5.25 | C73: =IF('Все позиции'!C228="","",'Все позиции'!C228) -> Угольник 450 полипропиленовый, 32 | D73: =IF('Все позиции'!D228="","",'Все позиции'!D228) -> шт. | E73: =IF('Все позиции'!E228="","",'Все позиции'!E228) -> 15 | F73: =IF('Все позиции'!F228="","",'Все позиции'!F228) -> 1020 | G73: =IF('Все позиции'!H228="","",'Все позиции'!H228) -> 15 | H73: =IF('Все позиции'!L228="","",'Все позиции'!L228) -> 520 | I73: =IF('Все позиции'!O228="","",'Все позиции'!O228) -> -0.49019608 | J73: =IF('Все позиции'!G228="","",'Все позиции'!G228) -> 15300 | K73: =IF('Все позиции'!M228="","",'Все позиции'!M228) -> 7800 | L73: =IF('Все позиции'!N228="","",'Все позиции'!N228) -> -7500 | M73: =IF('Все позиции'!P228="","",'Все позиции'!P228) -> Цена снижена | N73: =IF('Все позиции'!Q228="","",'Все позиции'!Q228) | O73: =IF('Все позиции'!R228="","",'Все позиции'!R228) -> Цена Согласована Марк
A74: =IF('Все позиции'!A307="","",'Все позиции'!A307) -> 6. Вентиляция 2 этаж | B74: =IF('Все позиции'!B307="","",'Все позиции'!B307) -> 6.67 | C74: =IF('Все позиции'!C307="","",'Все позиции'!C307) -> Ниппель из оцинкованной стали толщиной 0,5мм, класса «В», Ø160 | D74: =IF('Все позиции'!D307="","",'Все позиции'!D307) -> шт. | E74: =IF('Все позиции'!E307="","",'Все позиции'!E307) -> 10 | F74: =IF('Все позиции'!F307="","",'Все позиции'!F307) -> 1020 | G74: =IF('Все позиции'!H307="","",'Все позиции'!H307) -> 10 | H74: =IF('Все позиции'!L307="","",'Все позиции'!L307) -> 370 | I74: =IF('Все позиции'!O307="","",'Все позиции'!O307) -> -0.6372549 | J74: =IF('Все позиции'!G307="","",'Все позиции'!G307) -> 10200 | K74: =IF('Все позиции'!M307="","",'Все позиции'!M307) -> 3700 | L74: =IF('Все позиции'!N307="","",'Все позиции'!N307) -> -6500 | M74: =IF('Все позиции'!P307="","",'Все позиции'!P307) -> Цена снижена | N74: =IF('Все позиции'!Q307="","",'Все позиции'!Q307) | O74: =IF('Все позиции'!R307="","",'Все позиции'!R307)
A75: =IF('Все позиции'!A308="","",'Все позиции'!A308) -> 6. Вентиляция 2 этаж | B75: =IF('Все позиции'!B308="","",'Все позиции'!B308) -> 6.68 | C75: =IF('Все позиции'!C308="","",'Все позиции'!C308) -> Ниппель из оцинкованной стали толщиной 0,5мм, класса «В», Ø200 | D75: =IF('Все позиции'!D308="","",'Все позиции'!D308) -> шт. | E75: =IF('Все позиции'!E308="","",'Все позиции'!E308) -> 10 | F75: =IF('Все позиции'!F308="","",'Все позиции'!F308) -> 1020 | G75: =IF('Все позиции'!H308="","",'Все позиции'!H308) -> 10 | H75: =IF('Все позиции'!L308="","",'Все позиции'!L308) -> 370 | I75: =IF('Все позиции'!O308="","",'Все позиции'!O308) -> -0.6372549 | J75: =IF('Все позиции'!G308="","",'Все позиции'!G308) -> 10200 | K75: =IF('Все позиции'!M308="","",'Все позиции'!M308) -> 3700 | L75: =IF('Все позиции'!N308="","",'Все позиции'!N308) -> -6500 | M75: =IF('Все позиции'!P308="","",'Все позиции'!P308) -> Цена снижена | N75: =IF('Все позиции'!Q308="","",'Все позиции'!Q308) | O75: =IF('Все позиции'!R308="","",'Все позиции'!R308)
A76: =IF('Все позиции'!A245="","",'Все позиции'!A245) -> 6. Вентиляция 2 этаж | B76: =IF('Все позиции'!B245="","",'Все позиции'!B245) -> 6.5 | C76: =IF('Все позиции'!C245="","",'Все позиции'!C245) -> Диффузор круглый, Ø125 ЛК 125 | D76: =IF('Все позиции'!D245="","",'Все позиции'!D245) -> шт. | E76: =IF('Все позиции'!E245="","",'Все позиции'!E245) -> 9 | F76: =IF('Все позиции'!F245="","",'Все позиции'!F245) -> 1296 | G76: =IF('Все позиции'!H245="","",'Все позиции'!H245) -> 9 | H76: =IF('Все позиции'!L245="","",'Все позиции'!L245) -> 600 | I76: =IF('Все позиции'!O245="","",'Все позиции'!O245) -> -0.53703704 | J76: =IF('Все позиции'!G245="","",'Все позиции'!G245) -> 11664 | K76: =IF('Все позиции'!M245="","",'Все позиции'!M245) -> 5400 | L76: =IF('Все позиции'!N245="","",'Все позиции'!N245) -> -6264 | M76: =IF('Все позиции'!P245="","",'Все позиции'!P245) -> Цена снижена | N76: =IF('Все позиции'!Q245="","",'Все позиции'!Q245) -> по договору | O76: =IF('Все позиции'!R245="","",'Все позиции'!R245)
A77: =IF('Все позиции'!A237="","",'Все позиции'!A237) -> 5. Холодоснабжение 10 этаж | B77: =IF('Все позиции'!B237="","",'Все позиции'!B237) -> 5.34 | C77: =IF('Все позиции'!C237="","",'Все позиции'!C237) -> Трубки теплоизоляционные для трубы Ø40х6,7 толщиной 6мм | D77: =IF('Все позиции'!D237="","",'Все позиции'!D237) -> шт. | E77: =IF('Все позиции'!E237="","",'Все позиции'!E237) -> 8 | F77: =IF('Все позиции'!F237="","",'Все позиции'!F237) -> 1020 | G77: =IF('Все позиции'!H237="","",'Все позиции'!H237) -> 8 | H77: =IF('Все позиции'!L237="","",'Все позиции'!L237) -> 260 | I77: =IF('Все позиции'!O237="","",'Все позиции'!O237) -> -0.74509804 | J77: =IF('Все позиции'!G237="","",'Все позиции'!G237) -> 8160 | K77: =IF('Все позиции'!M237="","",'Все позиции'!M237) -> 2080 | L77: =IF('Все позиции'!N237="","",'Все позиции'!N237) -> -6080 | M77: =IF('Все позиции'!P237="","",'Все позиции'!P237) -> Цена снижена | N77: =IF('Все позиции'!Q237="","",'Все позиции'!Q237) -> по договору | O77: =IF('Все позиции'!R237="","",'Все позиции'!R237) -> Цена Согласована Марк
A78: =IF('Все позиции'!A217="","",'Все позиции'!A217) -> 5. Холодоснабжение 10 этаж | B78: =IF('Все позиции'!B217="","",'Все позиции'!B217) -> 5.14 | C78: =IF('Все позиции'!C217="","",'Все позиции'!C217) -> Муфта полипропиленовая 32 x 1/2" | D78: =IF('Все позиции'!D217="","",'Все позиции'!D217) -> шт. | E78: =IF('Все позиции'!E217="","",'Все позиции'!E217) -> 10 | F78: =IF('Все позиции'!F217="","",'Все позиции'!F217) -> 1296 | G78: =IF('Все позиции'!H217="","",'Все позиции'!H217) -> 10 | H78: =IF('Все позиции'!L217="","",'Все позиции'!L217) -> 700 | I78: =IF('Все позиции'!O217="","",'Все позиции'!O217) -> -0.45987654 | J78: =IF('Все позиции'!G217="","",'Все позиции'!G217) -> 12960 | K78: =IF('Все позиции'!M217="","",'Все позиции'!M217) -> 7000 | L78: =IF('Все позиции'!N217="","",'Все позиции'!N217) -> -5960 | M78: =IF('Все позиции'!P217="","",'Все позиции'!P217) -> Цена снижена | N78: =IF('Все позиции'!Q217="","",'Все позиции'!Q217) | O78: =IF('Все позиции'!R217="","",'Все позиции'!R217) -> Цена Согласована Марк
A79: =IF('Все позиции'!A218="","",'Все позиции'!A218) -> 5. Холодоснабжение 10 этаж | B79: =IF('Все позиции'!B218="","",'Все позиции'!B218) -> 5.15 | C79: =IF('Все позиции'!C218="","",'Все позиции'!C218) -> Штуцер 1/2" x 14мм | D79: =IF('Все позиции'!D218="","",'Все позиции'!D218) -> шт. | E79: =IF('Все позиции'!E218="","",'Все позиции'!E218) -> 10 | F79: =IF('Все позиции'!F218="","",'Все позиции'!F218) -> 1296 | G79: =IF('Все позиции'!H218="","",'Все позиции'!H218) -> 10 | H79: =IF('Все позиции'!L218="","",'Все позиции'!L218) -> 700 | I79: =IF('Все позиции'!O218="","",'Все позиции'!O218) -> -0.45987654 | J79: =IF('Все позиции'!G218="","",'Все позиции'!G218) -> 12960 | K79: =IF('Все позиции'!M218="","",'Все позиции'!M218) -> 7000 | L79: =IF('Все позиции'!N218="","",'Все позиции'!N218) -> -5960 | M79: =IF('Все позиции'!P218="","",'Все позиции'!P218) -> Цена снижена | N79: =IF('Все позиции'!Q218="","",'Все позиции'!Q218) | O79: =IF('Все позиции'!R218="","",'Все позиции'!R218) -> Цена Согласована Марк
A80: =IF('Все позиции'!A244="","",'Все позиции'!A244) -> 6. Вентиляция 2 этаж | B80: =IF('Все позиции'!B244="","",'Все позиции'!B244) -> 6.4 | C80: =IF('Все позиции'!C244="","",'Все позиции'!C244) -> Диффузор круглый, Ø100 ЛК 100 | D80: =IF('Все позиции'!D244="","",'Все позиции'!D244) -> шт. | E80: =IF('Все позиции'!E244="","",'Все позиции'!E244) -> 8 | F80: =IF('Все позиции'!F244="","",'Все позиции'!F244) -> 1296 | G80: =IF('Все позиции'!H244="","",'Все позиции'!H244) -> 8 | H80: =IF('Все позиции'!L244="","",'Все позиции'!L244) -> 600 | I80: =IF('Все позиции'!O244="","",'Все позиции'!O244) -> -0.53703704 | J80: =IF('Все позиции'!G244="","",'Все позиции'!G244) -> 10368 | K80: =IF('Все позиции'!M244="","",'Все позиции'!M244) -> 4800 | L80: =IF('Все позиции'!N244="","",'Все позиции'!N244) -> -5568 | M80: =IF('Все позиции'!P244="","",'Все позиции'!P244) -> Цена снижена | N80: =IF('Все позиции'!Q244="","",'Все позиции'!Q244) -> по договору | O80: =IF('Все позиции'!R244="","",'Все позиции'!R244)
A81: =IF('Все позиции'!A137="","",'Все позиции'!A137) -> 4. Вентиляция 10 этаж | B81: =IF('Все позиции'!B137="","",'Все позиции'!B137) -> 4.24 | C81: =IF('Все позиции'!C137="","",'Все позиции'!C137) -> Воздуховод из оцинкованной стали толщиной 0,5мм, класса «В», Ø125 | D81: =IF('Все позиции'!D137="","",'Все позиции'!D137) -> мп | E81: =IF('Все позиции'!E137="","",'Все позиции'!E137) -> 7 | F81: =IF('Все позиции'!F137="","",'Все позиции'!F137) -> 1360.8 | G81: =IF('Все позиции'!H137="","",'Все позиции'!H137) -> 7 | H81: =IF('Все позиции'!L137="","",'Все позиции'!L137) -> 689.79 | I81: =IF('Все позиции'!O137="","",'Все позиции'!O137) -> -0.49309965 | J81: =IF('Все позиции'!G137="","",'Все позиции'!G137) -> 9525.6 | K81: =IF('Все позиции'!M137="","",'Все позиции'!M137) -> 4828.53 | L81: =IF('Все позиции'!N137="","",'Все позиции'!N137) -> -4697.07 | M81: =IF('Все позиции'!P137="","",'Все позиции'!P137) -> Цена снижена | N81: =IF('Все позиции'!Q137="","",'Все позиции'!Q137) -> по договору | O81: =IF('Все позиции'!R137="","",'Все позиции'!R137)
A82: =IF('Все позиции'!A248="","",'Все позиции'!A248) -> 6. Вентиляция 2 этаж | B82: =IF('Все позиции'!B248="","",'Все позиции'!B248) -> 6.8 | C82: =IF('Все позиции'!C248="","",'Все позиции'!C248) -> Регулятор расхода воздуха, Ø100 КВК 100 | D82: =IF('Все позиции'!D248="","",'Все позиции'!D248) -> шт. | E82: =IF('Все позиции'!E248="","",'Все позиции'!E248) -> 11 | F82: =IF('Все позиции'!F248="","",'Все позиции'!F248) -> 1377 | G82: =IF('Все позиции'!H248="","",'Все позиции'!H248) -> 11 | H82: =IF('Все позиции'!L248="","",'Все позиции'!L248) -> 950 | I82: =IF('Все позиции'!O248="","",'Все позиции'!O248) -> -0.31009441 | J82: =IF('Все позиции'!G248="","",'Все позиции'!G248) -> 15147 | K82: =IF('Все позиции'!M248="","",'Все позиции'!M248) -> 10450 | L82: =IF('Все позиции'!N248="","",'Все позиции'!N248) -> -4697 | M82: =IF('Все позиции'!P248="","",'Все позиции'!P248) -> Цена снижена | N82: =IF('Все позиции'!Q248="","",'Все позиции'!Q248) -> по договору | O82: =IF('Все позиции'!R248="","",'Все позиции'!R248)
A83: =IF('Все позиции'!A124="","",'Все позиции'!A124) -> 4. Вентиляция 10 этаж | B83: =IF('Все позиции'!B124="","",'Все позиции'!B124) -> 4.11 | C83: =IF('Все позиции'!C124="","",'Все позиции'!C124) -> Адаптер для щелевой решетки с регулятором расхода, подключение 160мм два патрубка и увеличенным патрубком, 1000мм Адаптер для ЛРЩ 22-1-1500 y=67мм + подключение 2х160мм + заслонка | D83: =IF('Все позиции'!D124="","",'Все позиции'!D124) -> шт. | E83: =IF('Все позиции'!E124="","",'Все позиции'!E124) -> 1 | F83: =IF('Все позиции'!F124="","",'Все позиции'!F124) -> 6156 | G83: =IF('Все позиции'!H124="","",'Все позиции'!H124) -> 1 | H83: =IF('Все позиции'!L124="","",'Все позиции'!L124) -> 1500 | I83: =IF('Все позиции'!O124="","",'Все позиции'!O124) -> -0.75633528 | J83: =IF('Все позиции'!G124="","",'Все позиции'!G124) -> 6156 | K83: =IF('Все позиции'!M124="","",'Все позиции'!M124) -> 1500 | L83: =IF('Все позиции'!N124="","",'Все позиции'!N124) -> -4656 | M83: =IF('Все позиции'!P124="","",'Все позиции'!P124) -> Цена снижена | N83: =IF('Все позиции'!Q124="","",'Все позиции'!Q124) -> расценка сильно завышена | O83: =IF('Все позиции'!R124="","",'Все позиции'!R124)
A84: =IF('Все позиции'!A126="","",'Все позиции'!A126) -> 4. Вентиляция 10 этаж | B84: =IF('Все позиции'!B126="","",'Все позиции'!B126) -> 4.13 | C84: =IF('Все позиции'!C126="","",'Все позиции'!C126) -> Адаптер для щелевой решетки с регулятором расхода и увеличенным патрубком, 500мм Адаптер для ЛРЩ 22-1-500 y=67мм + заслонка | D84: =IF('Все позиции'!D126="","",'Все позиции'!D126) -> шт. | E84: =IF('Все позиции'!E126="","",'Все позиции'!E126) -> 1 | F84: =IF('Все позиции'!F126="","",'Все позиции'!F126) -> 6156 | G84: =IF('Все позиции'!H126="","",'Все позиции'!H126) -> 1 | H84: =IF('Все позиции'!L126="","",'Все позиции'!L126) -> 1500 | I84: =IF('Все позиции'!O126="","",'Все позиции'!O126) -> -0.75633528 | J84: =IF('Все позиции'!G126="","",'Все позиции'!G126) -> 6156 | K84: =IF('Все позиции'!M126="","",'Все позиции'!M126) -> 1500 | L84: =IF('Все позиции'!N126="","",'Все позиции'!N126) -> -4656 | M84: =IF('Все позиции'!P126="","",'Все позиции'!P126) -> Цена снижена | N84: =IF('Все позиции'!Q126="","",'Все позиции'!Q126) -> расценка сильно завышена | O84: =IF('Все позиции'!R126="","",'Все позиции'!R126)
A85: =IF('Все позиции'!A324="","",'Все позиции'!A324) -> 7. Холодоснабжение 2 этаж | B85: =IF('Все позиции'!B324="","",'Все позиции'!B324) -> 7.4 | C85: =IF('Все позиции'!C324="","",'Все позиции'!C324) -> Воздухоотводчик автоматический, Ду15 Airvent-R | D85: =IF('Все позиции'!D324="","",'Все позиции'!D324) -> шт. | E85: =IF('Все позиции'!E324="","",'Все позиции'!E324) -> 4 | F85: =IF('Все позиции'!F324="","",'Все позиции'!F324) -> 1620 | G85: =IF('Все позиции'!H324="","",'Все позиции'!H324) -> 4 | H85: =IF('Все позиции'!L324="","",'Все позиции'!L324) -> 500 | I85: =IF('Все позиции'!O324="","",'Все позиции'!O324) -> -0.69135802 | J85: =IF('Все позиции'!G324="","",'Все позиции'!G324) -> 6480 | K85: =IF('Все позиции'!M324="","",'Все позиции'!M324) -> 2000 | L85: =IF('Все позиции'!N324="","",'Все позиции'!N324) -> -4480 | M85: =IF('Все позиции'!P324="","",'Все позиции'!P324) -> Цена снижена | N85: =IF('Все позиции'!Q324="","",'Все позиции'!Q324) -> по договру | O85: =IF('Все позиции'!R324="","",'Все позиции'!R324)
A86: =IF('Все позиции'!A139="","",'Все позиции'!A139) -> 4. Вентиляция 10 этаж | B86: =IF('Все позиции'!B139="","",'Все позиции'!B139) -> 4.26 | C86: =IF('Все позиции'!C139="","",'Все позиции'!C139) -> Воздуховод из оцинкованной стали толщиной 0,5мм, класса «В», Ø200 | D86: =IF('Все позиции'!D139="","",'Все позиции'!D139) -> мп | E86: =IF('Все позиции'!E139="","",'Все позиции'!E139) -> 15 | F86: =IF('Все позиции'!F139="","",'Все позиции'!F139) -> 1360.8 | G86: =IF('Все позиции'!H139="","",'Все позиции'!H139) -> 15 | H86: =IF('Все позиции'!L139="","",'Все позиции'!L139) -> 1077.79 | I86: =IF('Все позиции'!O139="","",'Все позиции'!O139) -> -0.20797325 | J86: =IF('Все позиции'!G139="","",'Все позиции'!G139) -> 20412 | K86: =IF('Все позиции'!M139="","",'Все позиции'!M139) -> 16166.85 | L86: =IF('Все позиции'!N139="","",'Все позиции'!N139) -> -4245.15 | M86: =IF('Все позиции'!P139="","",'Все позиции'!P139) -> Цена снижена | N86: =IF('Все позиции'!Q139="","",'Все позиции'!Q139) -> по договору | O86: =IF('Все позиции'!R139="","",'Все позиции'!R139)
A87: =IF('Все позиции'!A122="","",'Все позиции'!A122) -> 4. Вентиляция 10 этаж | B87: =IF('Все позиции'!B122="","",'Все позиции'!B122) -> 4.9 | C87: =IF('Все позиции'!C122="","",'Все позиции'!C122) -> Адаптер для щелевой решетки с регулятором расхода, подключение 160мм два патрубка и увеличенным патрубком, 1000мм Адаптер для ЛРЩ 22-1-1400 y=67мм + подключение 2х160мм + заслонка | D87: =IF('Все позиции'!D122="","",'Все позиции'!D122) -> шт. | E87: =IF('Все позиции'!E122="","",'Все позиции'!E122) -> 1 | F87: =IF('Все позиции'!F122="","",'Все позиции'!F122) -> 5670 | G87: =IF('Все позиции'!H122="","",'Все позиции'!H122) -> 1 | H87: =IF('Все позиции'!L122="","",'Все позиции'!L122) -> 1500 | I87: =IF('Все позиции'!O122="","",'Все позиции'!O122) -> -0.73544974 | J87: =IF('Все позиции'!G122="","",'Все позиции'!G122) -> 5670 | K87: =IF('Все позиции'!M122="","",'Все позиции'!M122) -> 1500 | L87: =IF('Все позиции'!N122="","",'Все позиции'!N122) -> -4170 | M87: =IF('Все позиции'!P122="","",'Все позиции'!P122) -> Цена снижена | N87: =IF('Все позиции'!Q122="","",'Все позиции'!Q122) -> расценка сильно завышена | O87: =IF('Все позиции'!R122="","",'Все позиции'!R122)
A88: =IF('Все позиции'!A291="","",'Все позиции'!A291) -> 6. Вентиляция 2 этаж | B88: =IF('Все позиции'!B291="","",'Все позиции'!B291) -> 6.51 | C88: =IF('Все позиции'!C291="","",'Все позиции'!C291) -> Врезка плоская из оцинкованной стали толщиной 0,5мм, класса «В», Ø200 | D88: =IF('Все позиции'!D291="","",'Все позиции'!D291) -> шт. | E88: =IF('Все позиции'!E291="","",'Все позиции'!E291) -> 22 | F88: =IF('Все позиции'!F291="","",'Все позиции'!F291) -> 1020 | G88: =IF('Все позиции'!H291="","",'Все позиции'!H291) -> 22 | H88: =IF('Все позиции'!L291="","",'Все позиции'!L291) -> 855 | I88: =IF('Все позиции'!O291="","",'Все позиции'!O291) -> -0.16176471 | J88: =IF('Все позиции'!G291="","",'Все позиции'!G291) -> 22440 | K88: =IF('Все позиции'!M291="","",'Все позиции'!M291) -> 18810 | L88: =IF('Все позиции'!N291="","",'Все позиции'!N291) -> -3630 | M88: =IF('Все позиции'!P291="","",'Все позиции'!P291) -> Цена снижена | N88: =IF('Все позиции'!Q291="","",'Все позиции'!Q291) -> по договру | O88: =IF('Все позиции'!R291="","",'Все позиции'!R291)
A89: =IF('Все позиции'!A206="","",'Все позиции'!A206) -> 5. Холодоснабжение 10 этаж | B89: =IF('Все позиции'!B206="","",'Все позиции'!B206) -> 5.3 | C89: =IF('Все позиции'!C206="","",'Все позиции'!C206) -> Воздухоотводчик автоматический, Ду15 Airvent-R | D89: =IF('Все позиции'!D206="","",'Все позиции'!D206) -> шт. | E89: =IF('Все позиции'!E206="","",'Все позиции'!E206) -> 3 | F89: =IF('Все позиции'!F206="","",'Все позиции'!F206) -> 1620 | G89: =IF('Все позиции'!H206="","",'Все позиции'!H206) -> 3 | H89: =IF('Все позиции'!L206="","",'Все позиции'!L206) -> 500 | I89: =IF('Все позиции'!O206="","",'Все позиции'!O206) -> -0.69135802 | J89: =IF('Все позиции'!G206="","",'Все позиции'!G206) -> 4860 | K89: =IF('Все позиции'!M206="","",'Все позиции'!M206) -> 1500 | L89: =IF('Все позиции'!N206="","",'Все позиции'!N206) -> -3360 | M89: =IF('Все позиции'!P206="","",'Все позиции'!P206) -> Цена снижена | N89: =IF('Все позиции'!Q206="","",'Все позиции'!Q206) -> по договру | O89: =IF('Все позиции'!R206="","",'Все позиции'!R206)
A90: =IF('Все позиции'!A241="","",'Все позиции'!A241) -> 6. Вентиляция 2 этаж | B90: =IF('Все позиции'!B241="","",'Все позиции'!B241) -> 6.1 | C90: =IF('Все позиции'!C241="","",'Все позиции'!C241) -> Решетка защитная круглая, Ø100 БСК 100 | D90: =IF('Все позиции'!D241="","",'Все позиции'!D241) -> шт. | E90: =IF('Все позиции'!E241="","",'Все позиции'!E241) -> 3 | F90: =IF('Все позиции'!F241="","",'Все позиции'!F241) -> 1296 | G90: =IF('Все позиции'!H241="","",'Все позиции'!H241) -> 3 | H90: =IF('Все позиции'!L241="","",'Все позиции'!L241) -> 185 | I90: =IF('Все позиции'!O241="","",'Все позиции'!O241) -> -0.85725309 | J90: =IF('Все позиции'!G241="","",'Все позиции'!G241) -> 3888 | K90: =IF('Все позиции'!M241="","",'Все позиции'!M241) -> 555 | L90: =IF('Все позиции'!N241="","",'Все позиции'!N241) -> -3333 | M90: =IF('Все позиции'!P241="","",'Все позиции'!P241) -> Снижение предложено, но не внесено в итог | N90: =IF('Все позиции'!Q241="","",'Все позиции'!Q241) -> по договору | O90: =IF('Все позиции'!R241="","",'Все позиции'!R241)
A91: =IF('Все позиции'!A304="","",'Все позиции'!A304) -> 6. Вентиляция 2 этаж | B91: =IF('Все позиции'!B304="","",'Все позиции'!B304) -> 6.64 | C91: =IF('Все позиции'!C304="","",'Все позиции'!C304) -> Заглушка из оцинкованной стали толщиной 0,7мм, класса «В», 400x200 | D91: =IF('Все позиции'!D304="","",'Все позиции'!D304) -> шт. | E91: =IF('Все позиции'!E304="","",'Все позиции'!E304) -> 2 | F91: =IF('Все позиции'!F304="","",'Все позиции'!F304) -> 1944 | G91: =IF('Все позиции'!H304="","",'Все позиции'!H304) -> 2 | H91: =IF('Все позиции'!L304="","",'Все позиции'!L304) -> 370 | I91: =IF('Все позиции'!O304="","",'Все позиции'!O304) -> -0.80967078 | J91: =IF('Все позиции'!G304="","",'Все позиции'!G304) -> 3888 | K91: =IF('Все позиции'!M304="","",'Все позиции'!M304) -> 740 | L91: =IF('Все позиции'!N304="","",'Все позиции'!N304) -> -3148 | M91: =IF('Все позиции'!P304="","",'Все позиции'!P304) -> Цена снижена | N91: =IF('Все позиции'!Q304="","",'Все позиции'!Q304) | O91: =IF('Все позиции'!R304="","",'Все позиции'!R304)
A92: =IF('Все позиции'!A302="","",'Все позиции'!A302) -> 6. Вентиляция 2 этаж | B92: =IF('Все позиции'!B302="","",'Все позиции'!B302) -> 6.62 | C92: =IF('Все позиции'!C302="","",'Все позиции'!C302) -> Переход из оцинкованной стали толщиной 0,7мм, класса «В», 700x200/600x250 | D92: =IF('Все позиции'!D302="","",'Все позиции'!D302) -> шт. | E92: =IF('Все позиции'!E302="","",'Все позиции'!E302) -> 2 | F92: =IF('Все позиции'!F302="","",'Все позиции'!F302) -> 2592 | G92: =IF('Все позиции'!H302="","",'Все позиции'!H302) -> 2 | H92: =IF('Все позиции'!L302="","",'Все позиции'!L302) -> 1020 | I92: =IF('Все позиции'!O302="","",'Все позиции'!O302) -> -0.60648148 | J92: =IF('Все позиции'!G302="","",'Все позиции'!G302) -> 5184 | K92: =IF('Все позиции'!M302="","",'Все позиции'!M302) -> 2040 | L92: =IF('Все позиции'!N302="","",'Все позиции'!N302) -> -3144 | M92: =IF('Все позиции'!P302="","",'Все позиции'!P302) -> Цена снижена | N92: =IF('Все позиции'!Q302="","",'Все позиции'!Q302) | O92: =IF('Все позиции'!R302="","",'Все позиции'!R302)
A93: =IF('Все позиции'!A271="","",'Все позиции'!A271) -> 6. Вентиляция 2 этаж | B93: =IF('Все позиции'!B271="","",'Все позиции'!B271) -> 6.31 | C93: =IF('Все позиции'!C271="","",'Все позиции'!C271) -> Отвод 300 из оцинкованной стали толщиной 0,7мм, класса «В», 300x200 | D93: =IF('Все позиции'!D271="","",'Все позиции'!D271) -> шт. | E93: =IF('Все позиции'!E271="","",'Все позиции'!E271) -> 4 | F93: =IF('Все позиции'!F271="","",'Все позиции'!F271) -> 1620 | G93: =IF('Все позиции'!H271="","",'Все позиции'!H271) -> 4 | H93: =IF('Все позиции'!L271="","",'Все позиции'!L271) -> 850 | I93: =IF('Все позиции'!O271="","",'Все позиции'!O271) -> -0.47530864 | J93: =IF('Все позиции'!G271="","",'Все позиции'!G271) -> 6480 | K93: =IF('Все позиции'!M271="","",'Все позиции'!M271) -> 3400 | L93: =IF('Все позиции'!N271="","",'Все позиции'!N271) -> -3080 | M93: =IF('Все позиции'!P271="","",'Все позиции'!P271) -> Цена снижена | N93: =IF('Все позиции'!Q271="","",'Все позиции'!Q271) | O93: =IF('Все позиции'!R271="","",'Все позиции'!R271)
A94: =IF('Все позиции'!A232="","",'Все позиции'!A232) -> 5. Холодоснабжение 10 этаж | B94: =IF('Все позиции'!B232="","",'Все позиции'!B232) -> 5.29 | C94: =IF('Все позиции'!C232="","",'Все позиции'!C232) -> Тройник полипропиленовый, 32 | D94: =IF('Все позиции'!D232="","",'Все позиции'!D232) -> шт. | E94: =IF('Все позиции'!E232="","",'Все позиции'!E232) -> 6 | F94: =IF('Все позиции'!F232="","",'Все позиции'!F232) -> 1020 | G94: =IF('Все позиции'!H232="","",'Все позиции'!H232) -> 6 | H94: =IF('Все позиции'!L232="","",'Все позиции'!L232) -> 520 | I94: =IF('Все позиции'!O232="","",'Все позиции'!O232) -> -0.49019608 | J94: =IF('Все позиции'!G232="","",'Все позиции'!G232) -> 6120 | K94: =IF('Все позиции'!M232="","",'Все позиции'!M232) -> 3120 | L94: =IF('Все позиции'!N232="","",'Все позиции'!N232) -> -3000 | M94: =IF('Все позиции'!P232="","",'Все позиции'!P232) -> Цена снижена | N94: =IF('Все позиции'!Q232="","",'Все позиции'!Q232) | O94: =IF('Все позиции'!R232="","",'Все позиции'!R232) -> Цена Согласована Марк
A95: =IF('Все позиции'!A251="","",'Все позиции'!A251) -> 6. Вентиляция 2 этаж | B95: =IF('Все позиции'!B251="","",'Все позиции'!B251) -> 6.11 | C95: =IF('Все позиции'!C251="","",'Все позиции'!C251) -> Воздуховод гофрированный, Ø100 | D95: =IF('Все позиции'!D251="","",'Все позиции'!D251) -> мп | E95: =IF('Все позиции'!E251="","",'Все позиции'!E251) -> 8 | F95: =IF('Все позиции'!F251="","",'Все позиции'!F251) -> 1134 | G95: =IF('Все позиции'!H251="","",'Все позиции'!H251) -> 8 | H95: =IF('Все позиции'!L251="","",'Все позиции'!L251) -> 760 | I95: =IF('Все позиции'!O251="","",'Все позиции'!O251) -> -0.329806 | J95: =IF('Все позиции'!G251="","",'Все позиции'!G251) -> 9072 | K95: =IF('Все позиции'!M251="","",'Все позиции'!M251) -> 6080 | L95: =IF('Все позиции'!N251="","",'Все позиции'!N251) -> -2992 | M95: =IF('Все позиции'!P251="","",'Все позиции'!P251) -> Цена снижена | N95: =IF('Все позиции'!Q251="","",'Все позиции'!Q251) -> по договору | O95: =IF('Все позиции'!R251="","",'Все позиции'!R251)
A96: =IF('Все позиции'!A150="","",'Все позиции'!A150) -> 4. Вентиляция 10 этаж | B96: =IF('Все позиции'!B150="","",'Все позиции'!B150) -> 4.37 | C96: =IF('Все позиции'!C150="","",'Все позиции'!C150) -> Отвод 300 из оцинкованной стали толщиной 0,7мм, класса «В», 200x300 | D96: =IF('Все позиции'!D150="","",'Все позиции'!D150) -> шт. | E96: =IF('Все позиции'!E150="","",'Все позиции'!E150) -> 4 | F96: =IF('Все позиции'!F150="","",'Все позиции'!F150) -> 1620 | G96: =IF('Все позиции'!H150="","",'Все позиции'!H150) -> 4 | H96: =IF('Все позиции'!L150="","",'Все позиции'!L150) -> 880 | I96: =IF('Все позиции'!O150="","",'Все позиции'!O150) -> -0.45679012 | J96: =IF('Все позиции'!G150="","",'Все позиции'!G150) -> 6480 | K96: =IF('Все позиции'!M150="","",'Все позиции'!M150) -> 3520 | L96: =IF('Все позиции'!N150="","",'Все позиции'!N150) -> -2960 | M96: =IF('Все позиции'!P150="","",'Все позиции'!P150) -> Цена снижена | N96: =IF('Все позиции'!Q150="","",'Все позиции'!Q150) -> исходя из м2 изделия | O96: =IF('Все позиции'!R150="","",'Все позиции'!R150)
A97: =IF('Все позиции'!A247="","",'Все позиции'!A247) -> 6. Вентиляция 2 этаж | B97: =IF('Все позиции'!B247="","",'Все позиции'!B247) -> 6.7 | C97: =IF('Все позиции'!C247="","",'Все позиции'!C247) -> Диффузор круглый, Ø160 VE 160 | D97: =IF('Все позиции'!D247="","",'Все позиции'!D247) -> шт. | E97: =IF('Все позиции'!E247="","",'Все позиции'!E247) -> 4 | F97: =IF('Все позиции'!F247="","",'Все позиции'!F247) -> 1296 | G97: =IF('Все позиции'!H247="","",'Все позиции'!H247) -> 4 | H97: =IF('Все позиции'!L247="","",'Все позиции'!L247) -> 600 | I97: =IF('Все позиции'!O247="","",'Все позиции'!O247) -> -0.53703704 | J97: =IF('Все позиции'!G247="","",'Все позиции'!G247) -> 5184 | K97: =IF('Все позиции'!M247="","",'Все позиции'!M247) -> 2400 | L97: =IF('Все позиции'!N247="","",'Все позиции'!N247) -> -2784 | M97: =IF('Все позиции'!P247="","",'Все позиции'!P247) -> Цена снижена | N97: =IF('Все позиции'!Q247="","",'Все позиции'!Q247) -> по договору | O97: =IF('Все позиции'!R247="","",'Все позиции'!R247)
A98: =IF('Все позиции'!A254="","",'Все позиции'!A254) -> 6. Вентиляция 2 этаж | B98: =IF('Все позиции'!B254="","",'Все позиции'!B254) -> 6.14 | C98: =IF('Все позиции'!C254="","",'Все позиции'!C254) -> Воздуховод гофрированный изолированный, Ø125 | D98: =IF('Все позиции'!D254="","",'Все позиции'!D254) -> мп | E98: =IF('Все позиции'!E254="","",'Все позиции'!E254) -> 7 | F98: =IF('Все позиции'!F254="","",'Все позиции'!F254) -> 1134 | G98: =IF('Все позиции'!H254="","",'Все позиции'!H254) -> 7 | H98: =IF('Все позиции'!L254="","",'Все позиции'!L254) -> 760 | I98: =IF('Все позиции'!O254="","",'Все позиции'!O254) -> -0.329806 | J98: =IF('Все позиции'!G254="","",'Все позиции'!G254) -> 7938 | K98: =IF('Все позиции'!M254="","",'Все позиции'!M254) -> 5320 | L98: =IF('Все позиции'!N254="","",'Все позиции'!N254) -> -2618 | M98: =IF('Все позиции'!P254="","",'Все позиции'!P254) -> Цена снижена | N98: =IF('Все позиции'!Q254="","",'Все позиции'!Q254) -> по договору | O98: =IF('Все позиции'!R254="","",'Все позиции'!R254)
A99: =IF('Все позиции'!A189="","",'Все позиции'!A189) -> 4. Вентиляция 10 этаж | B99: =IF('Все позиции'!B189="","",'Все позиции'!B189) -> 4.76 | C99: =IF('Все позиции'!C189="","",'Все позиции'!C189) -> Ниппель из оцинкованной стали толщиной 0,5мм, класса «В», Ø100 | D99: =IF('Все позиции'!D189="","",'Все позиции'!D189) -> шт. | E99: =IF('Все позиции'!E189="","",'Все позиции'!E189) -> 4 | F99: =IF('Все позиции'!F189="","",'Все позиции'!F189) -> 1020 | G99: =IF('Все позиции'!H189="","",'Все позиции'!H189) -> 4 | H99: =IF('Все позиции'!L189="","",'Все позиции'!L189) -> 370 | I99: =IF('Все позиции'!O189="","",'Все позиции'!O189) -> -0.6372549 | J99: =IF('Все позиции'!G189="","",'Все позиции'!G189) -> 4080 | K99: =IF('Все позиции'!M189="","",'Все позиции'!M189) -> 1480 | L99: =IF('Все позиции'!N189="","",'Все позиции'!N189) -> -2600 | M99: =IF('Все позиции'!P189="","",'Все позиции'!P189) -> Цена снижена | N99: =IF('Все позиции'!Q189="","",'Все позиции'!Q189) | O99: =IF('Все позиции'!R189="","",'Все позиции'!R189)
A100: =IF('Все позиции'!A266="","",'Все позиции'!A266) -> 6. Вентиляция 2 этаж | B100: =IF('Все позиции'!B266="","",'Все позиции'!B266) -> 6.26 | C100: =IF('Все позиции'!C266="","",'Все позиции'!C266) -> Отвод 150 из оцинкованной стали толщиной 0,7мм, класса «В», 600x250 | D100: =IF('Все позиции'!D266="","",'Все позиции'!D266) -> шт. | E100: =IF('Все позиции'!E266="","",'Все позиции'!E266) -> 2 | F100: =IF('Все позиции'!F266="","",'Все позиции'!F266) -> 2106 | G100: =IF('Все позиции'!H266="","",'Все позиции'!H266) -> 2 | H100: =IF('Все позиции'!L266="","",'Все позиции'!L266) -> 855 | I100: =IF('Все позиции'!O266="","",'Все позиции'!O266) -> -0.59401709 | J100: =IF('Все позиции'!G266="","",'Все позиции'!G266) -> 4212 | K100: =IF('Все позиции'!M266="","",'Все позиции'!M266) -> 1710 | L100: =IF('Все позиции'!N266="","",'Все позиции'!N266) -> -2502 | M100: =IF('Все позиции'!P266="","",'Все позиции'!P266) -> Цена снижена | N100: =IF('Все позиции'!Q266="","",'Все позиции'!Q266) -> по договру | O100: =IF('Все позиции'!R266="","",'Все позиции'!R266)
...

Sheet Что оспорить
A1: Что можно оспорить и где есть риски
A2: «Потенциал» — сколько можно вернуть, если отстоять нашу позицию. «Риск» — где заказчик ошибся в нашу пользу и может поправить позже (сумма с минусом).
A3: Тип | B3: Позиции | C3: Что сделал заказчик | D3: Наш аргумент | E3: Сумма, ₽
A4: Потенциал | B4: 5.35, 6.71, 7.2, 7.8, 7.9, 7.10 (дренаж, демонтаж воздуховодов, подключение фанкойлов, демонтаж холодоснабжения и дренажа) | C4: Строки просто удалены из КП, без единого комментария. | D4: Работы выполняются/нужны. Требовать вернуть позиции или письменно обосновать исключение. | E4: ='Все позиции'!G238+'Все позиции'!G311+'Все позиции'!G322+'Все позиции'!G328+'Все позиции'!G329+'Все позиции'!G330 -> 1151370
A5: Потенциал | B5: 6.1–6.3 Решётка защитная круглая Ø100/Ø160/Ø200 (2 этаж) | C5: Предлагают 185 / 205,66 / 298,89 ₽ вместо 1 296 ₽ «по договору». | D5: В этом же КП п. 2.2–2.3 такие же решётки Ø160/Ø200 стоят 1 425 ₽ и приняты без вопросов, а на 10 этаже (п. 4.1) та же решётка Ø100 оставлена по 1 296 ₽. | E5: =-('Все позиции'!N241+'Все позиции'!N242+'Все позиции'!N243) -> 48296.18
A6: Потенциал | B6: 4.76–4.79, 6.65–6.68 Ниппели оцинкованные (10 и 2 этаж) | C6: Поставили 370 ₽/шт. | D6: В п. 3.8 «Ниппель ф160» стоит 630 ₽ и принят заказчиком без правок. Просить минимум 630 ₽. | E6: ='Все позиции'!H189*(630-'Все позиции'!L189)+'Все позиции'!H190*(630-'Все позиции'!L190)+'Все позиции'!H191*(630-'Все позиции'!L191)+'Все позиции'!H192*(630-'Все позиции'!L192)+'Все позиции'!H305*(630-'Все позиции'!L305)+'Все позиции'!H306*(630-'Все позиции'!L306)+'Все позиции'!H307*(630-'Все позиции'!L307)+'Все позиции'!H308*(630-'Все позиции'!L308) -> 24960
A7: Потенциал | B7: 4.56–4.66 Врезки, седла, тройник, переходы круглые (10 этаж) | C7: Поставили 370–440 ₽/шт. | D7: Ровно такие же изделия на 2 этаже (п. 6.48–6.56) заказчик сам оценил в 855 ₽; тройники и переходы по договору (п. 1.17–1.19) — 855 ₽. | E7: ='Все позиции'!H169*(855-'Все позиции'!L169)+'Все позиции'!H170*(855-'Все позиции'!L170)+'Все позиции'!H171*(855-'Все позиции'!L171)+'Все позиции'!H172*(855-'Все позиции'!L172)+'Все позиции'!H173*(855-'Все позиции'!L173)+'Все позиции'!H174*(855-'Все позиции'!L174)+'Все позиции'!H175*(855-'Все позиции'!L175)+'Все позиции'!H176*(855-'Все позиции'!L176)+'Все позиции'!H177*(855-'Все позиции'!L177)+'Все позиции'!H178*(855-'Все позиции'!L178)+'Все позиции'!H179*(855-'Все позиции'!L179) -> 18775
A8: Потенциал | B8: 4.82–4.83 Изоляция воздуховодов (10 этаж) | C8: Поставили 665 ₽. | D8: На 2 этаже (п. 6.72–6.73) та же работа — 800 ₽. | E8: ='Все позиции'!H195*(800-'Все позиции'!L195)+'Все позиции'!H196*(800-'Все позиции'!L196) -> 27135
A9: Потенциал | B9: 6.25 Отвод 15° Ø200 (2 этаж) | C9: Поставили 340 ₽. | D9: Все остальные круглые отводы — 855 ₽ «по договору». | E9: ='Все позиции'!H265*(855-'Все позиции'!L265) -> 1030
A10: Потенциал | B10: 6.64 Заглушка 400×200 (2 этаж) | C10: Поставили 370 ₽. | D10: Круглая заглушка Ø200 (п. 6.63) — 855 ₽; прямоугольная сложнее круглой. | E10: ='Все позиции'!H304*(855-'Все позиции'!L304) -> 970
A11: Отложено | B11: Дымоудаление: 4.85–4.88 и 6.75–6.78 | C11: Исключено, обещают «отдельный допник». | D11: Зафиксировать письменно сроки и цены допсоглашения, иначе это прямые потери. | E11: ='Все позиции'!G199+'Все позиции'!G200+'Все позиции'!G201+'Все позиции'!G202+'Все позиции'!G316+'Все позиции'!G317+'Все позиции'!G318+'Все позиции'!G319 -> 1028480
A12: Информация | B12: 9 позиций с пометкой «Цена согласована Марк» / «по договору» (1.33, 2.9, 2.10, 2.37, 2.38, 6.1–6.3, 7.7) | C12: Снижение написано в комментарии, но в итог их файла (16,53 млн) ещё не внесено. | D12: Итоговая сумма заказчика после внесения этих правок станет ниже. Уже учтено в листах «Сводка» и «Где занизили». | E12: =('Все позиции'!N37+'Все позиции'!N48+'Все позиции'!N49+'Все позиции'!N76+'Все позиции'!N77+'Все позиции'!N241+'Все позиции'!N242+'Все позиции'!N243+'Все позиции'!N327) -> -452611.16
A13: Риск | B13: 7.5–7.6 Клапан балансировочный / комплект трёхходового клапана (2 этаж) | C13: Поставили 1 994 ₽, а в комментарии пишут «в п. 5.5 стоит 1944». | D13: Опечатка в нашу пользу: если исправят на 1 944, потеряем ещё. | E13: =-('Все позиции'!H325+'Все позиции'!H326)*50 -> -3100
A14: Риск | B14: 4.24–4.26, 6.16–6.18 Воздуховоды оцинк. Ø125/Ø160/Ø200 | C14: Цены по договору «съехали» на строку: Ø160 — 862,23 (по договору п. 1.14 — 689,79), Ø200 на 10 эт. — 1 077,79 (по договору п. 1.15 — 862,23). | D14: Ошибка в нашу пользу; при перепроверке могут снизить. | E14: =-(('Все позиции'!H138+'Все позиции'!H257)*(862.23-689.79)+'Все позиции'!H139*(1077.79-862.23)) -> -10648.32
A15: Риск | B15: 6.69–6.70 Изоляция изделий (2 этаж) | C15: Оставили 1 296 и 3 240 ₽, хотя на 10 этаже те же позиции снизили до 450 и 665 ₽. | D15: Скорее всего пропустили; могут снизить следом. | E15: =-('Все позиции'!H309*('Все позиции'!L309-450)+'Все позиции'!H310*('Все позиции'!L310-665)) -> -3421
D16: Итого потенциал к возврату (без допника по дымоудалению) | E16: =SUMIFS(E4:E15,A4:A15,"Потенциал") -> 1272536.2
D17: Итого риски (могут снизить дополнительно) | E17: =SUMIFS(E4:E15,A4:A15,"Риск") -> -17169.32

Sheet Все позиции
A1: Сравнение КП: наше исходное vs исправленное заказчиком (Договор № СПБ-ГАЗЭ/ОВ/7-9, ул. Стартовая, д. 6, к. 2)
A2: Минус в столбце «Разница» — на сколько нам занизили. Жёлтые строки — снижение заказчик написал в комментарии, но в итог своего файла ещё не внёс. Все суммы без НДС.
A3: Раздел | B3: № | C3: Наименование | D3: Ед. | E3: Кол-во (наше КП) | F3: Цена за ед. (наше КП), ₽ | G3: Сумма (наше КП), ₽ | H3: Кол-во (заказчик) | I3: Цена в файле заказчика, ₽ | J3: Сумма в файле заказчика, ₽ | K3: Цена из комментария заказчика (не внесена в итог файла), ₽ | L3: Итоговая цена с учётом всех правок, ₽ | M3: Итоговая сумма с учётом всех правок, ₽ | N3: Разница, ₽ (итог − наше КП) | O3: Изменение цены, % | P3: Что произошло | Q3: Комментарий заказчика | R3: Ответ / согласование (из файла заказчика)
B4: 1. Вентиляция
A5: 1. Вентиляция | B5: 1.1 | C5: Диффузор 160 мм | D5: шт | E5: 72 | F5: 600 | G5: =E5*F5 -> 43200 | H5: 72 | I5: 600 | J5: =H5*I5 -> 43200 | L5: =IF(K5<>"",K5,I5) -> 600 | M5: =H5*L5 -> 43200 | N5: =M5-G5 -> 0 | O5: =IF(F5>0,L5/F5-1,"") -> 0 | P5: Без изменений
A6: 1. Вентиляция | B6: 1.2 | C6: Диффузор 160 мм (сущ) исключено | D6: шт | E6: 0 | F6: 0 | G6: =E6*F6 -> 0 | H6: 0 | J6: =H6*I6 -> 0 | L6: =IF(K6<>"",K6,I6) -> 0 | M6: =H6*L6 -> 0 | N6: =M6-G6 -> 0 | O6: =IF(F6>0,L6/F6-1,"") | P6: Без изменений
A7: 1. Вентиляция | B7: 1.3 | C7: Диффузор 100 мм | D7: шт | E7: 8 | F7: 600 | G7: =E7*F7 -> 4800 | H7: 8 | I7: 600 | J7: =H7*I7 -> 4800 | L7: =IF(K7<>"",K7,I7) -> 600 | M7: =H7*L7 -> 4800 | N7: =M7-G7 -> 0 | O7: =IF(F7>0,L7/F7-1,"") -> 0 | P7: Без изменений
A8: 1. Вентиляция | B8: 1.4 | C8: Решетка щелевая SWANa 2-1200 (сущ) исключено | D8: шт | E8: 0 | F8: 0 | G8: =E8*F8 -> 0 | H8: 0 | J8: =H8*I8 -> 0 | L8: =IF(K8<>"",K8,I8) -> 0 | M8: =H8*L8 -> 0 | N8: =M8-G8 -> 0 | O8: =IF(F8>0,L8/F8-1,"") | P8: Без изменений
A9: 1. Вентиляция | B9: 1.5 | C9: Регулятор расхода воздуха, Ø100 | D9: шт | E9: 12 | F9: 950 | G9: =E9*F9 -> 11400 | H9: 12 | I9: 950 | J9: =H9*I9 -> 11400 | L9: =IF(K9<>"",K9,I9) -> 950 | M9: =H9*L9 -> 11400 | N9: =M9-G9 -> 0 | O9: =IF(F9>0,L9/F9-1,"") -> 0 | P9: Без изменений
A10: 1. Вентиляция | B10: 1.6 | C10: Регулятор расхода воздуха, Ø160 | D10: шт | E10: 60 | F10: 950 | G10: =E10*F10 -> 57000 | H10: 60 | I10: 950 | J10: =H10*I10 -> 57000 | L10: =IF(K10<>"",K10,I10) -> 950 | M10: =H10*L10 -> 57000 | N10: =M10-G10 -> 0 | O10: =IF(F10>0,L10/F10-1,"") -> 0 | P10: Без изменений
A11: 1. Вентиляция | B11: 1.7 | C11: Регулятор расхода воздуха, Ø200 | D11: шт | E11: 64 | F11: 950 | G11: =E11*F11 -> 60800 | H11: 64 | I11: 950 | J11: =H11*I11 -> 60800 | L11: =IF(K11<>"",K11,I11) -> 950 | M11: =H11*L11 -> 60800 | N11: =M11-G11 -> 0 | O11: =IF(F11>0,L11/F11-1,"") -> 0 | P11: Без изменений
A12: 1. Вентиляция | B12: 1.8 | C12: Регулятор расхода воздуха, Ø250 | D12: шт | E12: 8 | F12: 950 | G12: =E12*F12 -> 7600 | H12: 8 | I12: 950 | J12: =H12*I12 -> 7600 | L12: =IF(K12<>"",K12,I12) -> 950 | M12: =H12*L12 -> 7600 | N12: =M12-G12 -> 0 | O12: =IF(F12>0,L12/F12-1,"") -> 0 | P12: Без изменений
A13: 1. Вентиляция | B13: 1.9 | C13: Воздуховод гофрированный 160 исключено | D13: м | E13: 0 | F13: 0 | G13: =E13*F13 -> 0 | H13: 0 | J13: =H13*I13 -> 0 | L13: =IF(K13<>"",K13,I13) -> 0 | M13: =H13*L13 -> 0 | N13: =M13-G13 -> 0 | O13: =IF(F13>0,L13/F13-1,"") | P13: Без изменений
A14: 1. Вентиляция | B14: 1.10 | C14: Воздуховод гофрированный 100 | D14: м | E14: 13.5 | F14: 760 | G14: =E14*F14 -> 10260 | H14: 13.5 | I14: 760 | J14: =H14*I14 -> 10260 | L14: =IF(K14<>"",K14,I14) -> 760 | M14: =H14*L14 -> 10260 | N14: =M14-G14 -> 0 | O14: =IF(F14>0,L14/F14-1,"") -> 0 | P14: Без изменений
A15: 1. Вентиляция | B15: 1.11 | C15: Воздуховод гофрированный Ø160 алюдек | D15: м | E15: 26.5 | F15: 760 | G15: =E15*F15 -> 20140 | H15: 26.5 | I15: 760 | J15: =H15*I15 -> 20140 | L15: =IF(K15<>"",K15,I15) -> 760 | M15: =H15*L15 -> 20140 | N15: =M15-G15 -> 0 | O15: =IF(F15>0,L15/F15-1,"") -> 0 | P15: Без изменений
A16: 1. Вентиляция | B16: 1.12 | C16: Воздуховод гофрированный изолированный, Ø160 санодек | D16: м | E16: 50 | F16: 760 | G16: =E16*F16 -> 38000 | H16: 50 | I16: 760 | J16: =H16*I16 -> 38000 | L16: =IF(K16<>"",K16,I16) -> 760 | M16: =H16*L16 -> 38000 | N16: =M16-G16 -> 0 | O16: =IF(F16>0,L16/F16-1,"") -> 0 | P16: Без изменений
A17: 1. Вентиляция | B17: 1.13 | C17: Воздуховод(класс герм. "В") толщина лист. стали b-0,5мм 100 - | D17: м | E17: 5.2 | F17: 950 | G17: =E17*F17 -> 4940 | H17: 5.2 | I17: 950 | J17: =H17*I17 -> 4940 | L17: =IF(K17<>"",K17,I17) -> 950 | M17: =H17*L17 -> 4940 | N17: =M17-G17 -> 0 | O17: =IF(F17>0,L17/F17-1,"") -> 0 | P17: Без изменений
A18: 1. Вентиляция | B18: 1.14 | C18: Воздуховод(класс герм. "В") толщина лист. стали b-0,5мм 160 | D18: м | E18: 771.3 | F18: 689.79 | G18: =E18*F18 -> 532035.03 | H18: 771.3 | I18: 689.79 | J18: =H18*I18 -> 532035.03 | L18: =IF(K18<>"",K18,I18) -> 689.79 | M18: =H18*L18 -> 532035.03 | N18: =M18-G18 -> 0 | O18: =IF(F18>0,L18/F18-1,"") -> 0 | P18: Без изменений
A19: 1. Вентиляция | B19: 1.15 | C19: Воздуховод(класс герм. "В") толщина лист. стали b-0,5мм 200 | D19: м | E19: 204.6 | F19: 862.23 | G19: =E19*F19 -> 176412.26 | H19: 204.6 | I19: 862.23 | J19: =H19*I19 -> 176412.26 | L19: =IF(K19<>"",K19,I19) -> 862.23 | M19: =H19*L19 -> 176412.26 | N19: =M19-G19 -> 0 | O19: =IF(F19>0,L19/F19-1,"") -> 0 | P19: Без изменений
A20: 1. Вентиляция | B20: 1.16 | C20: Воздуховод(класс герм. "В") толщина лист. стали b-0,6мм 250 | D20: м | E20: 4.4 | F20: 1077.79 | G20: =E20*F20 -> 4742.276 | H20: 4.4 | I20: 1077.79 | J20: =H20*I20 -> 4742.276 | L20: =IF(K20<>"",K20,I20) -> 1077.79 | M20: =H20*L20 -> 4742.276 | N20: =M20-G20 -> 0 | O20: =IF(F20>0,L20/F20-1,"") -> 0 | P20: Без изменений
A21: 1. Вентиляция | B21: 1.17 | C21: Тройник ф 160 | D21: шт. | E21: 155 | F21: 855 | G21: =E21*F21 -> 132525 | H21: 155 | I21: 855 | J21: =H21*I21 -> 132525 | L21: =IF(K21<>"",K21,I21) -> 855 | M21: =H21*L21 -> 132525 | N21: =M21-G21 -> 0 | O21: =IF(F21>0,L21/F21-1,"") -> 0 | P21: Без изменений
A22: 1. Вентиляция | B22: 1.18 | C22: Тройник ф 200 | D22: шт. | E22: 7 | F22: 855 | G22: =E22*F22 -> 5985 | H22: 7 | I22: 855 | J22: =H22*I22 -> 5985 | L22: =IF(K22<>"",K22,I22) -> 855 | M22: =H22*L22 -> 5985 | N22: =M22-G22 -> 0 | O22: =IF(F22>0,L22/F22-1,"") -> 0 | P22: Без изменений
A23: 1. Вентиляция | B23: 1.19 | C23: Переход 160-200 | D23: шт. | E23: 104 | F23: 855 | G23: =E23*F23 -> 88920 | H23: 104 | I23: 855 | J23: =H23*I23 -> 88920 | L23: =IF(K23<>"",K23,I23) -> 855 | M23: =H23*L23 -> 88920 | N23: =M23-G23 -> 0 | O23: =IF(F23>0,L23/F23-1,"") -> 0 | P23: Без изменений
A24: 1. Вентиляция | B24: 1.20 | C24: Отвод 90 ф160 | D24: шт. | E24: 272 | F24: 855 | G24: =E24*F24 -> 232560 | H24: 272 | I24: 855 | J24: =H24*I24 -> 232560 | L24: =IF(K24<>"",K24,I24) -> 855 | M24: =H24*L24 -> 232560 | N24: =M24-G24 -> 0 | O24: =IF(F24>0,L24/F24-1,"") -> 0 | P24: Без изменений
A25: 1. Вентиляция | B25: 1.21 | C25: Отвод 45 Ф160 | D25: шт. | E25: 243 | F25: 855 | G25: =E25*F25 -> 207765 | H25: 243 | I25: 855 | J25: =H25*I25 -> 207765 | L25: =IF(K25<>"",K25,I25) -> 855 | M25: =H25*L25 -> 207765 | N25: =M25-G25 -> 0 | O25: =IF(F25>0,L25/F25-1,"") -> 0 | P25: Без изменений
A26: 1. Вентиляция | B26: 1.22 | C26: Тройник 200/160/200 исключено | D26: шт. | E26: 0 | F26: 0 | G26: =E26*F26 -> 0 | H26: 0 | J26: =H26*I26 -> 0 | L26: =IF(K26<>"",K26,I26) -> 0 | M26: =H26*L26 -> 0 | N26: =M26-G26 -> 0 | O26: =IF(F26>0,L26/F26-1,"") | P26: Без изменений
A27: 1. Вентиляция | B27: 1.23 | C27: КВК ф250 исключено | D27: шт. | E27: 0 | F27: 0 | G27: =E27*F27 -> 0 | H27: 0 | J27: =H27*I27 -> 0 | L27: =IF(K27<>"",K27,I27) -> 0 | M27: =H27*L27 -> 0 | N27: =M27-G27 -> 0 | O27: =IF(F27>0,L27/F27-1,"") | P27: Без изменений
A28: 1. Вентиляция | B28: 1.24 | C28: Переход с воздуховодов на врезку балки | D28: шт. | E28: 340 | F28: 950 | G28: =E28*F28 -> 323000 | H28: 340 | I28: 950 | J28: =H28*I28 -> 323000 | L28: =IF(K28<>"",K28,I28) -> 950 | M28: =H28*L28 -> 323000 | N28: =M28-G28 -> 0 | O28: =IF(F28>0,L28/F28-1,"") -> 0 | P28: Без изменений
A29: 1. Вентиляция | B29: 1.25 | C29: Отвод 90 ф200 | D29: шт. | E29: 32 | F29: 855 | G29: =E29*F29 -> 27360 | H29: 32 | I29: 855 | J29: =H29*I29 -> 27360 | L29: =IF(K29<>"",K29,I29) -> 855 | M29: =H29*L29 -> 27360 | N29: =M29-G29 -> 0 | O29: =IF(F29>0,L29/F29-1,"") -> 0 | P29: Без изменений
A30: 1. Вентиляция | B30: 1.26 | C30: Отвод 45 ф 200 | D30: шт. | E30: 113 | F30: 855 | G30: =E30*F30 -> 96615 | H30: 113 | I30: 855 | J30: =H30*I30 -> 96615 | L30: =IF(K30<>"",K30,I30) -> 855 | M30: =H30*L30 -> 96615 | N30: =M30-G30 -> 0 | O30: =IF(F30>0,L30/F30-1,"") -> 0 | P30: Без изменений
A31: 1. Вентиляция | B31: 1.27 | C31: КВК ф 200 исключено | D31: шт. | E31: 0 | F31: 0 | G31: =E31*F31 -> 0 | H31: 0 | J31: =H31*I31 -> 0 | L31: =IF(K31<>"",K31,I31) -> 0 | M31: =H31*L31 -> 0 | N31: =M31-G31 -> 0 | O31: =IF(F31>0,L31/F31-1,"") | P31: Без изменений
A32: 1. Вентиляция | B32: 1.28 | C32: КВК160 исключено | D32: шт. | E32: 0 | F32: 0 | G32: =E32*F32 -> 0 | H32: 0 | J32: =H32*I32 -> 0 | L32: =IF(K32<>"",K32,I32) -> 0 | M32: =H32*L32 -> 0 | N32: =M32-G32 -> 0 | O32: =IF(F32>0,L32/F32-1,"") | P32: Без изменений
A33: 1. Вентиляция | B33: 1.29 | C33: Отвод 90 ф100 | D33: шт. | E33: 2 | F33: 855 | G33: =E33*F33 -> 1710 | H33: 2 | I33: 855 | J33: =H33*I33 -> 1710 | L33: =IF(K33<>"",K33,I33) -> 855 | M33: =H33*L33 -> 1710 | N33: =M33-G33 -> 0 | O33: =IF(F33>0,L33/F33-1,"") -> 0 | P33: Без изменений
A34: 1. Вентиляция | B34: 1.30 | C34: Переход 250\200 | D34: шт. | E34: 10 | F34: 855 | G34: =E34*F34 -> 8550 | H34: 10 | I34: 855 | J34: =H34*I34 -> 8550 | L34: =IF(K34<>"",K34,I34) -> 855 | M34: =H34*L34 -> 8550 | N34: =M34-G34 -> 0 | O34: =IF(F34>0,L34/F34-1,"") -> 0 | P34: Без изменений
A35: 1. Вентиляция | B35: 1.31 | C35: КВК ф100 исключено | D35: шт. | E35: 0 | F35: 0 | G35: =E35*F35 -> 0 | H35: 0 | J35: =H35*I35 -> 0 | L35: =IF(K35<>"",K35,I35) -> 0 | M35: =H35*L35 -> 0 | N35: =M35-G35 -> 0 | O35: =IF(F35>0,L35/F35-1,"") | P35: Без изменений
A36: 1. Вентиляция | B36: 1.32 | C36: Проделка отверстий | D36: шт. | E36: 128 | F36: 570 | G36: =E36*F36 -> 72960 | H36: 128 | I36: 570 | J36: =H36*I36 -> 72960 | L36: =IF(K36<>"",K36,I36) -> 570 | M36: =H36*L36 -> 72960 | N36: =M36-G36 -> 0 | O36: =IF(F36>0,L36/F36-1,"") -> 0 | P36: Без изменений
A37: 1. Вентиляция | B37: 1.33 | C37: Универсальная теплоизоляция в виде рулонов, толщиной 6 мм K- Flex-ST | D37: м2 | E37: 882 | F37: 665.89 | G37: =E37*F37 -> 587314.98 | H37: 882 | I37: 665.89 | J37: =H37*I37 -> 587314.98 | K37: 570 | L37: =IF(K37<>"",K37,I37) -> 570 | M37: =H37*L37 -> 502740 | N37: =M37-G37 -> -84574.98 | O37: =IF(F37>0,L37/F37-1,"") -> -0.14400276 | P37: Снижение согласовано, но не внесено в итог | Q37: р по договору | R37: Цена Согласована Марк
A38: 1. Вентиляция | B38: 1.34 | C38: ПНР 3-10 эт | D38: комп | E38: 4 | F38: 95238.1 | G38: =E38*F38 -> 380952.4 | H38: 4 | I38: 95238.1 | J38: =H38*I38 -> 380952.4 | L38: =IF(K38<>"",K38,I38) -> 95238.1 | M38: =H38*L38 -> 380952.4 | N38: =M38-G38 -> 0 | O38: =IF(F38>0,L38/F38-1,"") -> 0 | P38: Без изменений
B39: 2. Кондиционирование
A40: 2. Кондиционирование | B40: 2.1 | C40: Климатическая балка Swegon PARASOL | D40: шт. | E40: 340 | F40: 10000 | G40: =E40*F40 -> 3400000 | H40: 340 | I40: 10000 | J40: =H40*I40 -> 3400000 | L40: =IF(K40<>"",K40,I40) -> 10000 | M40: =H40*L40 -> 3400000 | N40: =M40-G40 -> 0 | O40: =IF(F40>0,L40/F40-1,"") -> 0 | P40: Без изменений
A41: 2. Кондиционирование | B41: 2.2 | C41: Решетка защитная круглая, Ø160 | D41: шт. | E41: 72 | F41: 1425 | G41: =E41*F41 -> 102600 | H41: 72 | I41: 1425 | J41: =H41*I41 -> 102600 | L41: =IF(K41<>"",K41,I41) -> 1425 | M41: =H41*L41 -> 102600 | N41: =M41-G41 -> 0 | O41: =IF(F41>0,L41/F41-1,"") -> 0 | P41: Без изменений
A42: 2. Кондиционирование | B42: 2.3 | C42: Решетка защитная круглая, Ø200 | D42: шт. | E42: 24 | F42: 1425 | G42: =E42*F42 -> 34200 | H42: 24 | I42: 1425 | J42: =H42*I42 -> 34200 | L42: =IF(K42<>"",K42,I42) -> 1425 | M42: =H42*L42 -> 34200 | N42: =M42-G42 -> 0 | O42: =IF(F42>0,L42/F42-1,"") -> 0 | P42: Без изменений
A43: 2. Кондиционирование | B43: 2.4 | C43: Решетка защитная прямоугольная, 400х200 | D43: шт. | E43: 4 | F43: 1710 | G43: =E43*F43 -> 6840 | H43: 4 | I43: 1710 | J43: =H43*I43 -> 6840 | L43: =IF(K43<>"",K43,I43) -> 1710 | M43: =H43*L43 -> 6840 | N43: =M43-G43 -> 0 | O43: =IF(F43>0,L43/F43-1,"") -> 0 | P43: Без изменений
A44: 2. Кондиционирование | B44: 2.5 | C44: Ручной балансировочный клапан, Ду15 STAD ТА | D44: шт. | E44: 20 | F44: 1900 | G44: =E44*F44 -> 38000 | H44: 20 | I44: 1900 | J44: =H44*I44 -> 38000 | L44: =IF(K44<>"",K44,I44) -> 1900 | M44: =H44*L44 -> 38000 | N44: =M44-G44 -> 0 | O44: =IF(F44>0,L44/F44-1,"") -> 0 | P44: Без изменений
A45: 2. Кондиционирование | B45: 2.6 | C45: Шаровый кран полнопроходной с накидной гайкой, Ду15 BVR- FR 065B8303RG Ридан | D45: шт. | E45: 40 | F45: 1710 | G45: =E45*F45 -> 68400 | H45: 40 | I45: 1710 | J45: =H45*I45 -> 68400 | L45: =IF(K45<>"",K45,I45) -> 1710 | M45: =H45*L45 -> 68400 | N45: =M45-G45 -> 0 | O45: =IF(F45>0,L45/F45-1,"") -> 0 | P45: Без изменений
A46: 2. Кондиционирование | B46: 2.7 | C46: Узел регулирования климатической балки 1/2 Modulator ½ | D46: шт. | E46: 340 | F46: 6650 | G46: =E46*F46 -> 2261000 | H46: 340 | I46: 2500 | J46: =H46*I46 -> 850000 | L46: =IF(K46<>"",K46,I46) -> 2500 | M46: =H46*L46 -> 850000 | N46: =M46-G46 -> -1411000 | O46: =IF(F46>0,L46/F46-1,"") -> -0.62406015 | P46: Цена снижена | Q46: по договоренности
A47: 2. Кондиционирование | B47: 2.8 | C47: Автоматический воздухоотводчик, ½” Danfoss Airvent 065B8323R | D47: шт. | E47: 40 | F47: 500 | G47: =E47*F47 -> 20000 | H47: 40 | I47: 500 | J47: =H47*I47 -> 20000 | L47: =IF(K47<>"",K47,I47) -> 500 | M47: =H47*L47 -> 20000 | N47: =M47-G47 -> 0 | O47: =IF(F47>0,L47/F47-1,"") -> 0 | P47: Без изменений
A48: 2. Кондиционирование | B48: 2.9 | C48: Трубопровод из полимерных труб РЕХ-а, Дн25х3.5 REHAU Rautitan Flex 11303701006 | D48: м.п. | E48: 1280 | F48: 500 | G48: =E48*F48 -> 640000 | H48: 1280 | I48: 500 | J48: =H48*I48 -> 640000 | K48: 400 | L48: =IF(K48<>"",K48,I48) -> 400 | M48: =H48*L48 -> 512000 | N48: =M48-G48 -> -128000 | O48: =IF(F48>0,L48/F48-1,"") -> -0.2 | P48: Снижение согласовано, но не внесено в итог | Q48: по договру | R48: Цена Согласована Марк
A49: 2. Кондиционирование | B49: 2.10 | C49: Трубопровод из полимерных труб РЕХ-а, Дн32х3.5 REHAU Rautitan Flex | D49: м.п. | E49: 800 | F49: 500 | G49: =E49*F49 -> 400000 | H49: 800 | I49: 500 | J49: =H49*I49 -> 400000 | K49: 400 | L49: =IF(K49<>"",K49,I49) -> 400 | M49: =H49*L49 -> 320000 | N49: =M49-G49 -> -80000 | O49: =IF(F49>0,L49/F49-1,"") -> -0.2 | P49: Снижение согласовано, но не внесено в итог | Q49: по договру | R49: Цена Согласована Марк
A50: 2. Кондиционирование | B50: 2.11 | C50: Трубопровод из полимерных труб РЕХ-а, Дн40х3.5 REHAU Rautitan Flex | D50: м.п. | E50: 200 | F50: 684 | G50: =E50*F50 -> 136800 | H50: 200 | I50: 684 | J50: =H50*I50 -> 136800 | L50: =IF(K50<>"",K50,I50) -> 684 | M50: =H50*L50 -> 136800 | N50: =M50-G50 -> 0 | O50: =IF(F50>0,L50/F50-1,"") -> 0 | P50: Без изменений
A51: 2. Кондиционирование | B51: 2.12 | C51: Трубопровод из полимерных труб РЕХ-а, Дн50х6,9 REHAU Rautitan Flex | D51: м.п. | E51: 240 | F51: 874 | G51: =E51*F51 -> 209760 | H51: 240 | I51: 874 | J51: =H51*I51 -> 209760 | L51: =IF(K51<>"",K51,I51) -> 874 | M51: =H51*L51 -> 209760 | N51: =M51-G51 -> 0 | O51: =IF(F51>0,L51/F51-1,"") -> 0 | P51: Без изменений
A52: 2. Кондиционирование | B52: 2.13 | C52: Трубопровод из полимерных труб РЕХ-а, Дн63х8,6 REHAU Rautitan Flex | D52: м.п. | E52: 640 | F52: 500 | G52: =E52*F52 -> 320000 | H52: 640 | I52: 500 | J52: =H52*I52 -> 320000 | L52: =IF(K52<>"",K52,I52) -> 500 | M52: =H52*L52 -> 320000 | N52: =M52-G52 -> 0 | O52: =IF(F52>0,L52/F52-1,"") -> 0 | P52: Без изменений
A53: 2. Кондиционирование | B53: 2.14 | C53: Пайка кондиционеров подача обратка переход с меди на рехао исключено | D53: шт. | E53: 0 | F53: 0 | G53: =E53*F53 -> 0 | H53: 0 | J53: =H53*I53 -> 0 | L53: =IF(K53<>"",K53,I53) -> 0 | M53: =H53*L53 -> 0 | N53: =M53-G53 -> 0 | O53: =IF(F53>0,L53/F53-1,"") | P53: Без изменений
A54: 2. Кондиционирование | B54: 2.15 | C54: Рехао тройник 63*8,7/32*4,4/63*8,7 | D54: шт. | E54: 136 | F54: 798 | G54: =E54*F54 -> 108528 | H54: 136 | I54: 798 | J54: =H54*I54 -> 108528 | L54: =IF(K54<>"",K54,I54) -> 798 | M54: =H54*L54 -> 108528 | N54: =M54-G54 -> 0 | O54: =IF(F54>0,L54/F54-1,"") -> 0 | P54: Без изменений
A55: 2. Кондиционирование | B55: 2.16 | C55: Рехао тройник 32*4,4/25*3,5/32*4,4 | D55: шт. | E55: 288 | F55: 798 | G55: =E55*F55 -> 229824 | H55: 288 | I55: 798 | J55: =H55*I55 -> 229824 | L55: =IF(K55<>"",K55,I55) -> 798 | M55: =H55*L55 -> 229824 | N55: =M55-G55 -> 0 | O55: =IF(F55>0,L55/F55-1,"") -> 0 | P55: Без изменений
A56: 2. Кондиционирование | B56: 2.17 | C56: Рехао Переходник 32*4,4 -25*3,5 | D56: шт. | E56: 216 | F56: 798 | G56: =E56*F56 -> 172368 | H56: 216 | I56: 798 | J56: =H56*I56 -> 172368 | L56: =IF(K56<>"",K56,I56) -> 798 | M56: =H56*L56 -> 172368 | N56: =M56-G56 -> 0 | O56: =IF(F56>0,L56/F56-1,"") -> 0 | P56: Без изменений
A57: 2. Кондиционирование | B57: 2.18 | C57: Отвод 90 25*3,5 | D57: шт. | E57: 272 | F57: 798 | G57: =E57*F57 -> 217056 | H57: 272 | I57: 798 | J57: =H57*I57 -> 217056 | L57: =IF(K57<>"",K57,I57) -> 798 | M57: =H57*L57 -> 217056 | N57: =M57-G57 -> 0 | O57: =IF(F57>0,L57/F57-1,"") -> 0 | P57: Без изменений
A58: 2. Кондиционирование | B58: 2.19 | C58: Отвод 90 32*4,4 | D58: шт. | E58: 96 | F58: 798 | G58: =E58*F58 -> 76608 | H58: 96 | I58: 798 | J58: =H58*I58 -> 76608 | L58: =IF(K58<>"",K58,I58) -> 798 | M58: =H58*L58 -> 76608 | N58: =M58-G58 -> 0 | O58: =IF(F58>0,L58/F58-1,"") -> 0 | P58: Без изменений
A59: 2. Кондиционирование | B59: 2.20 | C59: Полуотвод 45 63*8,7 | D59: шт. | E59: 8 | F59: 798 | G59: =E59*F59 -> 6384 | H59: 8 | I59: 798 | J59: =H59*I59 -> 6384 | L59: =IF(K59<>"",K59,I59) -> 798 | M59: =H59*L59 -> 6384 | N59: =M59-G59 -> 0 | O59: =IF(F59>0,L59/F59-1,"") -> 0 | P59: Без изменений
A60: 2. Кондиционирование | B60: 2.21 | C60: Переход 63*4,4/ 50*6,9 | D60: шт. | E60: 24 | F60: 798 | G60: =E60*F60 -> 19152 | H60: 24 | I60: 798 | J60: =H60*I60 -> 19152 | L60: =IF(K60<>"",K60,I60) -> 798 | M60: =H60*L60 -> 19152 | N60: =M60-G60 -> 0 | O60: =IF(F60>0,L60/F60-1,"") -> 0 | P60: Без изменений
A61: 2. Кондиционирование | B61: 2.22 | C61: Рехао Тройник 50*6,9/32*4,4/50*6,9 | D61: шт. | E61: 48 | F61: 798 | G61: =E61*F61 -> 38304 | H61: 48 | I61: 798 | J61: =H61*I61 -> 38304 | L61: =IF(K61<>"",K61,I61) -> 798 | M61: =H61*L61 -> 38304 | N61: =M61-G61 -> 0 | O61: =IF(F61>0,L61/F61-1,"") -> 0 | P61: Без изменений
A62: 2. Кондиционирование | B62: 2.23 | C62: Переход 50*6,9 / 40*5,5 | D62: шт. | E62: 16 | F62: 798 | G62: =E62*F62 -> 12768 | H62: 16 | I62: 798 | J62: =H62*I62 -> 12768 | L62: =IF(K62<>"",K62,I62) -> 798 | M62: =H62*L62 -> 12768 | N62: =M62-G62 -> 0 | O62: =IF(F62>0,L62/F62-1,"") -> 0 | P62: Без изменений
A63: 2. Кондиционирование | B63: 2.24 | C63: Рехао тройник 40*5,5/32*4,4/40*5,5 | D63: шт. | E63: 32 | F63: 798 | G63: =E63*F63 -> 25536 | H63: 32 | I63: 798 | J63: =H63*I63 -> 25536 | L63: =IF(K63<>"",K63,I63) -> 798 | M63: =H63*L63 -> 25536 | N63: =M63-G63 -> 0 | O63: =IF(F63>0,L63/F63-1,"") -> 0 | P63: Без изменений
A64: 2. Кондиционирование | B64: 2.25 | C64: полуотвод 25*3,5 | D64: шт. | E64: 40 | F64: 798 | G64: =E64*F64 -> 31920 | H64: 40 | I64: 798 | J64: =H64*I64 -> 31920 | L64: =IF(K64<>"",K64,I64) -> 798 | M64: =H64*L64 -> 31920 | N64: =M64-G64 -> 0 | O64: =IF(F64>0,L64/F64-1,"") -> 0 | P64: Без изменений
A65: 2. Кондиционирование | B65: 2.26 | C65: полуотвод 32*4,4 | D65: шт. | E65: 24 | F65: 798 | G65: =E65*F65 -> 19152 | H65: 24 | I65: 798 | J65: =H65*I65 -> 19152 | L65: =IF(K65<>"",K65,I65) -> 798 | M65: =H65*L65 -> 19152 | N65: =M65-G65 -> 0 | O65: =IF(F65>0,L65/F65-1,"") -> 0 | P65: Без изменений
... A75: 2. Кондиционирование | B75: 2.36 | C75: Проделка отверстий | D75: шт. | E75: 128 | F75: 285 | G75: =E75*F75 -> 36480 | H75: 128 | I75: 285 | J75: =H75*I75 -> 36480 | L75: =IF(K75<>"",K75,I75) -> 285 | M75: =H75*L75 -> 36480 | N75: =M75-G75 -> 0 | O75: =IF(F75>0,L75/F75-1,"") -> 0 | P75: Без изменений
A76: 2. Кондиционирование | B76: 2.37 | C76: Тепловая изоляция из вспененного каучука, толщиной 9 мм Armaflex АСЕ 28*13 | D76: м.п. | E76: 1280 | F76: 200 | G76: =E76*F76 -> 256000 | H76: 1280 | I76: 200 | J76: =H76*I76 -> 256000 | K76: 150 | L76: =IF(K76<>"",K76,I76) -> 150 | M76: =H76*L76 -> 192000 | N76: =M76-G76 -> -64000 | O76: =IF(F76>0,L76/F76-1,"") -> -0.25 | P76: Снижение согласовано, но не внесено в итог | Q76: по договору | R76: Цена Согласована Марк
A77: 2. Кондиционирование | B77: 2.38 | C77: Тепловая изоляция из вспененного каучука, толщиной 9 мм Armaflex АСЕ 35*13 | D77: м.п. | E77: 800 | F77: 200 | G77: =E77*F77 -> 160000 | H77: 800 | I77: 200 | J77: =H77*I77 -> 160000 | K77: 150 | L77: =IF(K77<>"",K77,I77) -> 150 | M77: =H77*L77 -> 120000 | N77: =M77-G77 -> -40000 | O77: =IF(F77>0,L77/F77-1,"") -> -0.25 | P77: Снижение согласовано, но не внесено в итог | Q77: по договору | R77: Цена Согласована Марк
A78: 2. Кондиционирование | B78: 2.39 | C78: Тепловая изоляция из вспененного каучука, толщиной 9 мм Armaflex АСЕ 42*13 | D78: м.п. | E78: 200 | F78: 228 | G78: =E78*F78 -> 45600 | H78: 200 | I78: 228 | J78: =H78*I78 -> 45600 | L78: =IF(K78<>"",K78,I78) -> 228 | M78: =H78*L78 -> 45600 | N78: =M78-G78 -> 0 | O78: =IF(F78>0,L78/F78-1,"") -> 0 | P78: Без изменений
A79: 2. Кондиционирование | B79: 2.40 | C79: Тепловая изоляция из вспененного каучука, толщиной 13 мм Armaflex АСЕ 50*13 | E79: 240 | F79: 228 | G79: =E79*F79 -> 54720 | H79: 240 | I79: 228 | J79: =H79*I79 -> 54720 | L79: =IF(K79<>"",K79,I79) -> 228 | M79: =H79*L79 -> 54720 | N79: =M79-G79 -> 0 | O79: =IF(F79>0,L79/F79-1,"") -> 0 | P79: Без изменений
A80: 2. Кондиционирование | B80: 2.41 | C80: Тепловая изоляция из вспененного каучука, толщиной 13 мм Armaflex АСЕ 63*13 | D80: м.п. | E80: 640 | F80: 150 | G80: =E80*F80 -> 96000 | H80: 640 | I80: 150 | J80: =H80*I80 -> 96000 | L80: =IF(K80<>"",K80,I80) -> 150 | M80: =H80*L80 -> 96000 | N80: =M80-G80 -> 0 | O80: =IF(F80>0,L80/F80-1,"") -> 0 | P80: Без изменений
A81: 2. Кондиционирование | B81: 2.42 | C81: ПНР 3-10 эт | D81: Компл. | E81: 4 | F81: 120000 | G81: =E81*F81 -> 480000 | H81: 4 | I81: 120000 | J81: =H81*I81 -> 480000 | L81: =IF(K81<>"",K81,I81) -> 120000 | M81: =H81*L81 -> 480000 | N81: =M81-G81 -> 0 | O81: =IF(F81>0,L81/F81-1,"") -> 0 | P81: Без изменений
B82: 3. Дополнительные работы 3,7,8,9 этаж
A83: 3. Дополнительные работы 3,7,8,9 этаж | B83: 3.1 | C83: Тройник ф 250 | D83: шт. | E83: 2 | F83: 630 | G83: =E83*F83 -> 1260 | H83: 2 | I83: 630 | J83: =H83*I83 -> 1260 | L83: =IF(K83<>"",K83,I83) -> 630 | M83: =H83*L83 -> 1260 | N83: =M83-G83 -> 0 | O83: =IF(F83>0,L83/F83-1,"") -> 0 | P83: Без изменений
A84: 3. Дополнительные работы 3,7,8,9 этаж | B84: 3.2 | C84: Отвод 45 ф 250 | D84: шт. | E84: 6 | F84: 630 | G84: =E84*F84 -> 3780 | H84: 6 | I84: 630 | J84: =H84*I84 -> 3780 | L84: =IF(K84<>"",K84,I84) -> 630 | M84: =H84*L84 -> 3780 | N84: =M84-G84 -> 0 | O84: =IF(F84>0,L84/F84-1,"") -> 0 | P84: Без изменений
A85: 3. Дополнительные работы 3,7,8,9 этаж | B85: 3.3 | C85: Врезка седлообразная ф160\160 | D85: шт. | E85: 47 | F85: 630 | G85: =E85*F85 -> 29610 | H85: 47 | I85: 630 | J85: =H85*I85 -> 29610 | L85: =IF(K85<>"",K85,I85) -> 630 | M85: =H85*L85 -> 29610 | N85: =M85-G85 -> 0 | O85: =IF(F85>0,L85/F85-1,"") -> 0 | P85: Без изменений
A86: 3. Дополнительные работы 3,7,8,9 этаж | B86: 3.4 | C86: Врезка седлообразная ф160\200 | D86: шт. | E86: 31 | F86: 630 | G86: =E86*F86 -> 19530 | H86: 31 | I86: 630 | J86: =H86*I86 -> 19530 | L86: =IF(K86<>"",K86,I86) -> 630 | M86: =H86*L86 -> 19530 | N86: =M86-G86 -> 0 | O86: =IF(F86>0,L86/F86-1,"") -> 0 | P86: Без изменений
A87: 3. Дополнительные работы 3,7,8,9 этаж | B87: 3.5 | C87: Врезка седлообразная ф200\200 | D87: шт. | E87: 29 | F87: 630 | G87: =E87*F87 -> 18270 | H87: 29 | I87: 630 | J87: =H87*I87 -> 18270 | L87: =IF(K87<>"",K87,I87) -> 630 | M87: =H87*L87 -> 18270 | N87: =M87-G87 -> 0 | O87: =IF(F87>0,L87/F87-1,"") -> 0 | P87: Без изменений
A88: 3. Дополнительные работы 3,7,8,9 этаж | B88: 3.6 | C88: Врезка прямая ф100 | D88: шт. | E88: 14 | F88: 630 | G88: =E88*F88 -> 8820 | H88: 14 | I88: 630 | J88: =H88*I88 -> 8820 | L88: =IF(K88<>"",K88,I88) -> 630 | M88: =H88*L88 -> 8820 | N88: =M88-G88 -> 0 | O88: =IF(F88>0,L88/F88-1,"") -> 0 | P88: Без изменений
A89: 3. Дополнительные работы 3,7,8,9 этаж | B89: 3.7 | C89: Изоляция изделий (отводы, тройники, переходы, клапана) | D89: шт. | E89: 1195 | F89: 840 | G89: =E89*F89 -> 1003800 | H89: 1195 | I89: 570 | J89: =H89*I89 -> 681150 | L89: =IF(K89<>"",K89,I89) -> 570 | M89: =H89*L89 -> 681150 | N89: =M89-G89 -> -322650 | O89: =IF(F89>0,L89/F89-1,"") -> -0.32142857 | P89: Цена снижена
A90: 3. Дополнительные работы 3,7,8,9 этаж | B90: 3.8 | C90: Ниппель ф160 | D90: шт. | E90: 27 | F90: 630 | G90: =E90*F90 -> 17010 | H90: 27 | I90: 630 | J90: =H90*I90 -> 17010 | L90: =IF(K90<>"",K90,I90) -> 630 | M90: =H90*L90 -> 17010 | N90: =M90-G90 -> 0 | O90: =IF(F90>0,L90/F90-1,"") -> 0 | P90: Без изменений
A91: 3. Дополнительные работы 3,7,8,9 этаж | B91: 3.9 | C91: Монтаж пожарного клапана | D91: к-т | E91: 4 | F91: 21000 | G91: =E91*F91 -> 84000 | H91: 2 | I91: 2900 | J91: =H91*I91 -> 5800 | L91: =IF(K91<>"",K91,I91) -> 2900 | M91: =H91*L91 -> 5800 | N91: =M91-G91 -> -78200 | O91: =IF(F91>0,L91/F91-1,"") -> -0.86190476 | P91: Снижены цена и количество | Q91: сильно завышена расценка
A92: 3. Дополнительные работы 3,7,8,9 этаж | B92: 3.10 | C92: Обрезка вытяжных воздуховодов | D92: шт | E92: 64 | F92: 1120 | G92: =E92*F92 -> 71680 | H92: 64 | I92: 1120 | J92: =H92*I92 -> 71680 | L92: =IF(K92<>"",K92,I92) -> 1120 | M92: =H92*L92 -> 71680 | N92: =M92-G92 -> 0 | O92: =IF(F92>0,L92/F92-1,"") -> 0 | P92: Без изменений
A93: 3. Дополнительные работы 3,7,8,9 этаж | B93: 3.11 | C93: Демонтаж вытяжки 400*200 | D93: мп | E93: 34.4 | F93: 840 | G93: =E93*F93 -> 28896 | H93: 34.4 | I93: 840 | J93: =H93*I93 -> 28896 | L93: =IF(K93<>"",K93,I93) -> 840 | M93: =H93*L93 -> 28896 | N93: =M93-G93 -> 0 | O93: =IF(F93>0,L93/F93-1,"") -> 0 | P93: Без изменений
A94: 3. Дополнительные работы 3,7,8,9 этаж | B94: 3.12 | C94: Демонтаж вытяжки ф200 | D94: мп | E94: 32.8 | F94: 700 | G94: =E94*F94 -> 22960 | H94: 32.8 | I94: 700 | J94: =H94*I94 -> 22960 | L94: =IF(K94<>"",K94,I94) -> 700 | M94: =H94*L94 -> 22960 | N94: =M94-G94 -> 0 | O94: =IF(F94>0,L94/F94-1,"") -> 0 | P94: Без изменений
A95: 3. Дополнительные работы 3,7,8,9 этаж | B95: 3.13 | C95: Перемонтаж щелевых диффузоров | D95: к-т | E95: 8 | F95: 16800 | G95: =E95*F95 -> 134400 | H95: 8 | I95: 4800 | J95: =H95*I95 -> 38400 | L95: =IF(K95<>"",K95,I95) -> 4800 | M95: =H95*L95 -> 38400 | N95: =M95-G95 -> -96000 | O95: =IF(F95>0,L95/F95-1,"") -> -0.71428571 | P95: Цена снижена | Q95: сильно завышено, что за диффузоры? С КСД? Размер? | R95: Демонтаж - монтаж щелевого диффузора. Поставь цену сама
A96: 3. Дополнительные работы 3,7,8,9 этаж | B96: 3.14 | C96: Перемонтаж вентканалов | D96: мп | E96: 61.6 | F96: 1120 | G96: =E96*F96 -> 68992 | H96: 61.6 | I96: 920 | J96: =H96*I96 -> 56672 | L96: =IF(K96<>"",K96,I96) -> 920 | M96: =H96*L96 -> 56672 | N96: =M96-G96 -> -12320 | O96: =IF(F96>0,L96/F96-1,"") -> -0.17857143 | P96: Цена снижена | Q96: Какие размеры? | R96: Цена Согласована Марк
A97: 3. Дополнительные работы 3,7,8,9 этаж | B97: 3.15 | C97: Демонтаж диффузора, монтаж гибкой подводки | D97: к-т | E97: 6 | F97: 4200 | G97: =E97*F97 -> 25200 | H97: 6 | I97: 1500 | J97: =H97*I97 -> 9000 | L97: =IF(K97<>"",K97,I97) -> 1500 | M97: =H97*L97 -> 9000 | N97: =M97-G97 -> -16200 | O97: =IF(F97>0,L97/F97-1,"") -> -0.64285714 | P97: Цена снижена | Q97: Расписать какой диффузор, какая гибкая подводка? | R97: демонтаж существующего диффузора, монтаж гибкой подводки временно, после зашивке ГКЛ будет монтаж данного диффузора в ГКЛ; Наименование изменено на: «Демонтаж диффузора, монтаж гибкой подводки, монтаж диффузора в гкл»
A98: 3. Дополнительные работы 3,7,8,9 этаж | B98: 3.16 | C98: Перемонтаж вентканалов (пересечение с АУПТ) | D98: к-т | E98: 2 | F98: 7000 | G98: =E98*F98 -> 14000 | H98: 2 | I98: 7000 | J98: =H98*I98 -> 14000 | L98: =IF(K98<>"",K98,I98) -> 7000 | M98: =H98*L98 -> 14000 | N98: =M98-G98 -> 0 | O98: =IF(F98>0,L98/F98-1,"") -> 0 | P98: Без изменений | Q98: расписать что за работа? | R98: Переделка согласованной трассы из-за изменений по системе АПТ.
A99: 3. Дополнительные работы 3,7,8,9 этаж | B99: 3.17 | C99: Демонтаж труб пожаротушения (сплинклер) | D99: мп | E99: 120 | F99: 700 | G99: =E99*F99 -> 84000 | H99: 120 | I99: 700 | J99: =H99*I99 -> 84000 | L99: =IF(K99<>"",K99,I99) -> 700 | M99: =H99*L99 -> 84000 | N99: =M99-G99 -> 0 | O99: =IF(F99>0,L99/F99-1,"") -> 0 | P99: Без изменений | Q99: какая труба? | R99: разные диаметры, 32, 40, 25, 20
A100: 3. Дополнительные работы 3,7,8,9 этаж | B100: 3.18 | C100: Устройство проходок (изоляция) | D100: шт | E100: 64 | F100: 420 | G100: =E100*F100 -> 26880 | H100: 64 | I100: 420 | J100: =H100*I100 -> 26880 | L100: =IF(K100<>"",K100,I100) -> 420 | M100: =H100*L100 -> 26880 | N100: =M100-G100 -> 0 | O100: =IF(F100>0,L100/F100-1,"") -> 0 | P100: Без изменений | Q100: Где проходка? Что изолируется? | R100: Воздуховоды, которые без изоляции, в местах проходок через стену изолируются
A101: 3. Дополнительные работы 3,7,8,9 этаж | B101: 3.19 | C101: Демонтаж короба щелевой решетки | D101: шт | E101: 8 | F101: 4200 | G101: =E101*F101 -> 33600 | H101: 8 | I101: 2400 | J101: =H101*I101 -> 19200 | L101: =IF(K101<>"",K101,I101) -> 2400 | M101: =H101*L101 -> 19200 | N101: =M101-G101 -> -14400 | O101: =IF(F101>0,L101/F101-1,"") -> -0.42857143 | P101: Цена снижена | Q101: непонятно что за работа, расписать | R101: щелевой диффузор достать из металлической плитки армстронга.
A102: 3. Дополнительные работы 3,7,8,9 этаж | B102: 3.20 | C102: соединитель 63 | D102: шт. | E102: 40 | F102: 588 | G102: =E102*F102 -> 23520 | H102: 40 | I102: 588 | J102: =H102*I102 -> 23520 | L102: =IF(K102<>"",K102,I102) -> 588 | M102: =H102*L102 -> 23520 | N102: =M102-G102 -> 0 | O102: =IF(F102>0,L102/F102-1,"") -> 0 | P102: Без изменений
A103: 3. Дополнительные работы 3,7,8,9 этаж | B103: 3.21 | C103: соединитель 50 | D103: шт. | E103: 40 | F103: 588 | G103: =E103*F103 -> 23520 | H103: 40 | I103: 588 | J103: =H103*I103 -> 23520 | L103: =IF(K103<>"",K103,I103) -> 588 | M103: =H103*L103 -> 23520 | N103: =M103-G103 -> 0 | O103: =IF(F103>0,L103/F103-1,"") -> 0 | P103: Без изменений
A104: 3. Дополнительные работы 3,7,8,9 этаж | B104: 3.22 | C104: соединитель 40 | D104: шт. | E104: 24 | F104: 588 | G104: =E104*F104 -> 14112 | H104: 24 | I104: 588 | J104: =H104*I104 -> 14112 | L104: =IF(K104<>"",K104,I104) -> 588 | M104: =H104*L104 -> 14112 | N104: =M104-G104 -> 0 | O104: =IF(F104>0,L104/F104-1,"") -> 0 | P104: Без изменений
A105: 3. Дополнительные работы 3,7,8,9 этаж | B105: 3.23 | C105: соединитель 32 | D105: шт. | E105: 56 | F105: 588 | G105: =E105*F105 -> 32928 | H105: 56 | I105: 588 | J105: =H105*I105 -> 32928 | L105: =IF(K105<>"",K105,I105) -> 588 | M105: =H105*L105 -> 32928 | N105: =M105-G105 -> 0 | O105: =IF(F105>0,L105/F105-1,"") -> 0 | P105: Без изменений
A106: 3. Дополнительные работы 3,7,8,9 этаж | B106: 3.24 | C106: соединитель 25 | D106: шт. | E106: 8 | F106: 588 | G106: =E106*F106 -> 4704 | H106: 8 | I106: 588 | J106: =H106*I106 -> 4704 | L106: =IF(K106<>"",K106,I106) -> 588 | M106: =H106*L106 -> 4704 | N106: =M106-G106 -> 0 | O106: =IF(F106>0,L106/F106-1,"") -> 0 | P106: Без изменений
A107: 3. Дополнительные работы 3,7,8,9 этаж | B107: 3.25 | C107: тройник 63*63*63 | D107: шт. | E107: 8 | F107: 588 | G107: =E107*F107 -> 4704 | H107: 8 | I107: 588 | J107: =H107*I107 -> 4704 | L107: =IF(K107<>"",K107,I107) -> 588 | M107: =H107*L107 -> 4704 | N107: =M107-G107 -> 0 | O107: =IF(F107>0,L107/F107-1,"") -> 0 | P107: Без изменений
A108: 3. Дополнительные работы 3,7,8,9 этаж | B108: 3.26 | C108: тройник 32*32*32 | D108: шт. | E108: 8 | F108: 588 | G108: =E108*F108 -> 4704 | H108: 8 | I108: 588 | J108: =H108*I108 -> 4704 | L108: =IF(K108<>"",K108,I108) -> 588 | M108: =H108*L108 -> 4704 | N108: =M108-G108 -> 0 | O108: =IF(F108>0,L108/F108-1,"") -> 0 | P108: Без изменений
A109: 3. Дополнительные работы 3,7,8,9 этаж | B109: 3.27 | C109: подключение к вводу | D109: к-т | E109: 16 | F109: 2100 | G109: =E109*F109 -> 33600 | H109: 16 | I109: 2100 | J109: =H109*I109 -> 33600 | L109: =IF(K109<>"",K109,I109) -> 2100 | M109: =H109*L109 -> 33600 | N109: =M109-G109 -> 0 | O109: =IF(F109>0,L109/F109-1,"") -> 0 | P109: Без изменений | Q109: что за подключение? Непонятно | R109: боченок, американка, переход с аксиального на резьбовой фитинг, демонтаж заглушек, слив остатков, удаление инородных включенийс резьб
...
